__init__.pyc (Python 3.11)
[Code]
    File Name: output/Live/mac_universal_64_static/Release/python-bundle/MIDI Remote Scripts/ableton/v2/control_surface/elements/__init__.py
    Object Name: <module>
    Qualified Name: <module>
    Arg Count: 0
    Pos Only Arg Count: 0
    KW Only Arg Count: 0
    Stack Size: 2
    Flags: 0x00000000
    [Names]
        'button'
        'ButtonElement'
        'ButtonElementMixin'
        'DummyUndoStepHandler'
        'button_matrix'
        'ButtonMatrixElement'
        'button_slider'
        'ButtonSliderElement'
        'color'
        'AnimatedColor'
        'Color'
        'DynamicColorBase'
        'SelectedClipColorFactory'
        'SelectedTrackColor'
        'SelectedTrackColorFactory'
        'SysexRGBColor'
        'to_midi_value'
        'combo'
        'ComboElement'
        'DoublePressContext'
        'DoublePressElement'
        'EventElement'
        'MultiElement'
        'ToggleElement'
        'WrapperElement'
        'display_data_source'
        'DisplayDataSource'
        'adjust_string'
        'adjust_string_crop'
        'encoder'
        'EncoderElement'
        'FineGrainWithModifierEncoderElement'
        'TouchEncoderElement'
        'TouchEncoderElementBase'
        'full_velocity_element'
        'FullVelocityElement'
        'NullFullVelocity'
        'logical_display_segment'
        'LogicalDisplaySegment'
        'optional'
        'ChoosingElement'
        'OptionalElement'
        'physical_display'
        'DisplayElement'
        'DisplayError'
        'DisplaySegmentationError'
        'PhysicalDisplayElement'
        'SubDisplayElement'
        'playhead_element'
        'NullPlayhead'
        'PlayheadElement'
        'proxy_element'
        'ProxyElement'
        'slider'
        'SliderElement'
        'sysex_element'
        'ColorSysexElement'
        'SysexElement'
        'velocity_levels_element'
        'NullVelocityLevels'
        'VelocityLevelsElement'
        '__all__'
    [Locals+Names]
    [Constants]
        1
        (
            'ButtonElement'
            'ButtonElementMixin'
            'DummyUndoStepHandler'
        )
        (
            'ButtonMatrixElement'
        )
        (
            'ButtonSliderElement'
        )
        (
            'AnimatedColor'
            'Color'
            'DynamicColorBase'
            'SelectedClipColorFactory'
            'SelectedTrackColor'
            'SelectedTrackColorFactory'
            'SysexRGBColor'
            'to_midi_value'
        )
        (
            'ComboElement'
            'DoublePressContext'
            'DoublePressElement'
            'EventElement'
            'MultiElement'
            'ToggleElement'
            'WrapperElement'
        )
        (
            'DisplayDataSource'
            'adjust_string'
            'adjust_string_crop'
        )
        (
            'EncoderElement'
            'FineGrainWithModifierEncoderElement'
            'TouchEncoderElement'
            'TouchEncoderElementBase'
        )
        (
            'FullVelocityElement'
            'NullFullVelocity'
        )
        (
            'LogicalDisplaySegment'
        )
        (
            'ChoosingElement'
            'OptionalElement'
        )
        (
            'DisplayElement'
            'DisplayError'
            'DisplaySegmentationError'
            'PhysicalDisplayElement'
            'SubDisplayElement'
        )
        (
            'NullPlayhead'
            'PlayheadElement'
        )
        (
            'ProxyElement'
        )
        (
            'SliderElement'
        )
        (
            'ColorSysexElement'
            'SysexElement'
        )
        (
            'NullVelocityLevels'
            'VelocityLevelsElement'
        )
        (
            'AnimatedColor'
            'ButtonElement'
            'ButtonElementMixin'
            'ButtonValue'
            'Color'
            'ColorSysexElement'
            'DummyUndoStepHandler'
            'DynamicColorBase'
            'OFF_VALUE'
            'ON_VALUE'
            'ButtonMatrixElement'
            'ButtonSliderElement'
            'ComboElement'
            'DoublePressContext'
            'DoublePressElement'
            'EventElement'
            'FullVelocityElement'
            'MultiElement'
            'ToggleElement'
            'WrapperElement'
            'adjust_string'
            'adjust_string_crop'
            'DisplayDataSource'
            'EncoderElement'
            'FineGrainWithModifierEncoderElement'
            'TouchEncoderElement'
            'TouchEncoderElementBase'
            'LogicalDisplaySegment'
            'ChoosingElement'
            'OptionalElement'
            'DisplayElement'
            'DisplayError'
            'DisplaySegmentationError'
            'NullFullVelocity'
            'NullPlayhead'
            'NullVelocityLevels'
            'PhysicalDisplayElement'
            'PlayheadElement'
            'ProxyElement'
            'SubDisplayElement'
            'SelectedTrackColor'
            'SelectedTrackColorFactory'
            'SelectedClipColorFactory'
            'SliderElement'
            'SysexElement'
            'SysexRGBColor'
            'to_midi_value'
            'VelocityLevelsElement'
        )
        None
    [Disassembly]
        0       RESUME                          0
        2       LOAD_CONST                      0: 1
        4       LOAD_CONST                      1: ('ButtonElement', 'ButtonElementMixin', 'DummyUndoStepHandler')
        6       IMPORT_NAME                     0: button
        8       IMPORT_FROM                     1: ButtonElement
        10      STORE_NAME                      1: ButtonElement
        12      IMPORT_FROM                     2: ButtonElementMixin
        14      STORE_NAME                      2: ButtonElementMixin
        16      IMPORT_FROM                     3: DummyUndoStepHandler
        18      STORE_NAME                      3: DummyUndoStepHandler
        20      POP_TOP                         
        22      LOAD_CONST                      0: 1
        24      LOAD_CONST                      2: ('ButtonMatrixElement',)
        26      IMPORT_NAME                     4: button_matrix
        28      IMPORT_FROM                     5: ButtonMatrixElement
        30      STORE_NAME                      5: ButtonMatrixElement
        32      POP_TOP                         
        34      LOAD_CONST                      0: 1
        36      LOAD_CONST                      3: ('ButtonSliderElement',)
        38      IMPORT_NAME                     6: button_slider
        40      IMPORT_FROM                     7: ButtonSliderElement
        42      STORE_NAME                      7: ButtonSliderElement
        44      POP_TOP                         
        46      LOAD_CONST                      0: 1
        48      LOAD_CONST                      4: ('AnimatedColor', 'Color', 'DynamicColorBase', 'SelectedClipColorFactory', 'SelectedTrackColor', 'SelectedTrackColorFactory', 'SysexRGBColor', 'to_midi_value')
        50      IMPORT_NAME                     8: color
        52      IMPORT_FROM                     9: AnimatedColor
        54      STORE_NAME                      9: AnimatedColor
        56      IMPORT_FROM                     10: Color
        58      STORE_NAME                      10: Color
        60      IMPORT_FROM                     11: DynamicColorBase
        62      STORE_NAME                      11: DynamicColorBase
        64      IMPORT_FROM                     12: SelectedClipColorFactory
        66      STORE_NAME                      12: SelectedClipColorFactory
        68      IMPORT_FROM                     13: SelectedTrackColor
        70      STORE_NAME                      13: SelectedTrackColor
        72      IMPORT_FROM                     14: SelectedTrackColorFactory
        74      STORE_NAME                      14: SelectedTrackColorFactory
        76      IMPORT_FROM                     15: SysexRGBColor
        78      STORE_NAME                      15: SysexRGBColor
        80      IMPORT_FROM                     16: to_midi_value
        82      STORE_NAME                      16: to_midi_value
        84      POP_TOP                         
        86      LOAD_CONST                      0: 1
        88      LOAD_CONST                      5: ('ComboElement', 'DoublePressContext', 'DoublePressElement', 'EventElement', 'MultiElement', 'ToggleElement', 'WrapperElement')
        90      IMPORT_NAME                     17: combo
        92      IMPORT_FROM                     18: ComboElement
        94      STORE_NAME                      18: ComboElement
        96      IMPORT_FROM                     19: DoublePressContext
        98      STORE_NAME                      19: DoublePressContext
        100     IMPORT_FROM                     20: DoublePressElement
        102     STORE_NAME                      20: DoublePressElement
        104     IMPORT_FROM                     21: EventElement
        106     STORE_NAME                      21: EventElement
        108     IMPORT_FROM                     22: MultiElement
        110     STORE_NAME                      22: MultiElement
        112     IMPORT_FROM                     23: ToggleElement
        114     STORE_NAME                      23: ToggleElement
        116     IMPORT_FROM                     24: WrapperElement
        118     STORE_NAME                      24: WrapperElement
        120     POP_TOP                         
        122     LOAD_CONST                      0: 1
        124     LOAD_CONST                      6: ('DisplayDataSource', 'adjust_string', 'adjust_string_crop')
        126     IMPORT_NAME                     25: display_data_source
        128     IMPORT_FROM                     26: DisplayDataSource
        130     STORE_NAME                      26: DisplayDataSource
        132     IMPORT_FROM                     27: adjust_string
        134     STORE_NAME                      27: adjust_string
        136     IMPORT_FROM                     28: adjust_string_crop
        138     STORE_NAME                      28: adjust_string_crop
        140     POP_TOP                         
        142     LOAD_CONST                      0: 1
        144     LOAD_CONST                      7: ('EncoderElement', 'FineGrainWithModifierEncoderElement', 'TouchEncoderElement', 'TouchEncoderElementBase')
        146     IMPORT_NAME                     29: encoder
        148     IMPORT_FROM                     30: EncoderElement
        150     STORE_NAME                      30: EncoderElement
        152     IMPORT_FROM                     31: FineGrainWithModifierEncoderElement
        154     STORE_NAME                      31: FineGrainWithModifierEncoderElement
        156     IMPORT_FROM                     32: TouchEncoderElement
        158     STORE_NAME                      32: TouchEncoderElement
        160     IMPORT_FROM                     33: TouchEncoderElementBase
        162     STORE_NAME                      33: TouchEncoderElementBase
        164     POP_TOP                         
        166     LOAD_CONST                      0: 1
        168     LOAD_CONST                      8: ('FullVelocityElement', 'NullFullVelocity')
        170     IMPORT_NAME                     34: full_velocity_element
        172     IMPORT_FROM                     35: FullVelocityElement
        174     STORE_NAME                      35: FullVelocityElement
        176     IMPORT_FROM                     36: NullFullVelocity
        178     STORE_NAME                      36: NullFullVelocity
        180     POP_TOP                         
        182     LOAD_CONST                      0: 1
        184     LOAD_CONST                      9: ('LogicalDisplaySegment',)
        186     IMPORT_NAME                     37: logical_display_segment
        188     IMPORT_FROM                     38: LogicalDisplaySegment
        190     STORE_NAME                      38: LogicalDisplaySegment
        192     POP_TOP                         
        194     LOAD_CONST                      0: 1
        196     LOAD_CONST                      10: ('ChoosingElement', 'OptionalElement')
        198     IMPORT_NAME                     39: optional
        200     IMPORT_FROM                     40: ChoosingElement
        202     STORE_NAME                      40: ChoosingElement
        204     IMPORT_FROM                     41: OptionalElement
        206     STORE_NAME                      41: OptionalElement
        208     POP_TOP                         
        210     LOAD_CONST                      0: 1
        212     LOAD_CONST                      11: ('DisplayElement', 'DisplayError', 'DisplaySegmentationError', 'PhysicalDisplayElement', 'SubDisplayElement')
        214     IMPORT_NAME                     42: physical_display
        216     IMPORT_FROM                     43: DisplayElement
        218     STORE_NAME                      43: DisplayElement
        220     IMPORT_FROM                     44: DisplayError
        222     STORE_NAME                      44: DisplayError
        224     IMPORT_FROM                     45: DisplaySegmentationError
        226     STORE_NAME                      45: DisplaySegmentationError
        228     IMPORT_FROM                     46: PhysicalDisplayElement
        230     STORE_NAME                      46: PhysicalDisplayElement
        232     IMPORT_FROM                     47: SubDisplayElement
        234     STORE_NAME                      47: SubDisplayElement
        236     POP_TOP                         
        238     LOAD_CONST                      0: 1
        240     LOAD_CONST                      12: ('NullPlayhead', 'PlayheadElement')
        242     IMPORT_NAME                     48: playhead_element
        244     IMPORT_FROM                     49: NullPlayhead
        246     STORE_NAME                      49: NullPlayhead
        248     IMPORT_FROM                     50: PlayheadElement
        250     STORE_NAME                      50: PlayheadElement
        252     POP_TOP                         
        254     LOAD_CONST                      0: 1
        256     LOAD_CONST                      13: ('ProxyElement',)
        258     IMPORT_NAME                     51: proxy_element
        260     IMPORT_FROM                     52: ProxyElement
        262     STORE_NAME                      52: ProxyElement
        264     POP_TOP                         
        266     LOAD_CONST                      0: 1
        268     LOAD_CONST                      14: ('SliderElement',)
        270     IMPORT_NAME                     53: slider
        272     IMPORT_FROM                     54: SliderElement
        274     STORE_NAME                      54: SliderElement
        276     POP_TOP                         
        278     LOAD_CONST                      0: 1
        280     LOAD_CONST                      15: ('ColorSysexElement', 'SysexElement')
        282     IMPORT_NAME                     55: sysex_element
        284     IMPORT_FROM                     56: ColorSysexElement
        286     STORE_NAME                      56: ColorSysexElement
        288     IMPORT_FROM                     57: SysexElement
        290     STORE_NAME                      57: SysexElement
        292     POP_TOP                         
        294     LOAD_CONST                      0: 1
        296     LOAD_CONST                      16: ('NullVelocityLevels', 'VelocityLevelsElement')
        298     IMPORT_NAME                     58: velocity_levels_element
        300     IMPORT_FROM                     59: NullVelocityLevels
        302     STORE_NAME                      59: NullVelocityLevels
        304     IMPORT_FROM                     60: VelocityLevelsElement
        306     STORE_NAME                      60: VelocityLevelsElement
        308     POP_TOP                         
        310     LOAD_CONST                      17: ('AnimatedColor', 'ButtonElement', 'ButtonElementMixin', 'ButtonValue', 'Color', 'ColorSysexElement', 'DummyUndoStepHandler', 'DynamicColorBase', 'OFF_VALUE', 'ON_VALUE', 'ButtonMatrixElement', 'ButtonSliderElement', 'ComboElement', 'DoublePressContext', 'DoublePressElement', 'EventElement', 'FullVelocityElement', 'MultiElement', 'ToggleElement', 'WrapperElement', 'adjust_string', 'adjust_string_crop', 'DisplayDataSource', 'EncoderElement', 'FineGrainWithModifierEncoderElement', 'TouchEncoderElement', 'TouchEncoderElementBase', 'LogicalDisplaySegment', 'ChoosingElement', 'OptionalElement', 'DisplayElement', 'DisplayError', 'DisplaySegmentationError', 'NullFullVelocity', 'NullPlayhead', 'NullVelocityLevels', 'PhysicalDisplayElement', 'PlayheadElement', 'ProxyElement', 'SubDisplayElement', 'SelectedTrackColor', 'SelectedTrackColorFactory', 'SelectedClipColorFactory', 'SliderElement', 'SysexElement', 'SysexRGBColor', 'to_midi_value', 'VelocityLevelsElement')
        312     STORE_NAME                      61: __all__
        314     LOAD_CONST                      18: None
        316     RETURN_VALUE                    
