button.pyc (Python 3.11)
[Code]
    File Name: output/Live/mac_universal_64_static/Release/python-bundle/MIDI Remote Scripts/ableton/v2/control_surface/elements/button.py
    Object Name: <module>
    Qualified Name: <module>
    Arg Count: 0
    Pos Only Arg Count: 0
    KW Only Arg Count: 0
    Stack Size: 6
    Flags: 0x00000000
    [Names]
        'past.builtins'
        'long'
        'Live'
        'base'
        'BooleanContext'
        'const'
        'has_event'
        'in_range'
        'listens'
        'old_hasattr'
        'input_control_element'
        'MIDI_CC_TYPE'
        'InputControlElement'
        'skin'
        'Skin'
        'color'
        'Color'
        'object'
        'DummyUndoStepHandler'
        'ButtonElementMixin'
        'ButtonElement'
    [Locals+Names]
    [Constants]
        0
        (
            'long'
        )
        None
        3
        (
            'BooleanContext'
            'const'
            'has_event'
            'in_range'
            'listens'
            'old_hasattr'
        )
        2
        (
            'MIDI_CC_TYPE'
            'InputControlElement'
        )
        (
            'Skin'
        )
        1
        (
            'Color'
        )
        [Code]
            File Name: output/Live/mac_universal_64_static/Release/python-bundle/MIDI Remote Scripts/ableton/v2/control_surface/elements/button.py
            Object Name: DummyUndoStepHandler
            Qualified Name: DummyUndoStepHandler
            Arg Count: 0
            Pos Only Arg Count: 0
            KW Only Arg Count: 0
            Stack Size: 1
            Flags: 0x00000000
            [Names]
                '__name__'
                '__module__'
                '__qualname__'
                'begin_undo_step'
                'end_undo_step'
            [Locals+Names]
            [Constants]
                'DummyUndoStepHandler'
                [Code]
                    File Name: output/Live/mac_universal_64_static/Release/python-bundle/MIDI Remote Scripts/ableton/v2/control_surface/elements/button.py
                    Object Name: begin_undo_step
                    Qualified Name: DummyUndoStepHandler.begin_undo_step
                    Arg Count: 1
                    Pos Only Arg Count: 0
                    KW Only Arg Count: 0
                    Stack Size: 1
                    Flags: 0x00000003 (CO_OPTIMIZED | CO_NEWLOCALS)
                    [Names]
                    [Locals+Names]
                        'self'
                    [Constants]
                        None
                    [Disassembly]
                        0       RESUME                          0
                        2       LOAD_CONST                      0: None
                        4       RETURN_VALUE                    
                [Code]
                    File Name: output/Live/mac_universal_64_static/Release/python-bundle/MIDI Remote Scripts/ableton/v2/control_surface/elements/button.py
                    Object Name: end_undo_step
                    Qualified Name: DummyUndoStepHandler.end_undo_step
                    Arg Count: 1
                    Pos Only Arg Count: 0
                    KW Only Arg Count: 0
                    Stack Size: 1
                    Flags: 0x00000003 (CO_OPTIMIZED | CO_NEWLOCALS)
                    [Names]
                    [Locals+Names]
                        'self'
                    [Constants]
                        None
                    [Disassembly]
                        0       RESUME                          0
                        2       LOAD_CONST                      0: None
                        4       RETURN_VALUE                    
                None
            [Disassembly]
                0       RESUME                          0
                2       LOAD_NAME                       0: __name__
                4       STORE_NAME                      1: __module__
                6       LOAD_CONST                      0: 'DummyUndoStepHandler'
                8       STORE_NAME                      2: __qualname__
                10      LOAD_CONST                      1: <CODE> begin_undo_step
                12      MAKE_FUNCTION                   0
                14      STORE_NAME                      3: begin_undo_step
                16      LOAD_CONST                      2: <CODE> end_undo_step
                18      MAKE_FUNCTION                   0
                20      STORE_NAME                      4: end_undo_step
                22      LOAD_CONST                      3: None
                24      RETURN_VALUE                    
        'DummyUndoStepHandler'
        [Code]
            File Name: output/Live/mac_universal_64_static/Release/python-bundle/MIDI Remote Scripts/ableton/v2/control_surface/elements/button.py
            Object Name: ButtonElementMixin
            Qualified Name: ButtonElementMixin
            Arg Count: 0
            Pos Only Arg Count: 0
            KW Only Arg Count: 0
            Stack Size: 1
            Flags: 0x00000000
            [Names]
                '__name__'
                '__module__'
                '__qualname__'
                'set_light'
            [Locals+Names]
            [Constants]
                'ButtonElementMixin'
                [Code]
                    File Name: output/Live/mac_universal_64_static/Release/python-bundle/MIDI Remote Scripts/ableton/v2/control_surface/elements/button.py
                    Object Name: set_light
                    Qualified Name: ButtonElementMixin.set_light
                    Arg Count: 2
                    Pos Only Arg Count: 0
                    KW Only Arg Count: 0
                    Stack Size: 1
                    Flags: 0x00000003 (CO_OPTIMIZED | CO_NEWLOCALS)
                    [Names]
                    [Locals+Names]
                        'self'
                        'value'
                    [Constants]
                        None
                    [Disassembly]
                        0       RESUME                          0
                        2       LOAD_CONST                      0: None
                        4       RETURN_VALUE                    
                None
            [Disassembly]
                0       RESUME                          0
                2       LOAD_NAME                       0: __name__
                4       STORE_NAME                      1: __module__
                6       LOAD_CONST                      0: 'ButtonElementMixin'
                8       STORE_NAME                      2: __qualname__
                10      NOP                             
                12      LOAD_CONST                      1: <CODE> set_light
                14      MAKE_FUNCTION                   0
                16      STORE_NAME                      3: set_light
                18      LOAD_CONST                      2: None
                20      RETURN_VALUE                    
        'ButtonElementMixin'
        [Code]
            File Name: output/Live/mac_universal_64_static/Release/python-bundle/MIDI Remote Scripts/ableton/v2/control_surface/elements/button.py
            Object Name: ButtonElement
            Qualified Name: ButtonElement
            Arg Count: 0
            Pos Only Arg Count: 0
            KW Only Arg Count: 0
            Stack Size: 6
            Flags: 0x00000000
            [Names]
                '__name__'
                '__module__'
                '__qualname__'
                'InputControlElement'
                'ProxiedInterface'
                'ButtonElementMixin'
                'Colors'
                'num_delayed_messages'
                'Skin'
                'DummyUndoStepHandler'
                '__init__'
                'reset'
                'is_momentary'
                'message_map_mode'
                'is_pressed'
                'set_light'
                '_set_skin_light'
                '_do_draw'
                'listens'
                '_ButtonElement__on_midi_value_changed'
                'send_value'
                'receive_value'
                'disconnect'
                '_disconnect_color_listener'
                '__classcell__'
            [Locals+Names]
                '__class__'
            [Constants]
                'ButtonElement'
                [Code]
                    File Name: output/Live/mac_universal_64_static/Release/python-bundle/MIDI Remote Scripts/ableton/v2/control_surface/elements/button.py
                    Object Name: ProxiedInterface
                    Qualified Name: ButtonElement.ProxiedInterface
                    Arg Count: 0
                    Pos Only Arg Count: 0
                    KW Only Arg Count: 0
                    Stack Size: 3
                    Flags: 0x00000000
                    [Names]
                        '__name__'
                        '__module__'
                        '__qualname__'
                        'const'
                        'is_momentary'
                        'is_pressed'
                    [Locals+Names]
                    [Constants]
                        'ButtonElement.ProxiedInterface'
                        True
                        False
                        None
                    [Disassembly]
                        0       RESUME                          0
                        2       LOAD_NAME                       0: __name__
                        4       STORE_NAME                      1: __module__
                        6       LOAD_CONST                      0: 'ButtonElement.ProxiedInterface'
                        8       STORE_NAME                      2: __qualname__
                        10      PUSH_NULL                       
                        12      LOAD_NAME                       3: const
                        14      LOAD_CONST                      1: True
                        16      PRECALL                         1
                        20      CALL                            1
                        30      STORE_NAME                      4: is_momentary
                        32      PUSH_NULL                       
                        34      LOAD_NAME                       3: const
                        36      LOAD_CONST                      2: False
                        38      PRECALL                         1
                        42      CALL                            1
                        52      STORE_NAME                      5: is_pressed
                        54      LOAD_CONST                      3: None
                        56      RETURN_VALUE                    
                'ProxiedInterface'
                [Code]
                    File Name: output/Live/mac_universal_64_static/Release/python-bundle/MIDI Remote Scripts/ableton/v2/control_surface/elements/button.py
                    Object Name: Colors
                    Qualified Name: ButtonElement.Colors
                    Arg Count: 0
                    Pos Only Arg Count: 0
                    KW Only Arg Count: 0
                    Stack Size: 4
                    Flags: 0x00000000
                    [Names]
                        '__name__'
                        '__module__'
                        '__qualname__'
                        'DefaultButton'
                    [Locals+Names]
                    [Constants]
                        'ButtonElement.Colors'
                        [Code]
                            File Name: output/Live/mac_universal_64_static/Release/python-bundle/MIDI Remote Scripts/ableton/v2/control_surface/elements/button.py
                            Object Name: DefaultButton
                            Qualified Name: ButtonElement.Colors.DefaultButton
                            Arg Count: 0
                            Pos Only Arg Count: 0
                            KW Only Arg Count: 0
                            Stack Size: 3
                            Flags: 0x00000000
                            [Names]
                                '__name__'
                                '__module__'
                                '__qualname__'
                                'Color'
                                'On'
                                'Off'
                                'Disabled'
                            [Locals+Names]
                            [Constants]
                                'ButtonElement.Colors.DefaultButton'
                                127
                                1
                                0
                                None
                            [Disassembly]
                                0       RESUME                          0
                                2       LOAD_NAME                       0: __name__
                                4       STORE_NAME                      1: __module__
                                6       LOAD_CONST                      0: 'ButtonElement.Colors.DefaultButton'
                                8       STORE_NAME                      2: __qualname__
                                10      PUSH_NULL                       
                                12      LOAD_NAME                       3: Color
                                14      LOAD_CONST                      1: 127
                                16      PRECALL                         1
                                20      CALL                            1
                                30      STORE_NAME                      4: On
                                32      PUSH_NULL                       
                                34      LOAD_NAME                       3: Color
                                36      LOAD_CONST                      2: 1
                                38      PRECALL                         1
                                42      CALL                            1
                                52      STORE_NAME                      5: Off
                                54      PUSH_NULL                       
                                56      LOAD_NAME                       3: Color
                                58      LOAD_CONST                      3: 0
                                60      PRECALL                         1
                                64      CALL                            1
                                74      STORE_NAME                      6: Disabled
                                76      LOAD_CONST                      4: None
                                78      RETURN_VALUE                    
                        'DefaultButton'
                        None
                    [Disassembly]
                        0       RESUME                          0
                        2       LOAD_NAME                       0: __name__
                        4       STORE_NAME                      1: __module__
                        6       LOAD_CONST                      0: 'ButtonElement.Colors'
                        8       STORE_NAME                      2: __qualname__
                        10      PUSH_NULL                       
                        12      LOAD_BUILD_CLASS                
                        14      LOAD_CONST                      1: <CODE> DefaultButton
                        16      MAKE_FUNCTION                   0
                        18      LOAD_CONST                      2: 'DefaultButton'
                        20      PRECALL                         2
                        24      CALL                            2
                        34      STORE_NAME                      3: DefaultButton
                        36      LOAD_CONST                      3: None
                        38      RETURN_VALUE                    
                'Colors'
                2
                False
                [Code]
                    File Name: output/Live/mac_universal_64_static/Release/python-bundle/MIDI Remote Scripts/ableton/v2/control_surface/elements/button.py
                    Object Name: __init__
                    Qualified Name: ButtonElement.__init__
                    Arg Count: 9
                    Pos Only Arg Count: 0
                    KW Only Arg Count: 0
                    Stack Size: 5
                    Flags: 0x0000000F (CO_OPTIMIZED | CO_NEWLOCALS | CO_VARARGS | CO_VARKEYWORDS)
                    [Names]
                        'super'
                        'ButtonElement'
                        '__init__'
                        'is_rgb'
                        'bool'
                        '_is_momentary'
                        '_last_received_value'
                        '_undo_step_handler'
                        '_skin'
                        'BooleanContext'
                        '_drawing_via_skin'
                    [Locals+Names]
                        'self'
                        'is_momentary'
                        'msg_type'
                        'channel'
                        'identifier'
                        'is_rgb'
                        'skin'
                        'undo_step_handler'
                        'send_should_depend_on_forwarding'
                        'a'
                        'k'
                        '__class__'
                    [Constants]
                        None
                        'send_should_depend_on_forwarding'
                        -1
                    [Disassembly]
                        0       COPY_FREE_VARS                  1
                        2       RESUME                          0
                        4       PUSH_NULL                       
                        6       LOAD_GLOBAL                     1: NULL + super
                        18      LOAD_GLOBAL                     2: ButtonElement
                        30      LOAD_FAST                       0: self
                        32      PRECALL                         2
                        36      CALL                            2
                        46      LOAD_ATTR                       2: __init__
                        56      LOAD_FAST                       2: msg_type
                        58      LOAD_FAST                       3: channel
                        60      LOAD_FAST                       4: identifier
                        62      BUILD_LIST                      3
                        64      LOAD_FAST                       9: a
                        66      LIST_EXTEND                     1
                        68      LIST_TO_TUPLE                   
                        70      LOAD_CONST                      1: 'send_should_depend_on_forwarding'
                        72      LOAD_FAST                       8: send_should_depend_on_forwarding
                        74      BUILD_MAP                       1
                        76      LOAD_FAST                       10: k
                        78      DICT_MERGE                      1
                        80      CALL_FUNCTION_EX                1
                        82      POP_TOP                         
                        84      LOAD_FAST                       5: is_rgb
                        86      LOAD_FAST                       0: self
                        88      STORE_ATTR                      3: is_rgb
                        98      LOAD_GLOBAL                     9: NULL + bool
                        110     LOAD_FAST                       1: is_momentary
                        112     PRECALL                         1
                        116     CALL                            1
                        126     LOAD_FAST                       0: self
                        128     STORE_ATTR                      5: _is_momentary
                        138     LOAD_CONST                      2: -1
                        140     LOAD_FAST                       0: self
                        142     STORE_ATTR                      6: _last_received_value
                        152     LOAD_FAST                       7: undo_step_handler
                        154     LOAD_FAST                       0: self
                        156     STORE_ATTR                      7: _undo_step_handler
                        166     LOAD_FAST                       6: skin
                        168     LOAD_FAST                       0: self
                        170     STORE_ATTR                      8: _skin
                        180     LOAD_GLOBAL                     19: NULL + BooleanContext
                        192     PRECALL                         0
                        196     CALL                            0
                        206     LOAD_FAST                       0: self
                        208     STORE_ATTR                      10: _drawing_via_skin
                        218     LOAD_CONST                      0: None
                        220     RETURN_VALUE                    
                [Code]
                    File Name: output/Live/mac_universal_64_static/Release/python-bundle/MIDI Remote Scripts/ableton/v2/control_surface/elements/button.py
                    Object Name: reset
                    Qualified Name: ButtonElement.reset
                    Arg Count: 1
                    Pos Only Arg Count: 0
                    KW Only Arg Count: 0
                    Stack Size: 3
                    Flags: 0x00000003 (CO_OPTIMIZED | CO_NEWLOCALS)
                    [Names]
                        'set_light'
                        'use_default_message'
                        'suppress_script_forwarding'
                    [Locals+Names]
                        'self'
                    [Constants]
                        None
                        'DefaultButton.Disabled'
                        False
                    [Disassembly]
                        0       RESUME                          0
                        2       LOAD_FAST                       0: self
                        4       LOAD_METHOD                     0: set_light
                        26      LOAD_CONST                      1: 'DefaultButton.Disabled'
                        28      PRECALL                         1
                        32      CALL                            1
                        42      POP_TOP                         
                        44      LOAD_FAST                       0: self
                        46      LOAD_METHOD                     1: use_default_message
                        68      PRECALL                         0
                        72      CALL                            0
                        82      POP_TOP                         
                        84      LOAD_CONST                      2: False
                        86      LOAD_FAST                       0: self
                        88      STORE_ATTR                      2: suppress_script_forwarding
                        98      LOAD_CONST                      0: None
                        100     RETURN_VALUE                    
                [Code]
                    File Name: output/Live/mac_universal_64_static/Release/python-bundle/MIDI Remote Scripts/ableton/v2/control_surface/elements/button.py
                    Object Name: is_momentary
                    Qualified Name: ButtonElement.is_momentary
                    Arg Count: 1
                    Pos Only Arg Count: 0
                    KW Only Arg Count: 0
                    Stack Size: 1
                    Flags: 0x00000003 (CO_OPTIMIZED | CO_NEWLOCALS)
                    [Names]
                        '_is_momentary'
                    [Locals+Names]
                        'self'
                    [Constants]
                        None
                    [Disassembly]
                        0       RESUME                          0
                        2       NOP                             
                        4       LOAD_FAST                       0: self
                        6       LOAD_ATTR                       0: _is_momentary
                        16      RETURN_VALUE                    
                [Code]
                    File Name: output/Live/mac_universal_64_static/Release/python-bundle/MIDI Remote Scripts/ableton/v2/control_surface/elements/button.py
                    Object Name: message_map_mode
                    Qualified Name: ButtonElement.message_map_mode
                    Arg Count: 1
                    Pos Only Arg Count: 0
                    KW Only Arg Count: 0
                    Stack Size: 1
                    Flags: 0x00000003 (CO_OPTIMIZED | CO_NEWLOCALS)
                    [Names]
                        'Live'
                        'MidiMap'
                        'MapMode'
                        'absolute'
                    [Locals+Names]
                        'self'
                    [Constants]
                        None
                    [Disassembly]
                        0       RESUME                          0
                        2       LOAD_GLOBAL                     0: Live
                        14      LOAD_ATTR                       1: MidiMap
                        24      LOAD_ATTR                       2: MapMode
                        34      LOAD_ATTR                       3: absolute
                        44      RETURN_VALUE                    
                [Code]
                    File Name: output/Live/mac_universal_64_static/Release/python-bundle/MIDI Remote Scripts/ableton/v2/control_surface/elements/button.py
                    Object Name: is_pressed
                    Qualified Name: ButtonElement.is_pressed
                    Arg Count: 1
                    Pos Only Arg Count: 0
                    KW Only Arg Count: 0
                    Stack Size: 3
                    Flags: 0x00000003 (CO_OPTIMIZED | CO_NEWLOCALS)
                    [Names]
                        '_is_momentary'
                        'int'
                        '_last_received_value'
                    [Locals+Names]
                        'self'
                    [Constants]
                        None
                        0
                    [Disassembly]
                        0       RESUME                          0
                        2       LOAD_FAST                       0: self
                        4       LOAD_ATTR                       0: _is_momentary
                        14      JUMP_IF_FALSE_OR_POP            23 (to 46)
                        16      LOAD_GLOBAL                     3: NULL + int
                        28      LOAD_FAST                       0: self
                        30      LOAD_ATTR                       2: _last_received_value
                        40      PRECALL                         1
                        44      CALL                            1
                        54      LOAD_CONST                      1: 0
                        56      COMPARE_OP                      4 (>)
                        62      RETURN_VALUE                    
                [Code]
                    File Name: output/Live/mac_universal_64_static/Release/python-bundle/MIDI Remote Scripts/ableton/v2/control_surface/elements/button.py
                    Object Name: set_light
                    Qualified Name: ButtonElement.set_light
                    Arg Count: 2
                    Pos Only Arg Count: 0
                    KW Only Arg Count: 0
                    Stack Size: 5
                    Flags: 0x00000003 (CO_OPTIMIZED | CO_NEWLOCALS)
                    [Names]
                        'old_hasattr'
                        'draw'
                        'type'
                        'int'
                        'long'
                        'in_range'
                        'send_value'
                        'isinstance'
                        'bool'
                        '_set_skin_light'
                    [Locals+Names]
                        'self'
                        'value'
                    [Constants]
                        None
                        'draw'
                        0
                        128
                        'DefaultButton.On'
                        'DefaultButton.Off'
                    [Disassembly]
                        0       RESUME                          0
                        2       LOAD_GLOBAL                     1: NULL + old_hasattr
                        14      LOAD_FAST                       1: value
                        16      LOAD_CONST                      1: 'draw'
                        18      PRECALL                         2
                        22      CALL                            2
                        32      POP_JUMP_FORWARD_IF_FALSE       23 (to 80)
                        34      LOAD_FAST                       1: value
                        36      LOAD_METHOD                     1: draw
                        58      LOAD_FAST                       0: self
                        60      PRECALL                         1
                        64      CALL                            1
                        74      POP_TOP                         
                        76      LOAD_CONST                      0: None
                        78      RETURN_VALUE                    
                        80      LOAD_GLOBAL                     5: NULL + type
                        92      LOAD_FAST                       1: value
                        94      PRECALL                         1
                        98      CALL                            1
                        108     LOAD_GLOBAL                     6: int
                        120     LOAD_GLOBAL                     8: long
                        132     BUILD_TUPLE                     2
                        134     CONTAINS_OP                     0 (in)
                        136     POP_JUMP_FORWARD_IF_FALSE       40 (to 218)
                        138     LOAD_GLOBAL                     11: NULL + in_range
                        150     LOAD_FAST                       1: value
                        152     LOAD_CONST                      2: 0
                        154     LOAD_CONST                      3: 128
                        156     PRECALL                         3
                        160     CALL                            3
                        170     POP_JUMP_FORWARD_IF_FALSE       23 (to 218)
                        172     LOAD_FAST                       0: self
                        174     LOAD_METHOD                     6: send_value
                        196     LOAD_FAST                       1: value
                        198     PRECALL                         1
                        202     CALL                            1
                        212     POP_TOP                         
                        214     LOAD_CONST                      0: None
                        216     RETURN_VALUE                    
                        218     LOAD_GLOBAL                     15: NULL + isinstance
                        230     LOAD_FAST                       1: value
                        232     LOAD_GLOBAL                     16: bool
                        244     PRECALL                         2
                        248     CALL                            2
                        258     POP_JUMP_FORWARD_IF_FALSE       27 (to 314)
                        260     LOAD_FAST                       0: self
                        262     LOAD_METHOD                     9: _set_skin_light
                        284     LOAD_FAST                       1: value
                        286     POP_JUMP_FORWARD_IF_FALSE       2 (to 292)
                        288     LOAD_CONST                      4: 'DefaultButton.On'
                        290     JUMP_FORWARD                    1 (to 294)
                        292     LOAD_CONST                      5: 'DefaultButton.Off'
                        294     PRECALL                         1
                        298     CALL                            1
                        308     POP_TOP                         
                        310     LOAD_CONST                      0: None
                        312     RETURN_VALUE                    
                        314     LOAD_FAST                       0: self
                        316     LOAD_METHOD                     9: _set_skin_light
                        338     LOAD_FAST                       1: value
                        340     PRECALL                         1
                        344     CALL                            1
                        354     POP_TOP                         
                        356     LOAD_CONST                      0: None
                        358     RETURN_VALUE                    
                [Code]
                    File Name: output/Live/mac_universal_64_static/Release/python-bundle/MIDI Remote Scripts/ableton/v2/control_surface/elements/button.py
                    Object Name: _set_skin_light
                    Qualified Name: ButtonElement._set_skin_light
                    Arg Count: 2
                    Pos Only Arg Count: 0
                    KW Only Arg Count: 0
                    Stack Size: 6
                    Flags: 0x00000003 (CO_OPTIMIZED | CO_NEWLOCALS)
                    [Names]
                        '_skin'
                        '_do_draw'
                        'has_event'
                        '_ButtonElement__on_midi_value_changed'
                        'subject'
                        '_disconnect_color_listener'
                    [Locals+Names]
                        'self'
                        'value'
                        'color'
                    [Constants]
                        None
                        'midi_value'
                    [Disassembly]
                        0       RESUME                          0
                        2       LOAD_CONST                      0: None
                        4       STORE_FAST                      2: color
                        6       NOP                             
                        8       LOAD_FAST                       0: self
                        10      LOAD_ATTR                       0: _skin
                        20      LOAD_FAST                       1: value
                        22      BINARY_SUBSCR                   
                        32      STORE_FAST                      2: color
                        34      LOAD_FAST                       0: self
                        36      LOAD_METHOD                     1: _do_draw
                        58      LOAD_FAST                       2: color
                        60      PRECALL                         1
                        64      CALL                            1
                        74      POP_TOP                         
                        76      LOAD_GLOBAL                     5: NULL + has_event
                        88      LOAD_FAST                       2: color
                        90      LOAD_CONST                      1: 'midi_value'
                        92      PRECALL                         2
                        96      CALL                            2
                        106     POP_JUMP_FORWARD_IF_FALSE       14 (to 136)
                        108     LOAD_FAST                       2: color
                        110     LOAD_FAST                       0: self
                        112     LOAD_ATTR                       3: _ButtonElement__on_midi_value_changed
                        122     STORE_ATTR                      4: subject
                        132     LOAD_CONST                      0: None
                        134     RETURN_VALUE                    
                        136     LOAD_FAST                       0: self
                        138     LOAD_METHOD                     5: _disconnect_color_listener
                        160     PRECALL                         0
                        164     CALL                            0
                        174     POP_TOP                         
                        176     LOAD_CONST                      0: None
                        178     RETURN_VALUE                    
                        180     PUSH_EXC_INFO                   
                        182     LOAD_GLOBAL                     5: NULL + has_event
                        194     LOAD_FAST                       2: color
                        196     LOAD_CONST                      1: 'midi_value'
                        198     PRECALL                         2
                        202     CALL                            2
                        212     POP_JUMP_FORWARD_IF_FALSE       13 (to 240)
                        214     LOAD_FAST                       2: color
                        216     LOAD_FAST                       0: self
                        218     LOAD_ATTR                       3: _ButtonElement__on_midi_value_changed
                        228     STORE_ATTR                      4: subject
                        238     RERAISE                         0
                        240     LOAD_FAST                       0: self
                        242     LOAD_METHOD                     5: _disconnect_color_listener
                        264     PRECALL                         0
                        268     CALL                            0
                        278     POP_TOP                         
                        280     RERAISE                         0
                        282     COPY                            3
                        284     POP_EXCEPT                      
                        286     RERAISE                         1
                [Code]
                    File Name: output/Live/mac_universal_64_static/Release/python-bundle/MIDI Remote Scripts/ableton/v2/control_surface/elements/button.py
                    Object Name: _do_draw
                    Qualified Name: ButtonElement._do_draw
                    Arg Count: 2
                    Pos Only Arg Count: 0
                    KW Only Arg Count: 0
                    Stack Size: 6
                    Flags: 0x00000003 (CO_OPTIMIZED | CO_NEWLOCALS)
                    [Names]
                        '_drawing_via_skin'
                        'draw'
                    [Locals+Names]
                        'self'
                        'color'
                    [Constants]
                        None
                    [Disassembly]
                        0       RESUME                          0
                        2       LOAD_FAST                       0: self
                        4       LOAD_METHOD                     0: _drawing_via_skin
                        26      PRECALL                         0
                        30      CALL                            0
                        40      BEFORE_WITH                     
                        42      POP_TOP                         
                        44      LOAD_FAST                       1: color
                        46      LOAD_METHOD                     1: draw
                        68      LOAD_FAST                       0: self
                        70      PRECALL                         1
                        74      CALL                            1
                        84      POP_TOP                         
                        86      LOAD_CONST                      0: None
                        88      LOAD_CONST                      0: None
                        90      LOAD_CONST                      0: None
                        92      PRECALL                         2
                        96      CALL                            2
                        106     POP_TOP                         
                        108     LOAD_CONST                      0: None
                        110     RETURN_VALUE                    
                        112     PUSH_EXC_INFO                   
                        114     WITH_EXCEPT_START               
                        116     POP_JUMP_FORWARD_IF_TRUE        4 (to 126)
                        118     RERAISE                         2
                        120     COPY                            3
                        122     POP_EXCEPT                      
                        124     RERAISE                         1
                        126     POP_TOP                         
                        128     POP_EXCEPT                      
                        130     POP_TOP                         
                        132     POP_TOP                         
                        134     LOAD_CONST                      0: None
                        136     RETURN_VALUE                    
                'midi_value'
                [Code]
                    File Name: output/Live/mac_universal_64_static/Release/python-bundle/MIDI Remote Scripts/ableton/v2/control_surface/elements/button.py
                    Object Name: __on_midi_value_changed
                    Qualified Name: ButtonElement.__on_midi_value_changed
                    Arg Count: 1
                    Pos Only Arg Count: 0
                    KW Only Arg Count: 0
                    Stack Size: 3
                    Flags: 0x00000007 (CO_OPTIMIZED | CO_NEWLOCALS | CO_VARARGS)
                    [Names]
                        '_do_draw'
                        '_ButtonElement__on_midi_value_changed'
                        'subject'
                    [Locals+Names]
                        'self'
                        'a'
                    [Constants]
                        None
                    [Disassembly]
                        0       RESUME                          0
                        2       LOAD_FAST                       0: self
                        4       LOAD_METHOD                     0: _do_draw
                        26      LOAD_FAST                       0: self
                        28      LOAD_ATTR                       1: _ButtonElement__on_midi_value_changed
                        38      LOAD_ATTR                       2: subject
                        48      PRECALL                         1
                        52      CALL                            1
                        62      POP_TOP                         
                        64      LOAD_CONST                      0: None
                        66      RETURN_VALUE                    
                None
                [Code]
                    File Name: output/Live/mac_universal_64_static/Release/python-bundle/MIDI Remote Scripts/ableton/v2/control_surface/elements/button.py
                    Object Name: send_value
                    Qualified Name: ButtonElement.send_value
                    Arg Count: 4
                    Pos Only Arg Count: 0
                    KW Only Arg Count: 0
                    Stack Size: 5
                    Flags: 0x00000003 (CO_OPTIMIZED | CO_NEWLOCALS)
                    [Names]
                        '_drawing_via_skin'
                        '_disconnect_color_listener'
                        'super'
                        'ButtonElement'
                        'send_value'
                    [Locals+Names]
                        'self'
                        'value'
                        'force'
                        'channel'
                        '__class__'
                    [Constants]
                        None
                    [Disassembly]
                        0       COPY_FREE_VARS                  1
                        2       RESUME                          0
                        4       LOAD_FAST                       0: self
                        6       LOAD_ATTR                       0: _drawing_via_skin
                        16      POP_JUMP_FORWARD_IF_TRUE        20 (to 58)
                        18      LOAD_FAST                       0: self
                        20      LOAD_METHOD                     1: _disconnect_color_listener
                        42      PRECALL                         0
                        46      CALL                            0
                        56      POP_TOP                         
                        58      LOAD_GLOBAL                     5: NULL + super
                        70      LOAD_GLOBAL                     6: ButtonElement
                        82      LOAD_FAST                       0: self
                        84      PRECALL                         2
                        88      CALL                            2
                        98      LOAD_METHOD                     4: send_value
                        120     LOAD_FAST                       1: value
                        122     LOAD_FAST                       2: force
                        124     LOAD_FAST                       3: channel
                        126     PRECALL                         3
                        130     CALL                            3
                        140     POP_TOP                         
                        142     LOAD_CONST                      0: None
                        144     RETURN_VALUE                    
                [Code]
                    File Name: output/Live/mac_universal_64_static/Release/python-bundle/MIDI Remote Scripts/ableton/v2/control_surface/elements/button.py
                    Object Name: receive_value
                    Qualified Name: ButtonElement.receive_value
                    Arg Count: 2
                    Pos Only Arg Count: 0
                    KW Only Arg Count: 0
                    Stack Size: 4
                    Flags: 0x00000003 (CO_OPTIMIZED | CO_NEWLOCALS)
                    [Names]
                        'is_pressed'
                        '_last_received_value'
                        '_undo_step_handler'
                        'begin_undo_step'
                        'super'
                        'ButtonElement'
                        'receive_value'
                        'end_undo_step'
                    [Locals+Names]
                        'self'
                        'value'
                        'pressed_before'
                        '__class__'
                    [Constants]
                        None
                    [Disassembly]
                        0       COPY_FREE_VARS                  1
                        2       RESUME                          0
                        4       LOAD_FAST                       0: self
                        6       LOAD_METHOD                     0: is_pressed
                        28      PRECALL                         0
                        32      CALL                            0
                        42      STORE_FAST                      2: pressed_before
                        44      LOAD_FAST                       1: value
                        46      LOAD_FAST                       0: self
                        48      STORE_ATTR                      1: _last_received_value
                        58      LOAD_FAST                       2: pressed_before
                        60      POP_JUMP_FORWARD_IF_TRUE        45 (to 152)
                        62      LOAD_FAST                       0: self
                        64      LOAD_METHOD                     0: is_pressed
                        86      PRECALL                         0
                        90      CALL                            0
                        100     POP_JUMP_FORWARD_IF_FALSE       25 (to 152)
                        102     LOAD_FAST                       0: self
                        104     LOAD_ATTR                       2: _undo_step_handler
                        114     LOAD_METHOD                     3: begin_undo_step
                        136     PRECALL                         0
                        140     CALL                            0
                        150     POP_TOP                         
                        152     LOAD_GLOBAL                     9: NULL + super
                        164     LOAD_GLOBAL                     10: ButtonElement
                        176     LOAD_FAST                       0: self
                        178     PRECALL                         2
                        182     CALL                            2
                        192     LOAD_METHOD                     6: receive_value
                        214     LOAD_FAST                       1: value
                        216     PRECALL                         1
                        220     CALL                            1
                        230     POP_TOP                         
                        232     LOAD_FAST                       2: pressed_before
                        234     POP_JUMP_FORWARD_IF_FALSE       47 (to 330)
                        236     LOAD_FAST                       0: self
                        238     LOAD_METHOD                     0: is_pressed
                        260     PRECALL                         0
                        264     CALL                            0
                        274     POP_JUMP_FORWARD_IF_TRUE        29 (to 334)
                        276     LOAD_FAST                       0: self
                        278     LOAD_ATTR                       2: _undo_step_handler
                        288     LOAD_METHOD                     7: end_undo_step
                        310     PRECALL                         0
                        314     CALL                            0
                        324     POP_TOP                         
                        326     LOAD_CONST                      0: None
                        328     RETURN_VALUE                    
                        330     LOAD_CONST                      0: None
                        332     RETURN_VALUE                    
                        334     LOAD_CONST                      0: None
                        336     RETURN_VALUE                    
                [Code]
                    File Name: output/Live/mac_universal_64_static/Release/python-bundle/MIDI Remote Scripts/ableton/v2/control_surface/elements/button.py
                    Object Name: disconnect
                    Qualified Name: ButtonElement.disconnect
                    Arg Count: 1
                    Pos Only Arg Count: 0
                    KW Only Arg Count: 0
                    Stack Size: 4
                    Flags: 0x00000003 (CO_OPTIMIZED | CO_NEWLOCALS)
                    [Names]
                        'super'
                        'ButtonElement'
                        'disconnect'
                        '_undo_step_handler'
                    [Locals+Names]
                        'self'
                        '__class__'
                    [Constants]
                        None
                    [Disassembly]
                        0       COPY_FREE_VARS                  1
                        2       RESUME                          0
                        4       LOAD_GLOBAL                     1: NULL + super
                        16      LOAD_GLOBAL                     2: ButtonElement
                        28      LOAD_FAST                       0: self
                        30      PRECALL                         2
                        34      CALL                            2
                        44      LOAD_METHOD                     2: disconnect
                        66      PRECALL                         0
                        70      CALL                            0
                        80      POP_TOP                         
                        82      LOAD_CONST                      0: None
                        84      LOAD_FAST                       0: self
                        86      STORE_ATTR                      3: _undo_step_handler
                        96      LOAD_CONST                      0: None
                        98      RETURN_VALUE                    
                [Code]
                    File Name: output/Live/mac_universal_64_static/Release/python-bundle/MIDI Remote Scripts/ableton/v2/control_surface/elements/button.py
                    Object Name: _disconnect_color_listener
                    Qualified Name: ButtonElement._disconnect_color_listener
                    Arg Count: 1
                    Pos Only Arg Count: 0
                    KW Only Arg Count: 0
                    Stack Size: 2
                    Flags: 0x00000003 (CO_OPTIMIZED | CO_NEWLOCALS)
                    [Names]
                        '_ButtonElement__on_midi_value_changed'
                        'subject'
                    [Locals+Names]
                        'self'
                    [Constants]
                        None
                    [Disassembly]
                        0       RESUME                          0
                        2       LOAD_CONST                      0: None
                        4       LOAD_FAST                       0: self
                        6       LOAD_ATTR                       0: _ButtonElement__on_midi_value_changed
                        16      STORE_ATTR                      1: subject
                        26      LOAD_CONST                      0: None
                        28      RETURN_VALUE                    
                (
                    False
                    None
                )
            [Disassembly]
                0       MAKE_CELL                       0: __class__
                2       RESUME                          0
                4       LOAD_NAME                       0: __name__
                6       STORE_NAME                      1: __module__
                8       LOAD_CONST                      0: 'ButtonElement'
                10      STORE_NAME                      2: __qualname__
                12      NOP                             
                14      PUSH_NULL                       
                16      LOAD_BUILD_CLASS                
                18      LOAD_CONST                      1: <CODE> ProxiedInterface
                20      MAKE_FUNCTION                   0
                22      LOAD_CONST                      2: 'ProxiedInterface'
                24      LOAD_NAME                       3: InputControlElement
                26      LOAD_ATTR                       4: ProxiedInterface
                36      LOAD_NAME                       5: ButtonElementMixin
                38      PRECALL                         4
                42      CALL                            4
                52      STORE_NAME                      4: ProxiedInterface
                54      PUSH_NULL                       
                56      LOAD_BUILD_CLASS                
                58      LOAD_CONST                      3: <CODE> Colors
                60      MAKE_FUNCTION                   0
                62      LOAD_CONST                      4: 'Colors'
                64      PRECALL                         2
                68      CALL                            2
                78      STORE_NAME                      6: Colors
                80      LOAD_CONST                      5: 2
                82      STORE_NAME                      7: num_delayed_messages
                84      LOAD_CONST                      6: False
                86      PUSH_NULL                       
                88      LOAD_NAME                       8: Skin
                90      LOAD_NAME                       6: Colors
                92      PRECALL                         1
                96      CALL                            1
                106     PUSH_NULL                       
                108     LOAD_NAME                       9: DummyUndoStepHandler
                110     PRECALL                         0
                114     CALL                            0
                124     LOAD_CONST                      6: False
                126     BUILD_TUPLE                     4
                128     LOAD_CLOSURE                    0: __class__
                130     BUILD_TUPLE                     1
                132     LOAD_CONST                      7: <CODE> __init__
                134     MAKE_FUNCTION                   9
                136     STORE_NAME                      10: __init__
                138     LOAD_CONST                      8: <CODE> reset
                140     MAKE_FUNCTION                   0
                142     STORE_NAME                      11: reset
                144     LOAD_CONST                      9: <CODE> is_momentary
                146     MAKE_FUNCTION                   0
                148     STORE_NAME                      12: is_momentary
                150     LOAD_CONST                      10: <CODE> message_map_mode
                152     MAKE_FUNCTION                   0
                154     STORE_NAME                      13: message_map_mode
                156     LOAD_CONST                      11: <CODE> is_pressed
                158     MAKE_FUNCTION                   0
                160     STORE_NAME                      14: is_pressed
                162     LOAD_CONST                      12: <CODE> set_light
                164     MAKE_FUNCTION                   0
                166     STORE_NAME                      15: set_light
                168     LOAD_CONST                      13: <CODE> _set_skin_light
                170     MAKE_FUNCTION                   0
                172     STORE_NAME                      16: _set_skin_light
                174     LOAD_CONST                      14: <CODE> _do_draw
                176     MAKE_FUNCTION                   0
                178     STORE_NAME                      17: _do_draw
                180     PUSH_NULL                       
                182     LOAD_NAME                       18: listens
                184     LOAD_CONST                      15: 'midi_value'
                186     PRECALL                         1
                190     CALL                            1
                200     LOAD_CONST                      16: <CODE> __on_midi_value_changed
                202     MAKE_FUNCTION                   0
                204     PRECALL                         0
                208     CALL                            0
                218     STORE_NAME                      19: _ButtonElement__on_midi_value_changed
                220     LOAD_CONST                      22: (False, None)
                222     LOAD_CLOSURE                    0: __class__
                224     BUILD_TUPLE                     1
                226     LOAD_CONST                      18: <CODE> send_value
                228     MAKE_FUNCTION                   9
                230     STORE_NAME                      20: send_value
                232     LOAD_CLOSURE                    0: __class__
                234     BUILD_TUPLE                     1
                236     LOAD_CONST                      19: <CODE> receive_value
                238     MAKE_FUNCTION                   8
                240     STORE_NAME                      21: receive_value
                242     LOAD_CLOSURE                    0: __class__
                244     BUILD_TUPLE                     1
                246     LOAD_CONST                      20: <CODE> disconnect
                248     MAKE_FUNCTION                   8
                250     STORE_NAME                      22: disconnect
                252     LOAD_CONST                      21: <CODE> _disconnect_color_listener
                254     MAKE_FUNCTION                   0
                256     STORE_NAME                      23: _disconnect_color_listener
                258     LOAD_CLOSURE                    0: __class__
                260     COPY                            1
                262     STORE_NAME                      24: __classcell__
                264     RETURN_VALUE                    
        'ButtonElement'
    [Disassembly]
        0       RESUME                          0
        2       LOAD_CONST                      0: 0
        4       LOAD_CONST                      1: ('long',)
        6       IMPORT_NAME                     0: past.builtins
        8       IMPORT_FROM                     1: long
        10      STORE_NAME                      1: long
        12      POP_TOP                         
        14      LOAD_CONST                      0: 0
        16      LOAD_CONST                      2: None
        18      IMPORT_NAME                     2: Live
        20      STORE_NAME                      2: Live
        22      LOAD_CONST                      3: 3
        24      LOAD_CONST                      4: ('BooleanContext', 'const', 'has_event', 'in_range', 'listens', 'old_hasattr')
        26      IMPORT_NAME                     3: base
        28      IMPORT_FROM                     4: BooleanContext
        30      STORE_NAME                      4: BooleanContext
        32      IMPORT_FROM                     5: const
        34      STORE_NAME                      5: const
        36      IMPORT_FROM                     6: has_event
        38      STORE_NAME                      6: has_event
        40      IMPORT_FROM                     7: in_range
        42      STORE_NAME                      7: in_range
        44      IMPORT_FROM                     8: listens
        46      STORE_NAME                      8: listens
        48      IMPORT_FROM                     9: old_hasattr
        50      STORE_NAME                      9: old_hasattr
        52      POP_TOP                         
        54      LOAD_CONST                      5: 2
        56      LOAD_CONST                      6: ('MIDI_CC_TYPE', 'InputControlElement')
        58      IMPORT_NAME                     10: input_control_element
        60      IMPORT_FROM                     11: MIDI_CC_TYPE
        62      STORE_NAME                      11: MIDI_CC_TYPE
        64      IMPORT_FROM                     12: InputControlElement
        66      STORE_NAME                      12: InputControlElement
        68      POP_TOP                         
        70      LOAD_CONST                      5: 2
        72      LOAD_CONST                      7: ('Skin',)
        74      IMPORT_NAME                     13: skin
        76      IMPORT_FROM                     14: Skin
        78      STORE_NAME                      14: Skin
        80      POP_TOP                         
        82      LOAD_CONST                      8: 1
        84      LOAD_CONST                      9: ('Color',)
        86      IMPORT_NAME                     15: color
        88      IMPORT_FROM                     16: Color
        90      STORE_NAME                      16: Color
        92      POP_TOP                         
        94      PUSH_NULL                       
        96      LOAD_BUILD_CLASS                
        98      LOAD_CONST                      10: <CODE> DummyUndoStepHandler
        100     MAKE_FUNCTION                   0
        102     LOAD_CONST                      11: 'DummyUndoStepHandler'
        104     LOAD_NAME                       17: object
        106     PRECALL                         3
        110     CALL                            3
        120     STORE_NAME                      18: DummyUndoStepHandler
        122     PUSH_NULL                       
        124     LOAD_BUILD_CLASS                
        126     LOAD_CONST                      12: <CODE> ButtonElementMixin
        128     MAKE_FUNCTION                   0
        130     LOAD_CONST                      13: 'ButtonElementMixin'
        132     LOAD_NAME                       17: object
        134     PRECALL                         3
        138     CALL                            3
        148     STORE_NAME                      19: ButtonElementMixin
        150     PUSH_NULL                       
        152     LOAD_BUILD_CLASS                
        154     LOAD_CONST                      14: <CODE> ButtonElement
        156     MAKE_FUNCTION                   0
        158     LOAD_CONST                      15: 'ButtonElement'
        160     LOAD_NAME                       12: InputControlElement
        162     LOAD_NAME                       19: ButtonElementMixin
        164     PRECALL                         4
        168     CALL                            4
        178     STORE_NAME                      20: ButtonElement
        180     LOAD_CONST                      2: None
        182     RETURN_VALUE                    
