modified_colors.pyc (Python 3.11)
[Code]
    File Name: output/Live/mac_universal_64_static/Release/python-bundle/MIDI Remote Scripts/novation/colors.py
    Object Name: <module>
    Qualified Name: <module>
    Arg Count: 0
    Pos Only Arg Count: 0
    KW Only Arg Count: 0
    Stack Size: 5
    Flags: 0x00000000
    [Names]
        'ableton.v2.control_surface.elements'
        'AnimatedColor'
        'Color'
        'BLINK_CHANNEL'
        'PULSE_CHANNEL'
        'Pulse'
        'Blink'
        'object'
        'Rgb'
        'Mono'
        'CLIP_COLOR_TABLE'
        'RGB_COLOR_TABLE'
    [Locals+Names]
    [Constants]
        0
        (
            'AnimatedColor'
            'Color'
        )
        1
        2
        [Code]
            File Name: output/Live/mac_universal_64_static/Release/python-bundle/MIDI Remote Scripts/novation/colors.py
            Object Name: Pulse
            Qualified Name: Pulse
            Arg Count: 0
            Pos Only Arg Count: 0
            KW Only Arg Count: 0
            Stack Size: 1
            Flags: 0x00000000
            [Names]
                '__name__'
                '__module__'
                '__qualname__'
                'PULSE_CHANNEL'
                '_channel'
            [Locals+Names]
            [Constants]
                'Pulse'
                None
            [Disassembly]
                0       RESUME                          0
                2       LOAD_NAME                       0: __name__
                4       STORE_NAME                      1: __module__
                6       LOAD_CONST                      0: 'Pulse'
                8       STORE_NAME                      2: __qualname__
                10      LOAD_NAME                       3: PULSE_CHANNEL
                12      STORE_NAME                      4: _channel
                14      LOAD_CONST                      1: None
                16      RETURN_VALUE                    
        'Pulse'
        [Code]
            File Name: output/Live/mac_universal_64_static/Release/python-bundle/MIDI Remote Scripts/novation/colors.py
            Object Name: Blink
            Qualified Name: Blink
            Arg Count: 0
            Pos Only Arg Count: 0
            KW Only Arg Count: 0
            Stack Size: 1
            Flags: 0x00000000
            [Names]
                '__name__'
                '__module__'
                '__qualname__'
                'BLINK_CHANNEL'
                '_channel'
            [Locals+Names]
            [Constants]
                'Blink'
                None
            [Disassembly]
                0       RESUME                          0
                2       LOAD_NAME                       0: __name__
                4       STORE_NAME                      1: __module__
                6       LOAD_CONST                      0: 'Blink'
                8       STORE_NAME                      2: __qualname__
                10      LOAD_NAME                       3: BLINK_CHANNEL
                12      STORE_NAME                      4: _channel
                14      LOAD_CONST                      1: None
                16      RETURN_VALUE                    
        'Blink'
        [Code]
            File Name: output/Live/mac_universal_64_static/Release/python-bundle/MIDI Remote Scripts/novation/colors.py
            Object Name: Rgb
            Qualified Name: Rgb
            Arg Count: 0
            Pos Only Arg Count: 0
            KW Only Arg Count: 0
            Stack Size: 4
            Flags: 0x00000000
            [Names]
                '__name__'
                '__module__'
                '__qualname__'
                'Color'
                'BLACK'
                'DARK_GREY'
                'GREY'
                'WHITE'
                'WHITE_HALF'
                'RED'
                'Blink'
                'RED_BLINK'
                'Pulse'
                'RED_PULSE'
                'RED_HALF'
                'OFF_WHITE'
                'ORANGE'
                'ORANGE_HALF'
                'CREAM'
                'AMBER'
                'AMBER_HALF'
                'DARK_YELLOW'
                'DARK_YELLOW_HALF'
                'GREEN'
                'GREEN_BLINK'
                'GREEN_PULSE'
                'GREEN_HALF'
                'MINT'
                'MINT_HALF'
                'LIGHT_BLUE'
                'LIGHT_BLUE_HALF'
                'BLUE'
                'BLUE_PULSE'
                'BLUE_HALF'
                'DARK_BLUE'
                'DARK_BLUE_HALF'
                'VIOLET'
                'PURPLE'
                'PURPLE_HALF'
                'AQUA'
                'DARK_ORANGE'
                'PALE_GREEN'
                'PALE_GREEN_HALF'
                'YELLOW'
                'YELLOW_HALF'
            [Locals+Names]
            [Constants]
                'Rgb'
                0
                1
                2
                3
                5
                (
                    'color1'
                    'color2'
                )
                7
                8
                9
                11
                12
                96
                14
                17
                19
                21
                27
                29
                31
                37
                39
                41
                43
                49
                51
                52
                53
                55
                77
                84
                87
                89
                97
                125
                None
            [Disassembly]
                0       RESUME                          0
                2       LOAD_NAME                       0: __name__
                4       STORE_NAME                      1: __module__
                6       LOAD_CONST                      0: 'Rgb'
                8       STORE_NAME                      2: __qualname__
                10      PUSH_NULL                       
                12      LOAD_NAME                       3: Color
                14      LOAD_CONST                      1: 0
                16      PRECALL                         1
                20      CALL                            1
                30      STORE_NAME                      4: BLACK
                32      PUSH_NULL                       
                34      LOAD_NAME                       3: Color
                36      LOAD_CONST                      2: 1
                38      PRECALL                         1
                42      CALL                            1
                52      STORE_NAME                      5: DARK_GREY
                54      PUSH_NULL                       
                56      LOAD_NAME                       3: Color
                58      LOAD_CONST                      3: 2
                60      PRECALL                         1
                64      CALL                            1
                74      STORE_NAME                      6: GREY
                76      PUSH_NULL                       
                78      LOAD_NAME                       3: Color
                80      LOAD_CONST                      4: 3
                82      PRECALL                         1
                86      CALL                            1
                96      STORE_NAME                      7: WHITE
                98      PUSH_NULL                       
                100     LOAD_NAME                       3: Color
                102     LOAD_CONST                      2: 1
                104     PRECALL                         1
                108     CALL                            1
                118     STORE_NAME                      8: WHITE_HALF
                120     PUSH_NULL                       
                122     LOAD_NAME                       3: Color
                124     LOAD_CONST                      5: 5
                126     PRECALL                         1
                130     CALL                            1
                140     STORE_NAME                      9: RED
                142     PUSH_NULL                       
                144     LOAD_NAME                       10: Blink
                146     LOAD_NAME                       4: BLACK
                148     LOAD_NAME                       9: RED
                150     KW_NAMES                        6: ('color1', 'color2')
                152     PRECALL                         2
                156     CALL                            2
                166     STORE_NAME                      11: RED_BLINK
                168     PUSH_NULL                       
                170     LOAD_NAME                       12: Pulse
                172     LOAD_NAME                       4: BLACK
                174     LOAD_NAME                       9: RED
                176     KW_NAMES                        6: ('color1', 'color2')
                178     PRECALL                         2
                182     CALL                            2
                192     STORE_NAME                      13: RED_PULSE
                194     PUSH_NULL                       
                196     LOAD_NAME                       3: Color
                198     LOAD_CONST                      7: 7
                200     PRECALL                         1
                204     CALL                            1
                214     STORE_NAME                      14: RED_HALF
                216     PUSH_NULL                       
                218     LOAD_NAME                       3: Color
                220     LOAD_CONST                      8: 8
                222     PRECALL                         1
                226     CALL                            1
                236     STORE_NAME                      15: OFF_WHITE
                238     PUSH_NULL                       
                240     LOAD_NAME                       3: Color
                242     LOAD_CONST                      9: 9
                244     PRECALL                         1
                248     CALL                            1
                258     STORE_NAME                      16: ORANGE
                260     PUSH_NULL                       
                262     LOAD_NAME                       3: Color
                264     LOAD_CONST                      10: 11
                266     PRECALL                         1
                270     CALL                            1
                280     STORE_NAME                      17: ORANGE_HALF
                282     PUSH_NULL                       
                284     LOAD_NAME                       3: Color
                286     LOAD_CONST                      11: 12
                288     PRECALL                         1
                292     CALL                            1
                302     STORE_NAME                      18: CREAM
                304     PUSH_NULL                       
                306     LOAD_NAME                       3: Color
                308     LOAD_CONST                      12: 96
                310     PRECALL                         1
                314     CALL                            1
                324     STORE_NAME                      19: AMBER
                326     PUSH_NULL                       
                328     LOAD_NAME                       3: Color
                330     LOAD_CONST                      13: 14
                332     PRECALL                         1
                336     CALL                            1
                346     STORE_NAME                      20: AMBER_HALF
                348     PUSH_NULL                       
                350     LOAD_NAME                       3: Color
                352     LOAD_CONST                      14: 17
                354     PRECALL                         1
                358     CALL                            1
                368     STORE_NAME                      21: DARK_YELLOW
                370     PUSH_NULL                       
                372     LOAD_NAME                       3: Color
                374     LOAD_CONST                      15: 19
                376     PRECALL                         1
                380     CALL                            1
                390     STORE_NAME                      22: DARK_YELLOW_HALF
                392     PUSH_NULL                       
                394     LOAD_NAME                       3: Color
                396     LOAD_CONST                      16: 21
                398     PRECALL                         1
                402     CALL                            1
                412     STORE_NAME                      23: GREEN
                414     PUSH_NULL                       
                416     LOAD_NAME                       10: Blink
                418     LOAD_NAME                       4: BLACK
                420     LOAD_NAME                       23: GREEN
                422     KW_NAMES                        6: ('color1', 'color2')
                424     PRECALL                         2
                428     CALL                            2
                438     STORE_NAME                      24: GREEN_BLINK
                440     PUSH_NULL                       
                442     LOAD_NAME                       12: Pulse
                444     LOAD_NAME                       4: BLACK
                446     LOAD_NAME                       23: GREEN
                448     KW_NAMES                        6: ('color1', 'color2')
                450     PRECALL                         2
                454     CALL                            2
                464     STORE_NAME                      25: GREEN_PULSE
                466     PUSH_NULL                       
                468     LOAD_NAME                       3: Color
                470     LOAD_CONST                      17: 27
                472     PRECALL                         1
                476     CALL                            1
                486     STORE_NAME                      26: GREEN_HALF
                488     PUSH_NULL                       
                490     LOAD_NAME                       3: Color
                492     LOAD_CONST                      18: 29
                494     PRECALL                         1
                498     CALL                            1
                508     STORE_NAME                      27: MINT
                510     PUSH_NULL                       
                512     LOAD_NAME                       3: Color
                514     LOAD_CONST                      19: 31
                516     PRECALL                         1
                520     CALL                            1
                530     STORE_NAME                      28: MINT_HALF
                532     PUSH_NULL                       
                534     LOAD_NAME                       3: Color
                536     LOAD_CONST                      20: 37
                538     PRECALL                         1
                542     CALL                            1
                552     STORE_NAME                      29: LIGHT_BLUE
                554     PUSH_NULL                       
                556     LOAD_NAME                       3: Color
                558     LOAD_CONST                      21: 39
                560     PRECALL                         1
                564     CALL                            1
                574     STORE_NAME                      30: LIGHT_BLUE_HALF
                576     PUSH_NULL                       
                578     LOAD_NAME                       3: Color
                580     LOAD_CONST                      22: 41
                582     PRECALL                         1
                586     CALL                            1
                596     STORE_NAME                      31: BLUE
                598     PUSH_NULL                       
                600     LOAD_NAME                       12: Pulse
                602     LOAD_NAME                       4: BLACK
                604     LOAD_NAME                       31: BLUE
                606     KW_NAMES                        6: ('color1', 'color2')
                608     PRECALL                         2
                612     CALL                            2
                622     STORE_NAME                      32: BLUE_PULSE
                624     PUSH_NULL                       
                626     LOAD_NAME                       3: Color
                628     LOAD_CONST                      23: 43
                630     PRECALL                         1
                634     CALL                            1
                644     STORE_NAME                      33: BLUE_HALF
                646     PUSH_NULL                       
                648     LOAD_NAME                       3: Color
                650     LOAD_CONST                      24: 49
                652     PRECALL                         1
                656     CALL                            1
                666     STORE_NAME                      34: DARK_BLUE
                668     PUSH_NULL                       
                670     LOAD_NAME                       3: Color
                672     LOAD_CONST                      25: 51
                674     PRECALL                         1
                678     CALL                            1
                688     STORE_NAME                      35: DARK_BLUE_HALF
                690     PUSH_NULL                       
                692     LOAD_NAME                       3: Color
                694     LOAD_CONST                      26: 52
                696     PRECALL                         1
                700     CALL                            1
                710     STORE_NAME                      36: VIOLET
                712     PUSH_NULL                       
                714     LOAD_NAME                       3: Color
                716     LOAD_CONST                      27: 53
                718     PRECALL                         1
                722     CALL                            1
                732     STORE_NAME                      37: PURPLE
                734     PUSH_NULL                       
                736     LOAD_NAME                       3: Color
                738     LOAD_CONST                      28: 55
                740     PRECALL                         1
                744     CALL                            1
                754     STORE_NAME                      38: PURPLE_HALF
                756     PUSH_NULL                       
                758     LOAD_NAME                       3: Color
                760     LOAD_CONST                      29: 77
                762     PRECALL                         1
                766     CALL                            1
                776     STORE_NAME                      39: AQUA
                778     PUSH_NULL                       
                780     LOAD_NAME                       3: Color
                782     LOAD_CONST                      30: 84
                784     PRECALL                         1
                788     CALL                            1
                798     STORE_NAME                      40: DARK_ORANGE
                800     PUSH_NULL                       
                802     LOAD_NAME                       3: Color
                804     LOAD_CONST                      31: 87
                806     PRECALL                         1
                810     CALL                            1
                820     STORE_NAME                      41: PALE_GREEN
                822     PUSH_NULL                       
                824     LOAD_NAME                       3: Color
                826     LOAD_CONST                      32: 89
                828     PRECALL                         1
                832     CALL                            1
                842     STORE_NAME                      42: PALE_GREEN_HALF
                844     PUSH_NULL                       
                846     LOAD_NAME                       3: Color
                848     LOAD_CONST                      33: 97
                850     PRECALL                         1
                854     CALL                            1
                864     STORE_NAME                      43: YELLOW
                866     PUSH_NULL                       
                868     LOAD_NAME                       3: Color
                870     LOAD_CONST                      34: 125
                872     PRECALL                         1
                876     CALL                            1
                886     STORE_NAME                      44: YELLOW_HALF
                888     LOAD_CONST                      35: None
                890     RETURN_VALUE                    
        'Rgb'
        [Code]
            File Name: output/Live/mac_universal_64_static/Release/python-bundle/MIDI Remote Scripts/novation/colors.py
            Object Name: Mono
            Qualified Name: Mono
            Arg Count: 0
            Pos Only Arg Count: 0
            KW Only Arg Count: 0
            Stack Size: 3
            Flags: 0x00000000
            [Names]
                '__name__'
                '__module__'
                '__qualname__'
                'Color'
                'OFF'
                'HALF'
                'ON'
            [Locals+Names]
            [Constants]
                'Mono'
                0
                63
                127
                None
            [Disassembly]
                0       RESUME                          0
                2       LOAD_NAME                       0: __name__
                4       STORE_NAME                      1: __module__
                6       LOAD_CONST                      0: 'Mono'
                8       STORE_NAME                      2: __qualname__
                10      PUSH_NULL                       
                12      LOAD_NAME                       3: Color
                14      LOAD_CONST                      1: 0
                16      PRECALL                         1
                20      CALL                            1
                30      STORE_NAME                      4: OFF
                32      PUSH_NULL                       
                34      LOAD_NAME                       3: Color
                36      LOAD_CONST                      2: 63
                38      PRECALL                         1
                42      CALL                            1
                52      STORE_NAME                      5: HALF
                54      PUSH_NULL                       
                56      LOAD_NAME                       3: Color
                58      LOAD_CONST                      3: 127
                60      PRECALL                         1
                64      CALL                            1
                74      STORE_NAME                      6: ON
                76      LOAD_CONST                      4: None
                78      RETURN_VALUE                    
        'Mono'
        10927616
        74
        16149507
        84
        4047616
        76
        6441901
        69
        14402304
        99
        8754719
        19
        16725558
        5
        3947580
        71
        10056267
        15
        8237133
        18
        12026454
        11
        12565097
        73
        13381230
        58
        12243060
        111
        16249980
        13
        13013643
        4
        10208397
        88
        695438
        65
        13821080
        110
        3101346
        46
        16749734
        107
        8962746
        102
        5538020
        79
        13684944
        117
        15064289
        119
        14183652
        94
        11442405
        44
        13408551
        100
        1090798
        78
        11096369
        127
        16753961
        96
        1769263
        87
        5480241
        64
        1698303
        90
        16773172
        97
        7491393
        126
        8940772
        80
        14837594
        10
        8912743
        16
        10060650
        105
        13872497
        14
        16753524
        108
        8092539
        70
        2319236
        39
        1716118
        47
        12349846
        59
        11481907
        121
        15029152
        57
        2490280
        25
        11119017
        112
        10701741
        81
        15597486
        8
        49071
        77
        10851765
        93
        12558270
        48
        32192
        43
        8758722
        103
        10204100
        104
        11958214
        55
        8623052
        66
        16726484
        95
        12581632
        86
        13958625
        28
        12173795
        115
        13482980
        116
        16777215
        3
        6094824
        33
        13496824
        114
        92
        36
        (
            9611263
            9160191
        )
        (
            (
                0
                0
            )
            (
                1
                1973790
            )
            (
                2
                8355711
            )
            (
                3
                16777215
            )
            (
                4
                16731212
            )
            (
                5
                16711680
            )
            (
                6
                5832704
            )
            (
                7
                1638400
            )
            (
                8
                16760172
            )
            (
                9
                16733184
            )
            (
                10
                5840128
            )
            (
                11
                2562816
            )
            (
                12
                16777036
            )
            (
                13
                16776960
            )
            (
                14
                5855488
            )
            (
                15
                1644800
            )
            (
                16
                8978252
            )
            (
                17
                5570304
            )
            (
                18
                1923328
            )
            (
                19
                1321728
            )
            (
                20
                5046092
            )
            (
                21
                65280
            )
            (
                22
                22784
            )
            (
                23
                6400
            )
            (
                24
                5046110
            )
            (
                25
                65305
            )
            (
                26
                22797
            )
            (
                27
                6402
            )
            (
                28
                5046152
            )
            (
                29
                65365
            )
            (
                30
                22813
            )
            (
                31
                7954
            )
            (
                32
                5046199
            )
            (
                33
                65433
            )
            (
                34
                22837
            )
            (
                35
                6418
            )
            (
                36
                5030911
            )
            (
                37
                43519
            )
            (
                38
                16722
            )
            (
                39
                4121
            )
            (
                40
                5015807
            )
            (
                41
                22015
            )
            (
                42
                7513
            )
            (
                43
                2073
            )
            (
                44
                5000447
            )
            (
                45
                255
            )
            (
                46
                89
            )
            (
                47
                25
            )
            (
                48
                8867071
            )
            (
                49
                5505279
            )
            (
                50
                1638500
            )
            (
                51
                983088
            )
            (
                52
                16731391
            )
            (
                53
                16711935
            )
            (
                54
                5832793
            )
            (
                55
                1638425
            )
            (
                56
                16731271
            )
            (
                57
                16711764
            )
            (
                58
                5832733
            )
            (
                59
                2228243
            )
            (
                60
                16717056
            )
            (
                61
                10040576
            )
            (
                62
                7950592
            )
            (
                63
                4416512
            )
            (
                64
                211200
            )
            (
                65
                22325
            )
            (
                66
                21631
            )
            (
                67
                255
            )
            (
                68
                17743
            )
            (
                69
                2425036
            )
            (
                70
                8355711
            )
            (
                71
                2105376
            )
            (
                72
                16711680
            )
            (
                73
                12451629
            )
            (
                74
                11529478
            )
            (
                75
                6618889
            )
            (
                76
                1084160
            )
            (
                77
                65415
            )
            (
                78
                43519
            )
            (
                79
                11007
            )
            (
                80
                4129023
            )
            (
                81
                7995647
            )
            (
                82
                11672189
            )
            (
                83
                4202752
            )
            (
                84
                16730624
            )
            (
                85
                8970502
            )
            (
                86
                7536405
            )
            (
                87
                65280
            )
            (
                88
                3931942
            )
            (
                89
                5898097
            )
            (
                90
                3735500
            )
            (
                91
                5999359
            )
            (
                92
                3232198
            )
            (
                93
                8880105
            )
            (
                94
                13835775
            )
            (
                95
                16711773
            )
            (
                96
                16744192
            )
            (
                97
                12169216
            )
            (
                98
                9502464
            )
            (
                99
                8609031
            )
            (
                100
                3746560
            )
            (
                101
                1330192
            )
            (
                102
                872504
            )
            (
                103
                1381674
            )
            (
                104
                1450074
            )
            (
                105
                6896668
            )
            (
                106
                11010058
            )
            (
                107
                14569789
            )
            (
                108
                14182940
            )
            (
                109
                16769318
            )
            (
                110
                10412335
            )
            (
                111
                6796559
            )
            (
                112
                1973808
            )
            (
                113
                14483307
            )
            (
                114
                8454077
            )
            (
                115
                10131967
            )
            (
                116
                9332479
            )
            (
                117
                4210752
            )
            (
                118
                7697781
            )
            (
                119
                14745599
            )
            (
                120
                10485760
            )
            (
                121
                3473408
            )
            (
                122
                1757184
            )
            (
                123
                475648
            )
            (
                124
                12169216
            )
            (
                125
                4141312
            )
            (
                126
                11755264
            )
            (
                127
                4920578
            )
        )
        None
    [Disassembly]
        0       RESUME                          0
        2       LOAD_CONST                      0: 0
        4       LOAD_CONST                      1: ('AnimatedColor', 'Color')
        6       IMPORT_NAME                     0: ableton.v2.control_surface.elements
        8       IMPORT_FROM                     1: AnimatedColor
        10      STORE_NAME                      1: AnimatedColor
        12      IMPORT_FROM                     2: Color
        14      STORE_NAME                      2: Color
        16      POP_TOP                         
        18      LOAD_CONST                      2: 1
        20      STORE_NAME                      3: BLINK_CHANNEL
        22      LOAD_CONST                      3: 2
        24      STORE_NAME                      4: PULSE_CHANNEL
        26      PUSH_NULL                       
        28      LOAD_BUILD_CLASS                
        30      LOAD_CONST                      4: <CODE> Pulse
        32      MAKE_FUNCTION                   0
        34      LOAD_CONST                      5: 'Pulse'
        36      LOAD_NAME                       1: AnimatedColor
        38      PRECALL                         3
        42      CALL                            3
        52      STORE_NAME                      5: Pulse
        54      PUSH_NULL                       
        56      LOAD_BUILD_CLASS                
        58      LOAD_CONST                      6: <CODE> Blink
        60      MAKE_FUNCTION                   0
        62      LOAD_CONST                      7: 'Blink'
        64      LOAD_NAME                       1: AnimatedColor
        66      PRECALL                         3
        70      CALL                            3
        80      STORE_NAME                      6: Blink
        82      PUSH_NULL                       
        84      LOAD_BUILD_CLASS                
        86      LOAD_CONST                      8: <CODE> Rgb
        88      MAKE_FUNCTION                   0
        90      LOAD_CONST                      9: 'Rgb'
        92      LOAD_NAME                       7: object
        94      PRECALL                         3
        98      CALL                            3
        108     STORE_NAME                      8: Rgb
        110     PUSH_NULL                       
        112     LOAD_BUILD_CLASS                
        114     LOAD_CONST                      10: <CODE> Mono
        116     MAKE_FUNCTION                   0
        118     LOAD_CONST                      11: 'Mono'
        120     LOAD_NAME                       7: object
        122     PRECALL                         3
        126     CALL                            3
        136     STORE_NAME                      9: Mono
        138     BUILD_MAP                       0
        140     LOAD_CONST                      12: 10927616
        142     LOAD_CONST                      13: 74
        144     MAP_ADD                         1
        146     LOAD_CONST                      14: 16149507
        148     LOAD_CONST                      15: 84
        150     MAP_ADD                         1
        152     LOAD_CONST                      16: 4047616
        154     LOAD_CONST                      17: 76
        156     MAP_ADD                         1
        158     LOAD_CONST                      18: 6441901
        160     LOAD_CONST                      19: 69
        162     MAP_ADD                         1
        164     LOAD_CONST                      20: 14402304
        166     LOAD_CONST                      21: 99
        168     MAP_ADD                         1
        170     LOAD_CONST                      22: 8754719
        172     LOAD_CONST                      23: 19
        174     MAP_ADD                         1
        176     LOAD_CONST                      24: 16725558
        178     LOAD_CONST                      25: 5
        180     MAP_ADD                         1
        182     LOAD_CONST                      26: 3947580
        184     LOAD_CONST                      27: 71
        186     MAP_ADD                         1
        188     LOAD_CONST                      28: 10056267
        190     LOAD_CONST                      29: 15
        192     MAP_ADD                         1
        194     LOAD_CONST                      30: 8237133
        196     LOAD_CONST                      31: 18
        198     MAP_ADD                         1
        200     LOAD_CONST                      32: 12026454
        202     LOAD_CONST                      33: 11
        204     MAP_ADD                         1
        206     LOAD_CONST                      34: 12565097
        208     LOAD_CONST                      35: 73
        210     MAP_ADD                         1
        212     LOAD_CONST                      36: 13381230
        214     LOAD_CONST                      37: 58
        216     MAP_ADD                         1
        218     LOAD_CONST                      38: 12243060
        220     LOAD_CONST                      39: 111
        222     MAP_ADD                         1
        224     LOAD_CONST                      40: 16249980
        226     LOAD_CONST                      41: 13
        228     MAP_ADD                         1
        230     LOAD_CONST                      42: 13013643
        232     LOAD_CONST                      43: 4
        234     MAP_ADD                         1
        236     LOAD_CONST                      44: 10208397
        238     LOAD_CONST                      45: 88
        240     MAP_ADD                         1
        242     BUILD_MAP                       0
        244     LOAD_CONST                      46: 695438
        246     LOAD_CONST                      47: 65
        248     MAP_ADD                         1
        250     LOAD_CONST                      48: 13821080
        252     LOAD_CONST                      49: 110
        254     MAP_ADD                         1
        256     LOAD_CONST                      50: 3101346
        258     LOAD_CONST                      51: 46
        260     MAP_ADD                         1
        262     LOAD_CONST                      52: 16749734
        264     LOAD_CONST                      53: 107
        266     MAP_ADD                         1
        268     LOAD_CONST                      54: 8962746
        270     LOAD_CONST                      55: 102
        272     MAP_ADD                         1
        274     LOAD_CONST                      56: 5538020
        276     LOAD_CONST                      57: 79
        278     MAP_ADD                         1
        280     LOAD_CONST                      58: 13684944
        282     LOAD_CONST                      59: 117
        284     MAP_ADD                         1
        286     LOAD_CONST                      60: 15064289
        288     LOAD_CONST                      61: 119
        290     MAP_ADD                         1
        292     LOAD_CONST                      62: 14183652
        294     LOAD_CONST                      63: 94
        296     MAP_ADD                         1
        298     LOAD_CONST                      64: 11442405
        300     LOAD_CONST                      65: 44
        302     MAP_ADD                         1
        304     LOAD_CONST                      66: 13408551
        306     LOAD_CONST                      67: 100
        308     MAP_ADD                         1
        310     LOAD_CONST                      68: 1090798
        312     LOAD_CONST                      69: 78
        314     MAP_ADD                         1
        316     LOAD_CONST                      70: 11096369
        318     LOAD_CONST                      71: 127
        320     MAP_ADD                         1
        322     LOAD_CONST                      72: 16753961
        324     LOAD_CONST                      73: 96
        326     MAP_ADD                         1
        328     LOAD_CONST                      74: 1769263
        330     LOAD_CONST                      75: 87
        332     MAP_ADD                         1
        334     LOAD_CONST                      76: 5480241
        336     LOAD_CONST                      77: 64
        338     MAP_ADD                         1
        340     LOAD_CONST                      78: 1698303
        342     LOAD_CONST                      79: 90
        344     MAP_ADD                         1
        346     DICT_UPDATE                     1
        348     BUILD_MAP                       0
        350     LOAD_CONST                      80: 16773172
        352     LOAD_CONST                      81: 97
        354     MAP_ADD                         1
        356     LOAD_CONST                      82: 7491393
        358     LOAD_CONST                      83: 126
        360     MAP_ADD                         1
        362     LOAD_CONST                      84: 8940772
        364     LOAD_CONST                      85: 80
        366     MAP_ADD                         1
        368     LOAD_CONST                      86: 14837594
        370     LOAD_CONST                      87: 10
        372     MAP_ADD                         1
        374     LOAD_CONST                      88: 8912743
        376     LOAD_CONST                      89: 16
        378     MAP_ADD                         1
        380     LOAD_CONST                      90: 10060650
        382     LOAD_CONST                      91: 105
        384     MAP_ADD                         1
        386     LOAD_CONST                      92: 13872497
        388     LOAD_CONST                      93: 14
        390     MAP_ADD                         1
        392     LOAD_CONST                      94: 16753524
        394     LOAD_CONST                      95: 108
        396     MAP_ADD                         1
        398     LOAD_CONST                      96: 8092539
        400     LOAD_CONST                      97: 70
        402     MAP_ADD                         1
        404     LOAD_CONST                      98: 2319236
        406     LOAD_CONST                      99: 39
        408     MAP_ADD                         1
        410     LOAD_CONST                      100: 1716118
        412     LOAD_CONST                      101: 47
        414     MAP_ADD                         1
        416     LOAD_CONST                      102: 12349846
        418     LOAD_CONST                      103: 59
        420     MAP_ADD                         1
        422     LOAD_CONST                      104: 11481907
        424     LOAD_CONST                      105: 121
        426     MAP_ADD                         1
        428     LOAD_CONST                      106: 15029152
        430     LOAD_CONST                      107: 57
        432     MAP_ADD                         1
        434     LOAD_CONST                      108: 2490280
        436     LOAD_CONST                      109: 25
        438     MAP_ADD                         1
        440     LOAD_CONST                      110: 11119017
        442     LOAD_CONST                      111: 112
        444     MAP_ADD                         1
        446     LOAD_CONST                      112: 10701741
        448     LOAD_CONST                      113: 81
        450     MAP_ADD                         1
        452     DICT_UPDATE                     1
        454     BUILD_MAP                       0
        456     LOAD_CONST                      114: 15597486
        458     LOAD_CONST                      115: 8
        460     MAP_ADD                         1
        462     LOAD_CONST                      116: 49071
        464     LOAD_CONST                      117: 77
        466     MAP_ADD                         1
        468     LOAD_CONST                      118: 10851765
        470     LOAD_CONST                      119: 93
        472     MAP_ADD                         1
        474     LOAD_CONST                      120: 12558270
        476     LOAD_CONST                      121: 48
        478     MAP_ADD                         1
        480     LOAD_CONST                      122: 32192
        482     LOAD_CONST                      123: 43
        484     MAP_ADD                         1
        486     LOAD_CONST                      124: 8758722
        488     LOAD_CONST                      125: 103
        490     MAP_ADD                         1
        492     LOAD_CONST                      126: 10204100
        494     LOAD_CONST                      127: 104
        496     MAP_ADD                         1
        498     LOAD_CONST                      128: 11958214
        500     LOAD_CONST                      129: 55
        502     MAP_ADD                         1
        504     LOAD_CONST                      130: 8623052
        506     LOAD_CONST                      131: 66
        508     MAP_ADD                         1
        510     LOAD_CONST                      132: 16726484
        512     LOAD_CONST                      133: 95
        514     MAP_ADD                         1
        516     LOAD_CONST                      134: 12581632
        518     LOAD_CONST                      135: 86
        520     MAP_ADD                         1
        522     LOAD_CONST                      136: 13958625
        524     LOAD_CONST                      137: 28
        526     MAP_ADD                         1
        528     LOAD_CONST                      138: 12173795
        530     LOAD_CONST                      139: 115
        532     MAP_ADD                         1
        534     LOAD_CONST                      140: 13482980
        536     LOAD_CONST                      141: 116
        538     MAP_ADD                         1
        540     LOAD_CONST                      142: 16777215
        542     LOAD_CONST                      143: 3
        544     MAP_ADD                         1
        546     LOAD_CONST                      144: 6094824
        548     LOAD_CONST                      145: 33
        550     MAP_ADD                         1
        552     LOAD_CONST                      146: 13496824
        554     LOAD_CONST                      147: 114
        556     MAP_ADD                         1
        558     DICT_UPDATE                     1
        560     LOAD_CONST                      148: 92
        562     LOAD_CONST                      149: 36
        564     LOAD_CONST                      150: (9611263, 9160191)
        566     BUILD_CONST_KEY_MAP             2
        568     DICT_UPDATE                     1
        570     STORE_NAME                      10: CLIP_COLOR_TABLE
        572     LOAD_CONST                      151: ((0, 0), (1, 1973790), (2, 8355711), (3, 16777215), (4, 16731212), (5, 16711680), (6, 5832704), (7, 1638400), (8, 16760172), (9, 16733184), (10, 5840128), (11, 2562816), (12, 16777036), (13, 16776960), (14, 5855488), (15, 1644800), (16, 8978252), (17, 5570304), (18, 1923328), (19, 1321728), (20, 5046092), (21, 65280), (22, 22784), (23, 6400), (24, 5046110), (25, 65305), (26, 22797), (27, 6402), (28, 5046152), (29, 65365), (30, 22813), (31, 7954), (32, 5046199), (33, 65433), (34, 22837), (35, 6418), (36, 5030911), (37, 43519), (38, 16722), (39, 4121), (40, 5015807), (41, 22015), (42, 7513), (43, 2073), (44, 5000447), (45, 255), (46, 89), (47, 25), (48, 8867071), (49, 5505279), (50, 1638500), (51, 983088), (52, 16731391), (53, 16711935), (54, 5832793), (55, 1638425), (56, 16731271), (57, 16711764), (58, 5832733), (59, 2228243), (60, 16717056), (61, 10040576), (62, 7950592), (63, 4416512), (64, 211200), (65, 22325), (66, 21631), (67, 255), (68, 17743), (69, 2425036), (70, 8355711), (71, 2105376), (72, 16711680), (73, 12451629), (74, 11529478), (75, 6618889), (76, 1084160), (77, 65415), (78, 43519), (79, 11007), (80, 4129023), (81, 7995647), (82, 11672189), (83, 4202752), (84, 16730624), (85, 8970502), (86, 7536405), (87, 65280), (88, 3931942), (89, 5898097), (90, 3735500), (91, 5999359), (92, 3232198), (93, 8880105), (94, 13835775), (95, 16711773), (96, 16744192), (97, 12169216), (98, 9502464), (99, 8609031), (100, 3746560), (101, 1330192), (102, 872504), (103, 1381674), (104, 1450074), (105, 6896668), (106, 11010058), (107, 14569789), (108, 14182940), (109, 16769318), (110, 10412335), (111, 6796559), (112, 1973808), (113, 14483307), (114, 8454077), (115, 10131967), (116, 9332479), (117, 4210752), (118, 7697781), (119, 14745599), (120, 10485760), (121, 3473408), (122, 1757184), (123, 475648), (124, 12169216), (125, 4141312), (126, 11755264), (127, 4920578))
        574     STORE_NAME                      11: RGB_COLOR_TABLE
        576     LOAD_CONST                      152: None
        578     RETURN_VALUE                    
