launchpad_pro_mk3.pyc (Python 3.11)
[Code]
    File Name: output/Live/mac_universal_64_static/Release/python-bundle/MIDI Remote Scripts/Launchpad_Pro_MK3/launchpad_pro_mk3.py
    Object Name: <module>
    Qualified Name: <module>
    Arg Count: 0
    Pos Only Arg Count: 0
    KW Only Arg Count: 0
    Stack Size: 6
    Flags: 0x00000000
    [Names]
        'functools'
        'partial'
        'ableton.v2.base'
        'const'
        'inject'
        'listens'
        'liveobj_valid'
        'ableton.v2.control_surface'
        'Layer'
        'ableton.v2.control_surface.components'
        'AutoArmComponent'
        'BackgroundComponent'
        'SessionOverviewComponent'
        'UndoRedoComponent'
        'ableton.v2.control_surface.mode'
        'AddLayerMode'
        'DelayMode'
        'ModesComponent'
        'MomentaryBehaviour'
        'ReenterBehaviour'
        'novation'
        'sysex'
        'novation.clip_actions'
        'ClipActionsComponent'
        'novation.colors'
        'Rgb'
        'novation.configurable_playable'
        'ConfigurablePlayableComponent'
        'novation.fixed_length'
        'FixedLengthComponent'
        'FixedLengthSetting'
        'novation.fixed_length_recording'
        'FixedLengthRecording'
        'novation.instrument_control'
        'InstrumentControlMixin'
        'novation.novation_base'
        'NovationBase'
        'novation.print_to_clip'
        'PrintToClipComponent'
        'novation.quantization'
        'QuantizationComponent'
        'novation.simple_device_navigation'
        'SimpleDeviceNavigationComponent'
        'novation.track_recording'
        'FixedLengthTrackRecordingComponent'
        ''
        'sysex_ids'
        'ids'
        'channel_strip'
        'ChannelStripComponent'
        'drum_group'
        'DrumGroupComponent'
        'elements'
        'FADER_MODES'
        'Elements'
        'mixer'
        'MixerComponent'
        'session'
        'SessionComponent'
        'simple_device'
        'SimpleDeviceParameterComponent'
        'skin'
        'transport'
        'TransportComponent'
        'DRUM_FEEDBACK_CHANNEL'
        'SCALE_FEEDBACK_CHANNEL'
        'SESSION_LAYOUT_BYTES'
        'CHORD_LAYOUT_BYTES'
        'NOTE_LAYOUT_BYTES'
        'LAYOUT_BYTES_TO_MODE_NAMES_MAP'
        'FADER_LAYOUT_BYTE'
        'LIVE_LAYOUT_BYTES'
        'NOTE_MODE_NAMES'
        'Launchpad_Pro_MK3'
    [Locals+Names]
    [Constants]
        0
        (
            'partial'
        )
        (
            'const'
            'inject'
            'listens'
            'liveobj_valid'
        )
        (
            'Layer'
        )
        (
            'AutoArmComponent'
            'BackgroundComponent'
            'SessionOverviewComponent'
            'UndoRedoComponent'
        )
        (
            'AddLayerMode'
            'DelayMode'
            'ModesComponent'
            'MomentaryBehaviour'
            'ReenterBehaviour'
        )
        (
            'sysex'
        )
        (
            'ClipActionsComponent'
        )
        (
            'Rgb'
        )
        (
            'ConfigurablePlayableComponent'
        )
        (
            'FixedLengthComponent'
            'FixedLengthSetting'
        )
        (
            'FixedLengthRecording'
        )
        (
            'InstrumentControlMixin'
        )
        (
            'NovationBase'
        )
        (
            'PrintToClipComponent'
        )
        (
            'QuantizationComponent'
        )
        (
            'SimpleDeviceNavigationComponent'
        )
        (
            'FixedLengthTrackRecordingComponent'
        )
        1
        (
            'sysex_ids'
        )
        (
            'ChannelStripComponent'
        )
        (
            'DrumGroupComponent'
        )
        (
            'FADER_MODES'
            'Elements'
        )
        (
            'MixerComponent'
        )
        (
            'SessionComponent'
        )
        (
            'SimpleDeviceParameterComponent'
        )
        (
            'skin'
        )
        (
            'TransportComponent'
        )
        2
        'session'
        'chord'
        'note'
        (
            'chord'
            'note'
        )
        [Code]
            File Name: output/Live/mac_universal_64_static/Release/python-bundle/MIDI Remote Scripts/Launchpad_Pro_MK3/launchpad_pro_mk3.py
            Object Name: Launchpad_Pro_MK3
            Qualified Name: Launchpad_Pro_MK3
            Arg Count: 0
            Pos Only Arg Count: 0
            KW Only Arg Count: 0
            Stack Size: 3
            Flags: 0x00000000
            [Names]
                '__name__'
                '__module__'
                '__qualname__'
                'ids'
                'LP_PRO_MK3_FAMILY_CODE'
                'model_family_code'
                'Elements'
                'element_class'
                'SessionComponent'
                'session_class'
                'MixerComponent'
                'mixer_class'
                'ChannelStripComponent'
                'channel_strip_class'
                'skin'
                'suppress_layout_switch'
                'FixedLengthTrackRecordingComponent'
                'track_recording_class'
                '__init__'
                'disconnect'
                'on_identified'
                'port_settings_changed'
                '_setup_faders'
                '_create_components'
                '_create_session_overview'
                '_create_auto_arm'
                '_create_background'
                '_create_print_to_clip'
                '_create_undo_redo'
                '_create_transport'
                '_create_clip_actions'
                '_create_quantization'
                '_create_fixed_length'
                '_create_drum_group'
                '_create_device_parameters'
                '_create_device_navigation'
                '_create_scale_pad_translator'
                '_create_mixer_modes'
                '_create_session_modes'
                '_create_note_modes'
                '_create_main_modes'
                'listens'
                '_Launchpad_Pro_MK3__on_main_mode_changed'
                '_Launchpad_Pro_MK3__on_layout_switch_value'
                '_drum_group_changed'
                '_is_instrument_mode'
                '_feedback_velocity_changed'
                '__classcell__'
            [Locals+Names]
                '__class__'
            [Constants]
                'Launchpad_Pro_MK3'
                False
                [Code]
                    File Name: output/Live/mac_universal_64_static/Release/python-bundle/MIDI Remote Scripts/Launchpad_Pro_MK3/launchpad_pro_mk3.py
                    Object Name: __init__
                    Qualified Name: Launchpad_Pro_MK3.__init__
                    Arg Count: 1
                    Pos Only Arg Count: 0
                    KW Only Arg Count: 0
                    Stack Size: 5
                    Flags: 0x0000000F (CO_OPTIMIZED | CO_NEWLOCALS | CO_VARARGS | CO_VARKEYWORDS)
                    [Names]
                        '_layout_to_restore'
                        '_can_restore_layout'
                        'ids'
                        'SESSION_LAYOUT_BYTES'
                        '_last_layout_bytes'
                        'super'
                        'Launchpad_Pro_MK3'
                        '__init__'
                    [Locals+Names]
                        'self'
                        'a'
                        'k'
                        '__class__'
                    [Constants]
                        None
                        False
                    [Disassembly]
                        0       COPY_FREE_VARS                  1
                        2       RESUME                          0
                        4       LOAD_CONST                      0: None
                        6       LOAD_FAST                       0: self
                        8       STORE_ATTR                      0: _layout_to_restore
                        18      LOAD_CONST                      1: False
                        20      LOAD_FAST                       0: self
                        22      STORE_ATTR                      1: _can_restore_layout
                        32      LOAD_GLOBAL                     4: ids
                        44      LOAD_ATTR                       3: SESSION_LAYOUT_BYTES
                        54      LOAD_FAST                       0: self
                        56      STORE_ATTR                      4: _last_layout_bytes
                        66      PUSH_NULL                       
                        68      LOAD_GLOBAL                     11: NULL + super
                        80      LOAD_GLOBAL                     12: Launchpad_Pro_MK3
                        92      LOAD_FAST                       0: self
                        94      PRECALL                         2
                        98      CALL                            2
                        108     LOAD_ATTR                       7: __init__
                        118     LOAD_FAST                       1: a
                        120     BUILD_MAP                       0
                        122     LOAD_FAST                       2: k
                        124     DICT_MERGE                      1
                        126     CALL_FUNCTION_EX                1
                        128     POP_TOP                         
                        130     LOAD_CONST                      0: None
                        132     RETURN_VALUE                    
                [Code]
                    File Name: output/Live/mac_universal_64_static/Release/python-bundle/MIDI Remote Scripts/Launchpad_Pro_MK3/launchpad_pro_mk3.py
                    Object Name: disconnect
                    Qualified Name: Launchpad_Pro_MK3.disconnect
                    Arg Count: 1
                    Pos Only Arg Count: 0
                    KW Only Arg Count: 0
                    Stack Size: 4
                    Flags: 0x00000003 (CO_OPTIMIZED | CO_NEWLOCALS)
                    [Names]
                        'super'
                        'Launchpad_Pro_MK3'
                        'disconnect'
                        '_auto_arm'
                        'set_enabled'
                        '_elements'
                        'scale_feedback_switch'
                        'send_value'
                        'Rgb'
                        'GREEN'
                        'midi_value'
                    [Locals+Names]
                        'self'
                        '__class__'
                    [Constants]
                        None
                        False
                    [Disassembly]
                        0       COPY_FREE_VARS                  1
                        2       RESUME                          0
                        4       LOAD_GLOBAL                     1: NULL + super
                        16      LOAD_GLOBAL                     2: Launchpad_Pro_MK3
                        28      LOAD_FAST                       0: self
                        30      PRECALL                         2
                        34      CALL                            2
                        44      LOAD_METHOD                     2: disconnect
                        66      PRECALL                         0
                        70      CALL                            0
                        80      POP_TOP                         
                        82      LOAD_FAST                       0: self
                        84      LOAD_ATTR                       3: _auto_arm
                        94      LOAD_METHOD                     4: set_enabled
                        116     LOAD_CONST                      1: False
                        118     PRECALL                         1
                        122     CALL                            1
                        132     POP_TOP                         
                        134     LOAD_FAST                       0: self
                        136     LOAD_ATTR                       5: _elements
                        146     LOAD_ATTR                       6: scale_feedback_switch
                        156     LOAD_METHOD                     7: send_value
                        178     LOAD_GLOBAL                     16: Rgb
                        190     LOAD_ATTR                       9: GREEN
                        200     LOAD_ATTR                       10: midi_value
                        210     PRECALL                         1
                        214     CALL                            1
                        224     POP_TOP                         
                        226     LOAD_CONST                      0: None
                        228     RETURN_VALUE                    
                [Code]
                    File Name: output/Live/mac_universal_64_static/Release/python-bundle/MIDI Remote Scripts/Launchpad_Pro_MK3/launchpad_pro_mk3.py
                    Object Name: on_identified
                    Qualified Name: Launchpad_Pro_MK3.on_identified
                    Arg Count: 2
                    Pos Only Arg Count: 0
                    KW Only Arg Count: 0
                    Stack Size: 4
                    Flags: 0x00000003 (CO_OPTIMIZED | CO_NEWLOCALS)
                    [Names]
                        '_elements'
                        'firmware_mode_switch'
                        'send_value'
                        'sysex'
                        'DAW_MODE_BYTE'
                        'layout_switch'
                        '_last_layout_bytes'
                        '_target_track_changed'
                        '_drum_group_changed'
                        'set_feedback_channels'
                        'DRUM_FEEDBACK_CHANNEL'
                        'SCALE_FEEDBACK_CHANNEL'
                        '_setup_faders'
                        'super'
                        'Launchpad_Pro_MK3'
                        'on_identified'
                    [Locals+Names]
                        'self'
                        'midi_bytes'
                        '__class__'
                    [Constants]
                        None
                    [Disassembly]
                        0       COPY_FREE_VARS                  1
                        2       RESUME                          0
                        4       LOAD_FAST                       0: self
                        6       LOAD_ATTR                       0: _elements
                        16      LOAD_ATTR                       1: firmware_mode_switch
                        26      LOAD_METHOD                     2: send_value
                        48      LOAD_GLOBAL                     6: sysex
                        60      LOAD_ATTR                       4: DAW_MODE_BYTE
                        70      PRECALL                         1
                        74      CALL                            1
                        84      POP_TOP                         
                        86      LOAD_FAST                       0: self
                        88      LOAD_ATTR                       0: _elements
                        98      LOAD_ATTR                       5: layout_switch
                        108     LOAD_METHOD                     2: send_value
                        130     LOAD_FAST                       0: self
                        132     LOAD_ATTR                       6: _last_layout_bytes
                        142     PRECALL                         1
                        146     CALL                            1
                        156     POP_TOP                         
                        158     LOAD_FAST                       0: self
                        160     LOAD_METHOD                     7: _target_track_changed
                        182     PRECALL                         0
                        186     CALL                            0
                        196     POP_TOP                         
                        198     LOAD_FAST                       0: self
                        200     LOAD_METHOD                     8: _drum_group_changed
                        222     PRECALL                         0
                        226     CALL                            0
                        236     POP_TOP                         
                        238     LOAD_FAST                       0: self
                        240     LOAD_METHOD                     9: set_feedback_channels
                        262     LOAD_GLOBAL                     20: DRUM_FEEDBACK_CHANNEL
                        274     LOAD_GLOBAL                     22: SCALE_FEEDBACK_CHANNEL
                        286     BUILD_LIST                      2
                        288     PRECALL                         1
                        292     CALL                            1
                        302     POP_TOP                         
                        304     LOAD_FAST                       0: self
                        306     LOAD_METHOD                     12: _setup_faders
                        328     PRECALL                         0
                        332     CALL                            0
                        342     POP_TOP                         
                        344     LOAD_GLOBAL                     27: NULL + super
                        356     LOAD_GLOBAL                     28: Launchpad_Pro_MK3
                        368     LOAD_FAST                       0: self
                        370     PRECALL                         2
                        374     CALL                            2
                        384     LOAD_METHOD                     15: on_identified
                        406     LOAD_FAST                       1: midi_bytes
                        408     PRECALL                         1
                        412     CALL                            1
                        422     POP_TOP                         
                        424     LOAD_CONST                      0: None
                        426     RETURN_VALUE                    
                [Code]
                    File Name: output/Live/mac_universal_64_static/Release/python-bundle/MIDI Remote Scripts/Launchpad_Pro_MK3/launchpad_pro_mk3.py
                    Object Name: port_settings_changed
                    Qualified Name: Launchpad_Pro_MK3.port_settings_changed
                    Arg Count: 1
                    Pos Only Arg Count: 0
                    KW Only Arg Count: 0
                    Stack Size: 4
                    Flags: 0x00000003 (CO_OPTIMIZED | CO_NEWLOCALS)
                    [Names]
                        '_auto_arm'
                        'set_enabled'
                        'super'
                        'Launchpad_Pro_MK3'
                        'port_settings_changed'
                    [Locals+Names]
                        'self'
                        '__class__'
                    [Constants]
                        None
                        False
                    [Disassembly]
                        0       COPY_FREE_VARS                  1
                        2       RESUME                          0
                        4       LOAD_FAST                       0: self
                        6       LOAD_ATTR                       0: _auto_arm
                        16      LOAD_METHOD                     1: set_enabled
                        38      LOAD_CONST                      1: False
                        40      PRECALL                         1
                        44      CALL                            1
                        54      POP_TOP                         
                        56      LOAD_GLOBAL                     5: NULL + super
                        68      LOAD_GLOBAL                     6: Launchpad_Pro_MK3
                        80      LOAD_FAST                       0: self
                        82      PRECALL                         2
                        86      CALL                            2
                        96      LOAD_METHOD                     4: port_settings_changed
                        118     PRECALL                         0
                        122     CALL                            0
                        132     POP_TOP                         
                        134     LOAD_CONST                      0: None
                        136     RETURN_VALUE                    
                [Code]
                    File Name: output/Live/mac_universal_64_static/Release/python-bundle/MIDI Remote Scripts/Launchpad_Pro_MK3/launchpad_pro_mk3.py
                    Object Name: _setup_faders
                    Qualified Name: Launchpad_Pro_MK3._setup_faders
                    Arg Count: 1
                    Pos Only Arg Count: 0
                    KW Only Arg Count: 0
                    Stack Size: 6
                    Flags: 0x00000003 (CO_OPTIMIZED | CO_NEWLOCALS)
                    [Names]
                        'enumerate'
                        'FADER_MODES'
                        'sysex'
                        'FADER_HORIZONTAL_ORIENTATION'
                        'FADER_BIPOLAR'
                        'FADER_VERTICAL_ORIENTATION'
                        'FADER_UNIPOLAR'
                        '_elements'
                        'fader_setup_element'
                        'send_value'
                    [Locals+Names]
                        'self'
                        'i'
                        'fader_mode'
                        'orientation'
                        'polarity'
                    [Constants]
                        None
                        'pan'
                    [Disassembly]
                        0       RESUME                          0
                        2       LOAD_GLOBAL                     1: NULL + enumerate
                        14      LOAD_GLOBAL                     2: FADER_MODES
                        26      PRECALL                         1
                        30      CALL                            1
                        40      GET_ITER                        
                        42      FOR_ITER                        95 (to 234)
                        44      UNPACK_SEQUENCE                 2
                        48      STORE_FAST                      1: i
                        50      STORE_FAST                      2: fader_mode
                        52      LOAD_FAST                       2: fader_mode
                        54      LOAD_CONST                      1: 'pan'
                        56      COMPARE_OP                      2 (==)
                        62      POP_JUMP_FORWARD_IF_FALSE       24 (to 112)
                        64      LOAD_GLOBAL                     4: sysex
                        76      LOAD_ATTR                       3: FADER_HORIZONTAL_ORIENTATION
                        86      LOAD_GLOBAL                     4: sysex
                        98      LOAD_ATTR                       4: FADER_BIPOLAR
                        108     BUILD_TUPLE                     2
                        110     JUMP_FORWARD                    23 (to 158)
                        112     LOAD_GLOBAL                     4: sysex
                        124     LOAD_ATTR                       5: FADER_VERTICAL_ORIENTATION
                        134     LOAD_GLOBAL                     4: sysex
                        146     LOAD_ATTR                       6: FADER_UNIPOLAR
                        156     BUILD_TUPLE                     2
                        158     UNPACK_SEQUENCE                 2
                        162     STORE_FAST                      3: orientation
                        164     STORE_FAST                      4: polarity
                        166     LOAD_FAST                       0: self
                        168     LOAD_ATTR                       7: _elements
                        178     LOAD_ATTR                       8: fader_setup_element
                        188     LOAD_METHOD                     9: send_value
                        210     LOAD_FAST                       1: i
                        212     LOAD_FAST                       3: orientation
                        214     LOAD_FAST                       4: polarity
                        216     PRECALL                         3
                        220     CALL                            3
                        230     POP_TOP                         
                        232     JUMP_BACKWARD                   96 (to 42)
                        234     LOAD_CONST                      0: None
                        236     RETURN_VALUE                    
                [Code]
                    File Name: output/Live/mac_universal_64_static/Release/python-bundle/MIDI Remote Scripts/Launchpad_Pro_MK3/launchpad_pro_mk3.py
                    Object Name: _create_components
                    Qualified Name: Launchpad_Pro_MK3._create_components
                    Arg Count: 1
                    Pos Only Arg Count: 0
                    KW Only Arg Count: 0
                    Stack Size: 6
                    Flags: 0x00000003 (CO_OPTIMIZED | CO_NEWLOCALS)
                    [Names]
                        'FixedLengthSetting'
                        '_fixed_length_setting'
                        'FixedLengthRecording'
                        'song'
                        '_fixed_length_recording'
                        '_create_quantization'
                        'inject'
                        'const'
                        '_quantization'
                        'everywhere'
                        'super'
                        'Launchpad_Pro_MK3'
                        '_create_components'
                        '_create_recording_modes'
                        '_create_session_overview'
                        '_create_auto_arm'
                        '_create_background'
                        '_create_device_navigation'
                        '_create_device_parameters'
                        '_create_print_to_clip'
                        '_create_undo_redo'
                        '_create_transport'
                        '_create_clip_actions'
                        '_create_fixed_length'
                        '_create_drum_group'
                        '_create_scale_pad_translator'
                        '_create_mixer_modes'
                        '_create_session_modes'
                        '_create_note_modes'
                        '_create_main_modes'
                        '_elements'
                        'layout_switch'
                        '_Launchpad_Pro_MK3__on_layout_switch_value'
                        'subject'
                    [Locals+Names]
                        'self'
                        '__class__'
                    [Constants]
                        None
                        (
                            'fixed_length_recording'
                            'quantization_component'
                        )
                    [Disassembly]
                        0       COPY_FREE_VARS                  1
                        2       RESUME                          0
                        4       LOAD_GLOBAL                     1: NULL + FixedLengthSetting
                        16      PRECALL                         0
                        20      CALL                            0
                        30      LOAD_FAST                       0: self
                        32      STORE_ATTR                      1: _fixed_length_setting
                        42      LOAD_GLOBAL                     5: NULL + FixedLengthRecording
                        54      LOAD_FAST                       0: self
                        56      LOAD_ATTR                       3: song
                        66      LOAD_FAST                       0: self
                        68      LOAD_ATTR                       1: _fixed_length_setting
                        78      PRECALL                         2
                        82      CALL                            2
                        92      LOAD_FAST                       0: self
                        94      STORE_ATTR                      4: _fixed_length_recording
                        104     LOAD_FAST                       0: self
                        106     LOAD_METHOD                     5: _create_quantization
                        128     PRECALL                         0
                        132     CALL                            0
                        142     POP_TOP                         
                        144     LOAD_GLOBAL                     13: NULL + inject
                        156     LOAD_GLOBAL                     15: NULL + const
                        168     LOAD_FAST                       0: self
                        170     LOAD_ATTR                       4: _fixed_length_recording
                        180     PRECALL                         1
                        184     CALL                            1
                        194     LOAD_GLOBAL                     15: NULL + const
                        206     LOAD_FAST                       0: self
                        208     LOAD_ATTR                       8: _quantization
                        218     PRECALL                         1
                        222     CALL                            1
                        232     KW_NAMES                        1: ('fixed_length_recording', 'quantization_component')
                        234     PRECALL                         2
                        238     CALL                            2
                        248     LOAD_METHOD                     9: everywhere
                        270     PRECALL                         0
                        274     CALL                            0
                        284     BEFORE_WITH                     
                        286     POP_TOP                         
                        288     LOAD_GLOBAL                     21: NULL + super
                        300     LOAD_GLOBAL                     22: Launchpad_Pro_MK3
                        312     LOAD_FAST                       0: self
                        314     PRECALL                         2
                        318     CALL                            2
                        328     LOAD_METHOD                     12: _create_components
                        350     PRECALL                         0
                        354     CALL                            0
                        364     POP_TOP                         
                        366     LOAD_FAST                       0: self
                        368     LOAD_METHOD                     13: _create_recording_modes
                        390     PRECALL                         0
                        394     CALL                            0
                        404     POP_TOP                         
                        406     LOAD_CONST                      0: None
                        408     LOAD_CONST                      0: None
                        410     LOAD_CONST                      0: None
                        412     PRECALL                         2
                        416     CALL                            2
                        426     POP_TOP                         
                        428     JUMP_FORWARD                    11 (to 452)
                        430     PUSH_EXC_INFO                   
                        432     WITH_EXCEPT_START               
                        434     POP_JUMP_FORWARD_IF_TRUE        4 (to 444)
                        436     RERAISE                         2
                        438     COPY                            3
                        440     POP_EXCEPT                      
                        442     RERAISE                         1
                        444     POP_TOP                         
                        446     POP_EXCEPT                      
                        448     POP_TOP                         
                        450     POP_TOP                         
                        452     LOAD_FAST                       0: self
                        454     LOAD_METHOD                     14: _create_session_overview
                        476     PRECALL                         0
                        480     CALL                            0
                        490     POP_TOP                         
                        492     LOAD_FAST                       0: self
                        494     LOAD_METHOD                     15: _create_auto_arm
                        516     PRECALL                         0
                        520     CALL                            0
                        530     POP_TOP                         
                        532     LOAD_FAST                       0: self
                        534     LOAD_METHOD                     16: _create_background
                        556     PRECALL                         0
                        560     CALL                            0
                        570     POP_TOP                         
                        572     LOAD_FAST                       0: self
                        574     LOAD_METHOD                     17: _create_device_navigation
                        596     PRECALL                         0
                        600     CALL                            0
                        610     POP_TOP                         
                        612     LOAD_FAST                       0: self
                        614     LOAD_METHOD                     18: _create_device_parameters
                        636     PRECALL                         0
                        640     CALL                            0
                        650     POP_TOP                         
                        652     LOAD_FAST                       0: self
                        654     LOAD_METHOD                     19: _create_print_to_clip
                        676     PRECALL                         0
                        680     CALL                            0
                        690     POP_TOP                         
                        692     LOAD_FAST                       0: self
                        694     LOAD_METHOD                     20: _create_undo_redo
                        716     PRECALL                         0
                        720     CALL                            0
                        730     POP_TOP                         
                        732     LOAD_FAST                       0: self
                        734     LOAD_METHOD                     21: _create_transport
                        756     PRECALL                         0
                        760     CALL                            0
                        770     POP_TOP                         
                        772     LOAD_FAST                       0: self
                        774     LOAD_METHOD                     22: _create_clip_actions
                        796     PRECALL                         0
                        800     CALL                            0
                        810     POP_TOP                         
                        812     LOAD_FAST                       0: self
                        814     LOAD_METHOD                     23: _create_fixed_length
                        836     PRECALL                         0
                        840     CALL                            0
                        850     POP_TOP                         
                        852     LOAD_FAST                       0: self
                        854     LOAD_METHOD                     24: _create_drum_group
                        876     PRECALL                         0
                        880     CALL                            0
                        890     POP_TOP                         
                        892     LOAD_FAST                       0: self
                        894     LOAD_METHOD                     25: _create_scale_pad_translator
                        916     PRECALL                         0
                        920     CALL                            0
                        930     POP_TOP                         
                        932     LOAD_FAST                       0: self
                        934     LOAD_METHOD                     26: _create_mixer_modes
                        956     PRECALL                         0
                        960     CALL                            0
                        970     POP_TOP                         
                        972     LOAD_FAST                       0: self
                        974     LOAD_METHOD                     27: _create_session_modes
                        996     PRECALL                         0
                        1000    CALL                            0
                        1010    POP_TOP                         
                        1012    LOAD_FAST                       0: self
                        1014    LOAD_METHOD                     28: _create_note_modes
                        1036    PRECALL                         0
                        1040    CALL                            0
                        1050    POP_TOP                         
                        1052    LOAD_FAST                       0: self
                        1054    LOAD_METHOD                     29: _create_main_modes
                        1076    PRECALL                         0
                        1080    CALL                            0
                        1090    POP_TOP                         
                        1092    LOAD_FAST                       0: self
                        1094    LOAD_ATTR                       30: _elements
                        1104    LOAD_ATTR                       31: layout_switch
                        1114    LOAD_FAST                       0: self
                        1116    LOAD_ATTR                       32: _Launchpad_Pro_MK3__on_layout_switch_value
                        1126    STORE_ATTR                      33: subject
                        1136    LOAD_CONST                      0: None
                        1138    RETURN_VALUE                    
                [Code]
                    File Name: output/Live/mac_universal_64_static/Release/python-bundle/MIDI Remote Scripts/Launchpad_Pro_MK3/launchpad_pro_mk3.py
                    Object Name: _create_session_overview
                    Qualified Name: Launchpad_Pro_MK3._create_session_overview
                    Arg Count: 1
                    Pos Only Arg Count: 0
                    KW Only Arg Count: 0
                    Stack Size: 9
                    Flags: 0x00000003 (CO_OPTIMIZED | CO_NEWLOCALS)
                    [Names]
                        'SessionOverviewComponent'
                        '_session_ring'
                        'Layer'
                        '_session_overview'
                    [Locals+Names]
                        'self'
                    [Constants]
                        None
                        'Session_Overview'
                        False
                        True
                        'clip_launch_matrix'
                        (
                            'button_matrix'
                        )
                        (
                            'name'
                            'is_enabled'
                            'session_ring'
                            'enable_skinning'
                            'layer'
                        )
                    [Disassembly]
                        0       RESUME                          0
                        2       LOAD_GLOBAL                     1: NULL + SessionOverviewComponent
                        14      LOAD_CONST                      1: 'Session_Overview'
                        16      LOAD_CONST                      2: False
                        18      LOAD_FAST                       0: self
                        20      LOAD_ATTR                       1: _session_ring
                        30      LOAD_CONST                      3: True
                        32      LOAD_GLOBAL                     5: NULL + Layer
                        44      LOAD_CONST                      4: 'clip_launch_matrix'
                        46      KW_NAMES                        5: ('button_matrix',)
                        48      PRECALL                         1
                        52      CALL                            1
                        62      KW_NAMES                        6: ('name', 'is_enabled', 'session_ring', 'enable_skinning', 'layer')
                        64      PRECALL                         5
                        68      CALL                            5
                        78      LOAD_FAST                       0: self
                        80      STORE_ATTR                      3: _session_overview
                        90      LOAD_CONST                      0: None
                        92      RETURN_VALUE                    
                [Code]
                    File Name: output/Live/mac_universal_64_static/Release/python-bundle/MIDI Remote Scripts/Launchpad_Pro_MK3/launchpad_pro_mk3.py
                    Object Name: _create_auto_arm
                    Qualified Name: Launchpad_Pro_MK3._create_auto_arm
                    Arg Count: 1
                    Pos Only Arg Count: 0
                    KW Only Arg Count: 0
                    Stack Size: 4
                    Flags: 0x00000003 (CO_OPTIMIZED | CO_NEWLOCALS)
                    [Names]
                        'AutoArmComponent'
                        '_auto_arm'
                    [Locals+Names]
                        'self'
                    [Constants]
                        None
                        'Auto_Arm'
                        False
                        (
                            'name'
                            'is_enabled'
                        )
                    [Disassembly]
                        0       RESUME                          0
                        2       LOAD_GLOBAL                     1: NULL + AutoArmComponent
                        14      LOAD_CONST                      1: 'Auto_Arm'
                        16      LOAD_CONST                      2: False
                        18      KW_NAMES                        3: ('name', 'is_enabled')
                        20      PRECALL                         2
                        24      CALL                            2
                        34      LOAD_FAST                       0: self
                        36      STORE_ATTR                      1: _auto_arm
                        46      LOAD_CONST                      0: None
                        48      RETURN_VALUE                    
                [Code]
                    File Name: output/Live/mac_universal_64_static/Release/python-bundle/MIDI Remote Scripts/Launchpad_Pro_MK3/launchpad_pro_mk3.py
                    Object Name: _create_background
                    Qualified Name: Launchpad_Pro_MK3._create_background
                    Arg Count: 1
                    Pos Only Arg Count: 0
                    KW Only Arg Count: 0
                    Stack Size: 22
                    Flags: 0x00000003 (CO_OPTIMIZED | CO_NEWLOCALS)
                    [Names]
                        'BackgroundComponent'
                        'Layer'
                        '_background'
                        'set_enabled'
                    [Locals+Names]
                        'self'
                    [Constants]
                        None
                        'Background'
                        False
                        True
                        'clear_button'
                        'duplicate_button'
                        'quantize_button'
                        'scene_launch_buttons'
                        -1
                        (
                            'clear_button'
                            'duplicate_button'
                            'quantize_button'
                            'scene_launch_buttons'
                            'priority'
                        )
                        'duplicate_button_with_shift'
                        'track_select_buttons_with_shift'
                        'up_button_with_shift'
                        'down_button_with_shift'
                        'left_button_with_shift'
                        'right_button_with_shift'
                        'clear_button_with_shift'
                        'volume_button_with_shift'
                        'pan_button_with_shift'
                        'sends_button_with_shift'
                        'device_button_with_shift'
                        'stop_clip_button_with_shift'
                        'fixed_length_button_with_shift'
                        (
                            'duplicate_button_with_shift'
                            'track_select_buttons_with_shift'
                            'up_button_with_shift'
                            'down_button_with_shift'
                            'left_button_with_shift'
                            'right_button_with_shift'
                            'double_button'
                            'clear_button_with_shift'
                            'volume_button_with_shift'
                            'pan_button_with_shift'
                            'sends_button_with_shift'
                            'device_button_with_shift'
                            'stop_clip_button_with_shift'
                            'fixed_length_button_with_shift'
                        )
                        (
                            'name'
                            'is_enabled'
                            'add_nop_listeners'
                            'layer'
                        )
                    [Disassembly]
                        0       RESUME                          0
                        2       LOAD_GLOBAL                     1: NULL + BackgroundComponent
                        14      LOAD_CONST                      1: 'Background'
                        16      LOAD_CONST                      2: False
                        18      LOAD_CONST                      3: True
                        20      LOAD_GLOBAL                     3: NULL + Layer
                        32      LOAD_CONST                      4: 'clear_button'
                        34      LOAD_CONST                      5: 'duplicate_button'
                        36      LOAD_CONST                      6: 'quantize_button'
                        38      LOAD_CONST                      7: 'scene_launch_buttons'
                        40      LOAD_CONST                      8: -1
                        42      KW_NAMES                        9: ('clear_button', 'duplicate_button', 'quantize_button', 'scene_launch_buttons', 'priority')
                        44      PRECALL                         5
                        48      CALL                            5
                        58      LOAD_GLOBAL                     3: NULL + Layer
                        70      LOAD_CONST                      10: 'duplicate_button_with_shift'
                        72      LOAD_CONST                      11: 'track_select_buttons_with_shift'
                        74      LOAD_CONST                      12: 'up_button_with_shift'
                        76      LOAD_CONST                      13: 'down_button_with_shift'
                        78      LOAD_CONST                      14: 'left_button_with_shift'
                        80      LOAD_CONST                      15: 'right_button_with_shift'
                        82      LOAD_CONST                      10: 'duplicate_button_with_shift'
                        84      LOAD_CONST                      16: 'clear_button_with_shift'
                        86      LOAD_CONST                      17: 'volume_button_with_shift'
                        88      LOAD_CONST                      18: 'pan_button_with_shift'
                        90      LOAD_CONST                      19: 'sends_button_with_shift'
                        92      LOAD_CONST                      20: 'device_button_with_shift'
                        94      LOAD_CONST                      21: 'stop_clip_button_with_shift'
                        96      LOAD_CONST                      22: 'fixed_length_button_with_shift'
                        98      KW_NAMES                        23: ('duplicate_button_with_shift', 'track_select_buttons_with_shift', 'up_button_with_shift', 'down_button_with_shift', 'left_button_with_shift', 'right_button_with_shift', 'double_button', 'clear_button_with_shift', 'volume_button_with_shift', 'pan_button_with_shift', 'sends_button_with_shift', 'device_button_with_shift', 'stop_clip_button_with_shift', 'fixed_length_button_with_shift')
                        100     PRECALL                         14
                        104     CALL                            14
                        114     BINARY_OP                       0 (+)
                        118     KW_NAMES                        24: ('name', 'is_enabled', 'add_nop_listeners', 'layer')
                        120     PRECALL                         4
                        124     CALL                            4
                        134     LOAD_FAST                       0: self
                        136     STORE_ATTR                      2: _background
                        146     LOAD_FAST                       0: self
                        148     LOAD_ATTR                       2: _background
                        158     LOAD_METHOD                     3: set_enabled
                        180     LOAD_CONST                      3: True
                        182     PRECALL                         1
                        186     CALL                            1
                        196     POP_TOP                         
                        198     LOAD_CONST                      0: None
                        200     RETURN_VALUE                    
                [Code]
                    File Name: output/Live/mac_universal_64_static/Release/python-bundle/MIDI Remote Scripts/Launchpad_Pro_MK3/launchpad_pro_mk3.py
                    Object Name: _create_print_to_clip
                    Qualified Name: Launchpad_Pro_MK3._create_print_to_clip
                    Arg Count: 1
                    Pos Only Arg Count: 0
                    KW Only Arg Count: 0
                    Stack Size: 8
                    Flags: 0x00000003 (CO_OPTIMIZED | CO_NEWLOCALS)
                    [Names]
                        'PrintToClipComponent'
                        'Layer'
                        '_print_to_clip'
                        'set_enabled'
                    [Locals+Names]
                        'self'
                    [Constants]
                        None
                        'Print_To_Clip'
                        False
                        'print_to_clip_element'
                        'print_to_clip_enabler_element'
                        (
                            'print_to_clip_control'
                            'print_to_clip_enabler'
                        )
                        (
                            'name'
                            'is_enabled'
                            'layer'
                        )
                        True
                    [Disassembly]
                        0       RESUME                          0
                        2       LOAD_GLOBAL                     1: NULL + PrintToClipComponent
                        14      LOAD_CONST                      1: 'Print_To_Clip'
                        16      LOAD_CONST                      2: False
                        18      LOAD_GLOBAL                     3: NULL + Layer
                        30      LOAD_CONST                      3: 'print_to_clip_element'
                        32      LOAD_CONST                      4: 'print_to_clip_enabler_element'
                        34      KW_NAMES                        5: ('print_to_clip_control', 'print_to_clip_enabler')
                        36      PRECALL                         2
                        40      CALL                            2
                        50      KW_NAMES                        6: ('name', 'is_enabled', 'layer')
                        52      PRECALL                         3
                        56      CALL                            3
                        66      LOAD_FAST                       0: self
                        68      STORE_ATTR                      2: _print_to_clip
                        78      LOAD_FAST                       0: self
                        80      LOAD_ATTR                       2: _print_to_clip
                        90      LOAD_METHOD                     3: set_enabled
                        112     LOAD_CONST                      7: True
                        114     PRECALL                         1
                        118     CALL                            1
                        128     POP_TOP                         
                        130     LOAD_CONST                      0: None
                        132     RETURN_VALUE                    
                [Code]
                    File Name: output/Live/mac_universal_64_static/Release/python-bundle/MIDI Remote Scripts/Launchpad_Pro_MK3/launchpad_pro_mk3.py
                    Object Name: _create_undo_redo
                    Qualified Name: Launchpad_Pro_MK3._create_undo_redo
                    Arg Count: 1
                    Pos Only Arg Count: 0
                    KW Only Arg Count: 0
                    Stack Size: 8
                    Flags: 0x00000003 (CO_OPTIMIZED | CO_NEWLOCALS)
                    [Names]
                        'UndoRedoComponent'
                        'Layer'
                        '_undo_redo'
                        'undo_button'
                        'color'
                        'pressed_color'
                        'redo_button'
                        'set_enabled'
                    [Locals+Names]
                        'self'
                    [Constants]
                        None
                        'Undo_Redo'
                        False
                        'record_arm_button_with_shift'
                        'mute_button_with_shift'
                        (
                            'undo_button'
                            'redo_button'
                        )
                        (
                            'name'
                            'is_enabled'
                            'layer'
                        )
                        'Action.Undo'
                        'Action.UndoPressed'
                        'Action.Redo'
                        'Action.RedoPressed'
                        True
                    [Disassembly]
                        0       RESUME                          0
                        2       LOAD_GLOBAL                     1: NULL + UndoRedoComponent
                        14      LOAD_CONST                      1: 'Undo_Redo'
                        16      LOAD_CONST                      2: False
                        18      LOAD_GLOBAL                     3: NULL + Layer
                        30      LOAD_CONST                      3: 'record_arm_button_with_shift'
                        32      LOAD_CONST                      4: 'mute_button_with_shift'
                        34      KW_NAMES                        5: ('undo_button', 'redo_button')
                        36      PRECALL                         2
                        40      CALL                            2
                        50      KW_NAMES                        6: ('name', 'is_enabled', 'layer')
                        52      PRECALL                         3
                        56      CALL                            3
                        66      LOAD_FAST                       0: self
                        68      STORE_ATTR                      2: _undo_redo
                        78      LOAD_CONST                      7: 'Action.Undo'
                        80      LOAD_FAST                       0: self
                        82      LOAD_ATTR                       2: _undo_redo
                        92      LOAD_ATTR                       3: undo_button
                        102     STORE_ATTR                      4: color
                        112     LOAD_CONST                      8: 'Action.UndoPressed'
                        114     LOAD_FAST                       0: self
                        116     LOAD_ATTR                       2: _undo_redo
                        126     LOAD_ATTR                       3: undo_button
                        136     STORE_ATTR                      5: pressed_color
                        146     LOAD_CONST                      9: 'Action.Redo'
                        148     LOAD_FAST                       0: self
                        150     LOAD_ATTR                       2: _undo_redo
                        160     LOAD_ATTR                       6: redo_button
                        170     STORE_ATTR                      4: color
                        180     LOAD_CONST                      10: 'Action.RedoPressed'
                        182     LOAD_FAST                       0: self
                        184     LOAD_ATTR                       2: _undo_redo
                        194     LOAD_ATTR                       6: redo_button
                        204     STORE_ATTR                      5: pressed_color
                        214     LOAD_FAST                       0: self
                        216     LOAD_ATTR                       2: _undo_redo
                        226     LOAD_METHOD                     7: set_enabled
                        248     LOAD_CONST                      11: True
                        250     PRECALL                         1
                        254     CALL                            1
                        264     POP_TOP                         
                        266     LOAD_CONST                      0: None
                        268     RETURN_VALUE                    
                [Code]
                    File Name: output/Live/mac_universal_64_static/Release/python-bundle/MIDI Remote Scripts/Launchpad_Pro_MK3/launchpad_pro_mk3.py
                    Object Name: _create_transport
                    Qualified Name: Launchpad_Pro_MK3._create_transport
                    Arg Count: 1
                    Pos Only Arg Count: 0
                    KW Only Arg Count: 0
                    Stack Size: 11
                    Flags: 0x00000003 (CO_OPTIMIZED | CO_NEWLOCALS)
                    [Names]
                        'TransportComponent'
                        'Layer'
                        '_transport'
                        'tap_tempo_button'
                        'color'
                        'set_enabled'
                    [Locals+Names]
                        'self'
                    [Constants]
                        None
                        'Transport'
                        False
                        'play_button'
                        'play_button_with_shift'
                        'solo_button_with_shift'
                        'record_button_with_shift'
                        'sends_button_with_shift'
                        (
                            'play_button'
                            'continue_playing_button'
                            'metronome_button'
                            'capture_midi_button'
                            'tap_tempo_button'
                        )
                        (
                            'name'
                            'is_enabled'
                            'layer'
                        )
                        'Transport.TapTempo'
                        True
                    [Disassembly]
                        0       RESUME                          0
                        2       LOAD_GLOBAL                     1: NULL + TransportComponent
                        14      LOAD_CONST                      1: 'Transport'
                        16      LOAD_CONST                      2: False
                        18      LOAD_GLOBAL                     3: NULL + Layer
                        30      LOAD_CONST                      3: 'play_button'
                        32      LOAD_CONST                      4: 'play_button_with_shift'
                        34      LOAD_CONST                      5: 'solo_button_with_shift'
                        36      LOAD_CONST                      6: 'record_button_with_shift'
                        38      LOAD_CONST                      7: 'sends_button_with_shift'
                        40      KW_NAMES                        8: ('play_button', 'continue_playing_button', 'metronome_button', 'capture_midi_button', 'tap_tempo_button')
                        42      PRECALL                         5
                        46      CALL                            5
                        56      KW_NAMES                        9: ('name', 'is_enabled', 'layer')
                        58      PRECALL                         3
                        62      CALL                            3
                        72      LOAD_FAST                       0: self
                        74      STORE_ATTR                      2: _transport
                        84      LOAD_CONST                      10: 'Transport.TapTempo'
                        86      LOAD_FAST                       0: self
                        88      LOAD_ATTR                       2: _transport
                        98      LOAD_ATTR                       3: tap_tempo_button
                        108     STORE_ATTR                      4: color
                        118     LOAD_FAST                       0: self
                        120     LOAD_ATTR                       2: _transport
                        130     LOAD_METHOD                     5: set_enabled
                        152     LOAD_CONST                      11: True
                        154     PRECALL                         1
                        158     CALL                            1
                        168     POP_TOP                         
                        170     LOAD_CONST                      0: None
                        172     RETURN_VALUE                    
                [Code]
                    File Name: output/Live/mac_universal_64_static/Release/python-bundle/MIDI Remote Scripts/Launchpad_Pro_MK3/launchpad_pro_mk3.py
                    Object Name: _create_clip_actions
                    Qualified Name: Launchpad_Pro_MK3._create_clip_actions
                    Arg Count: 1
                    Pos Only Arg Count: 0
                    KW Only Arg Count: 0
                    Stack Size: 10
                    Flags: 0x00000003 (CO_OPTIMIZED | CO_NEWLOCALS)
                    [Names]
                        'ClipActionsComponent'
                        '_quantization'
                        'Layer'
                        '_clip_actions'
                    [Locals+Names]
                        'self'
                    [Constants]
                        None
                        'Clip_Actions'
                        False
                        'duplicate_button'
                        'quantize_button'
                        'duplicate_button_with_shift'
                        (
                            'duplicate_button'
                            'quantize_button'
                            'double_loop_button'
                        )
                        (
                            'name'
                            'quantization_component'
                            'is_enabled'
                            'layer'
                        )
                    [Disassembly]
                        0       RESUME                          0
                        2       LOAD_GLOBAL                     1: NULL + ClipActionsComponent
                        14      LOAD_CONST                      1: 'Clip_Actions'
                        16      LOAD_FAST                       0: self
                        18      LOAD_ATTR                       1: _quantization
                        28      LOAD_CONST                      2: False
                        30      LOAD_GLOBAL                     5: NULL + Layer
                        42      LOAD_CONST                      3: 'duplicate_button'
                        44      LOAD_CONST                      4: 'quantize_button'
                        46      LOAD_CONST                      5: 'duplicate_button_with_shift'
                        48      KW_NAMES                        6: ('duplicate_button', 'quantize_button', 'double_loop_button')
                        50      PRECALL                         3
                        54      CALL                            3
                        64      KW_NAMES                        7: ('name', 'quantization_component', 'is_enabled', 'layer')
                        66      PRECALL                         4
                        70      CALL                            4
                        80      LOAD_FAST                       0: self
                        82      STORE_ATTR                      3: _clip_actions
                        92      LOAD_CONST                      0: None
                        94      RETURN_VALUE                    
                [Code]
                    File Name: output/Live/mac_universal_64_static/Release/python-bundle/MIDI Remote Scripts/Launchpad_Pro_MK3/launchpad_pro_mk3.py
                    Object Name: _create_quantization
                    Qualified Name: Launchpad_Pro_MK3._create_quantization
                    Arg Count: 1
                    Pos Only Arg Count: 0
                    KW Only Arg Count: 0
                    Stack Size: 7
                    Flags: 0x00000003 (CO_OPTIMIZED | CO_NEWLOCALS)
                    [Names]
                        'QuantizationComponent'
                        'Layer'
                        '_quantization'
                        'set_enabled'
                    [Locals+Names]
                        'self'
                    [Constants]
                        None
                        'Quantization'
                        False
                        'quantize_button_with_shift'
                        (
                            'quantization_toggle_button'
                        )
                        (
                            'name'
                            'is_enabled'
                            'layer'
                        )
                        True
                    [Disassembly]
                        0       RESUME                          0
                        2       LOAD_GLOBAL                     1: NULL + QuantizationComponent
                        14      LOAD_CONST                      1: 'Quantization'
                        16      LOAD_CONST                      2: False
                        18      LOAD_GLOBAL                     3: NULL + Layer
                        30      LOAD_CONST                      3: 'quantize_button_with_shift'
                        32      KW_NAMES                        4: ('quantization_toggle_button',)
                        34      PRECALL                         1
                        38      CALL                            1
                        48      KW_NAMES                        5: ('name', 'is_enabled', 'layer')
                        50      PRECALL                         3
                        54      CALL                            3
                        64      LOAD_FAST                       0: self
                        66      STORE_ATTR                      2: _quantization
                        76      LOAD_FAST                       0: self
                        78      LOAD_ATTR                       2: _quantization
                        88      LOAD_METHOD                     3: set_enabled
                        110     LOAD_CONST                      6: True
                        112     PRECALL                         1
                        116     CALL                            1
                        126     POP_TOP                         
                        128     LOAD_CONST                      0: None
                        130     RETURN_VALUE                    
                [Code]
                    File Name: output/Live/mac_universal_64_static/Release/python-bundle/MIDI Remote Scripts/Launchpad_Pro_MK3/launchpad_pro_mk3.py
                    Object Name: _create_fixed_length
                    Qualified Name: Launchpad_Pro_MK3._create_fixed_length
                    Arg Count: 1
                    Pos Only Arg Count: 0
                    KW Only Arg Count: 0
                    Stack Size: 8
                    Flags: 0x00000003 (CO_OPTIMIZED | CO_NEWLOCALS)
                    [Names]
                        'FixedLengthComponent'
                        '_fixed_length_setting'
                        'Layer'
                        '_fixed_length'
                        'settings_component'
                        'layer'
                        'set_enabled'
                    [Locals+Names]
                        'self'
                    [Constants]
                        None
                        'Fixed_Length'
                        False
                        'fixed_length_button'
                        (
                            'fixed_length_button'
                        )
                        (
                            'fixed_length_setting'
                            'name'
                            'is_enabled'
                            'layer'
                        )
                        'track_select_buttons'
                        (
                            'length_option_buttons'
                        )
                        True
                    [Disassembly]
                        0       RESUME                          0
                        2       LOAD_GLOBAL                     1: NULL + FixedLengthComponent
                        14      LOAD_FAST                       0: self
                        16      LOAD_ATTR                       1: _fixed_length_setting
                        26      LOAD_CONST                      1: 'Fixed_Length'
                        28      LOAD_CONST                      2: False
                        30      LOAD_GLOBAL                     5: NULL + Layer
                        42      LOAD_CONST                      3: 'fixed_length_button'
                        44      KW_NAMES                        4: ('fixed_length_button',)
                        46      PRECALL                         1
                        50      CALL                            1
                        60      KW_NAMES                        5: ('fixed_length_setting', 'name', 'is_enabled', 'layer')
                        62      PRECALL                         4
                        66      CALL                            4
                        76      LOAD_FAST                       0: self
                        78      STORE_ATTR                      3: _fixed_length
                        88      LOAD_GLOBAL                     5: NULL + Layer
                        100     LOAD_CONST                      6: 'track_select_buttons'
                        102     KW_NAMES                        7: ('length_option_buttons',)
                        104     PRECALL                         1
                        108     CALL                            1
                        118     LOAD_FAST                       0: self
                        120     LOAD_ATTR                       3: _fixed_length
                        130     LOAD_ATTR                       4: settings_component
                        140     STORE_ATTR                      5: layer
                        150     LOAD_FAST                       0: self
                        152     LOAD_ATTR                       3: _fixed_length
                        162     LOAD_METHOD                     6: set_enabled
                        184     LOAD_CONST                      8: True
                        186     PRECALL                         1
                        190     CALL                            1
                        200     POP_TOP                         
                        202     LOAD_CONST                      0: None
                        204     RETURN_VALUE                    
                [Code]
                    File Name: output/Live/mac_universal_64_static/Release/python-bundle/MIDI Remote Scripts/Launchpad_Pro_MK3/launchpad_pro_mk3.py
                    Object Name: _create_drum_group
                    Qualified Name: Launchpad_Pro_MK3._create_drum_group
                    Arg Count: 1
                    Pos Only Arg Count: 0
                    KW Only Arg Count: 0
                    Stack Size: 9
                    Flags: 0x00000003 (CO_OPTIMIZED | CO_NEWLOCALS)
                    [Names]
                        'DrumGroupComponent'
                        '_clip_actions'
                        'DRUM_FEEDBACK_CHANNEL'
                        'Layer'
                        '_drum_group'
                        'set_enabled'
                    [Locals+Names]
                        'self'
                    [Constants]
                        None
                        'Drum_Group'
                        False
                        'drum_pads'
                        (
                            'matrix'
                        )
                        (
                            'name'
                            'is_enabled'
                            'translation_channel'
                            'layer'
                        )
                        True
                    [Disassembly]
                        0       RESUME                          0
                        2       LOAD_GLOBAL                     1: NULL + DrumGroupComponent
                        14      LOAD_FAST                       0: self
                        16      LOAD_ATTR                       1: _clip_actions
                        26      LOAD_CONST                      1: 'Drum_Group'
                        28      LOAD_CONST                      2: False
                        30      LOAD_GLOBAL                     4: DRUM_FEEDBACK_CHANNEL
                        42      LOAD_GLOBAL                     7: NULL + Layer
                        54      LOAD_CONST                      3: 'drum_pads'
                        56      KW_NAMES                        4: ('matrix',)
                        58      PRECALL                         1
                        62      CALL                            1
                        72      KW_NAMES                        5: ('name', 'is_enabled', 'translation_channel', 'layer')
                        74      PRECALL                         5
                        78      CALL                            5
                        88      LOAD_FAST                       0: self
                        90      STORE_ATTR                      4: _drum_group
                        100     LOAD_FAST                       0: self
                        102     LOAD_ATTR                       4: _drum_group
                        112     LOAD_METHOD                     5: set_enabled
                        134     LOAD_CONST                      6: True
                        136     PRECALL                         1
                        140     CALL                            1
                        150     POP_TOP                         
                        152     LOAD_CONST                      0: None
                        154     RETURN_VALUE                    
                [Code]
                    File Name: output/Live/mac_universal_64_static/Release/python-bundle/MIDI Remote Scripts/Launchpad_Pro_MK3/launchpad_pro_mk3.py
                    Object Name: _create_device_parameters
                    Qualified Name: Launchpad_Pro_MK3._create_device_parameters
                    Arg Count: 1
                    Pos Only Arg Count: 0
                    KW Only Arg Count: 0
                    Stack Size: 10
                    Flags: 0x00000003 (CO_OPTIMIZED | CO_NEWLOCALS)
                    [Names]
                        'SimpleDeviceParameterComponent'
                        '_device_bank_registry'
                        'Layer'
                        'Rgb'
                        'DARK_BLUE'
                        'midi_value'
                        '_device_parameters'
                        'set_enabled'
                    [Locals+Names]
                        'self'
                    [Constants]
                        None
                        'Device_Parameters'
                        False
                        'device_button_faders'
                        'device_button_fader_color_elements'
                        'stop_fader_element'
                        (
                            'parameter_controls'
                            'static_color_controls'
                            'stop_fader_control'
                        )
                        (
                            'name'
                            'is_enabled'
                            'device_bank_registry'
                            'layer'
                            'static_color_value'
                        )
                        True
                    [Disassembly]
                        0       RESUME                          0
                        2       LOAD_GLOBAL                     1: NULL + SimpleDeviceParameterComponent
                        14      LOAD_CONST                      1: 'Device_Parameters'
                        16      LOAD_CONST                      2: False
                        18      LOAD_FAST                       0: self
                        20      LOAD_ATTR                       1: _device_bank_registry
                        30      LOAD_GLOBAL                     5: NULL + Layer
                        42      LOAD_CONST                      3: 'device_button_faders'
                        44      LOAD_CONST                      4: 'device_button_fader_color_elements'
                        46      LOAD_CONST                      5: 'stop_fader_element'
                        48      KW_NAMES                        6: ('parameter_controls', 'static_color_controls', 'stop_fader_control')
                        50      PRECALL                         3
                        54      CALL                            3
                        64      LOAD_GLOBAL                     6: Rgb
                        76      LOAD_ATTR                       4: DARK_BLUE
                        86      LOAD_ATTR                       5: midi_value
                        96      KW_NAMES                        7: ('name', 'is_enabled', 'device_bank_registry', 'layer', 'static_color_value')
                        98      PRECALL                         5
                        102     CALL                            5
                        112     LOAD_FAST                       0: self
                        114     STORE_ATTR                      6: _device_parameters
                        124     LOAD_FAST                       0: self
                        126     LOAD_ATTR                       6: _device_parameters
                        136     LOAD_METHOD                     7: set_enabled
                        158     LOAD_CONST                      8: True
                        160     PRECALL                         1
                        164     CALL                            1
                        174     POP_TOP                         
                        176     LOAD_CONST                      0: None
                        178     RETURN_VALUE                    
                [Code]
                    File Name: output/Live/mac_universal_64_static/Release/python-bundle/MIDI Remote Scripts/Launchpad_Pro_MK3/launchpad_pro_mk3.py
                    Object Name: _create_device_navigation
                    Qualified Name: Launchpad_Pro_MK3._create_device_navigation
                    Arg Count: 1
                    Pos Only Arg Count: 0
                    KW Only Arg Count: 0
                    Stack Size: 3
                    Flags: 0x00000003 (CO_OPTIMIZED | CO_NEWLOCALS)
                    [Names]
                        'SimpleDeviceNavigationComponent'
                        '_device_navigation'
                    [Locals+Names]
                        'self'
                    [Constants]
                        None
                        'Device_Navigation'
                        (
                            'name'
                        )
                    [Disassembly]
                        0       RESUME                          0
                        2       LOAD_GLOBAL                     1: NULL + SimpleDeviceNavigationComponent
                        14      LOAD_CONST                      1: 'Device_Navigation'
                        16      KW_NAMES                        2: ('name',)
                        18      PRECALL                         1
                        22      CALL                            1
                        32      LOAD_FAST                       0: self
                        34      STORE_ATTR                      1: _device_navigation
                        44      LOAD_CONST                      0: None
                        46      RETURN_VALUE                    
                [Code]
                    File Name: output/Live/mac_universal_64_static/Release/python-bundle/MIDI Remote Scripts/Launchpad_Pro_MK3/launchpad_pro_mk3.py
                    Object Name: _create_scale_pad_translator
                    Qualified Name: Launchpad_Pro_MK3._create_scale_pad_translator
                    Arg Count: 1
                    Pos Only Arg Count: 0
                    KW Only Arg Count: 0
                    Stack Size: 8
                    Flags: 0x00000003 (CO_OPTIMIZED | CO_NEWLOCALS)
                    [Names]
                        'ConfigurablePlayableComponent'
                        'SCALE_FEEDBACK_CHANNEL'
                        'Layer'
                        '_scale_pad_translator'
                        'set_enabled'
                    [Locals+Names]
                        'self'
                    [Constants]
                        None
                        'Scale_Pads'
                        False
                        'scale_pads'
                        (
                            'matrix'
                        )
                        (
                            'name'
                            'is_enabled'
                            'layer'
                        )
                        True
                    [Disassembly]
                        0       RESUME                          0
                        2       LOAD_GLOBAL                     1: NULL + ConfigurablePlayableComponent
                        14      LOAD_GLOBAL                     2: SCALE_FEEDBACK_CHANNEL
                        26      LOAD_CONST                      1: 'Scale_Pads'
                        28      LOAD_CONST                      2: False
                        30      LOAD_GLOBAL                     5: NULL + Layer
                        42      LOAD_CONST                      3: 'scale_pads'
                        44      KW_NAMES                        4: ('matrix',)
                        46      PRECALL                         1
                        50      CALL                            1
                        60      KW_NAMES                        5: ('name', 'is_enabled', 'layer')
                        62      PRECALL                         4
                        66      CALL                            4
                        76      LOAD_FAST                       0: self
                        78      STORE_ATTR                      3: _scale_pad_translator
                        88      LOAD_FAST                       0: self
                        90      LOAD_ATTR                       3: _scale_pad_translator
                        100     LOAD_METHOD                     4: set_enabled
                        122     LOAD_CONST                      6: True
                        124     PRECALL                         1
                        128     CALL                            1
                        138     POP_TOP                         
                        140     LOAD_CONST                      0: None
                        142     RETURN_VALUE                    
                [Code]
                    File Name: output/Live/mac_universal_64_static/Release/python-bundle/MIDI Remote Scripts/Launchpad_Pro_MK3/launchpad_pro_mk3.py
                    Object Name: _create_mixer_modes
                    Qualified Name: Launchpad_Pro_MK3._create_mixer_modes
                    Arg Count: 1
                    Pos Only Arg Count: 0
                    KW Only Arg Count: 0
                    Stack Size: 15
                    Flags: 0x00000003 (CO_OPTIMIZED | CO_NEWLOCALS)
                    [Names]
                        'ModesComponent'
                        'Layer'
                        '_mixer_modes'
                        '_mixer'
                        'layer'
                        'partial'
                        'setattr'
                        '_session'
                        'AddLayerMode'
                        'Rgb'
                        'GREEN'
                        'midi_value'
                        '_background'
                        '_device_navigation'
                        '_device_parameters'
                        'selected_mode'
                        'set_enabled'
                    [Locals+Names]
                        'self'
                        'add_track_select_button_mode'
                        'add_fader_mode'
                        'reselect_track_select_mode'
                        'restore_main_layout'
                        'switch_to_fader_layout'
                    [Constants]
                        None
                        'Mixer_Modes'
                        False
                        True
                        'record_arm_button'
                        'mute_button'
                        'solo_button'
                        'volume_button'
                        'pan_button'
                        'sends_button'
                        'device_button'
                        'stop_clip_button'
                        (
                            'arm_button'
                            'mute_button'
                            'solo_button'
                            'volume_button'
                            'pan_button'
                            'sends_button'
                            'device_button'
                            'stop_button'
                        )
                        (
                            'name'
                            'is_enabled'
                            'enable_skinning'
                            'layer'
                        )
                        'volume_button_faders'
                        'pan_button_faders'
                        'sends_button_faders'
                        (
                            'volume_controls'
                            'pan_controls'
                            'send_controls'
                        )
                        'selected_mode'
                        'track_select'
                        [Code]
                            File Name: output/Live/mac_universal_64_static/Release/python-bundle/MIDI Remote Scripts/Launchpad_Pro_MK3/launchpad_pro_mk3.py
                            Object Name: restore_main_layout
                            Qualified Name: Launchpad_Pro_MK3._create_mixer_modes.<locals>.restore_main_layout
                            Arg Count: 0
                            Pos Only Arg Count: 0
                            KW Only Arg Count: 0
                            Stack Size: 3
                            Flags: 0x00000013 (CO_OPTIMIZED | CO_NEWLOCALS | CO_NESTED)
                            [Names]
                                '_can_restore_layout'
                                '_layout_to_restore'
                                '_elements'
                                'layout_switch'
                                'send_value'
                            [Locals+Names]
                                'self'
                            [Constants]
                                None
                            [Disassembly]
                                0       COPY_FREE_VARS                  1
                                2       RESUME                          0
                                4       LOAD_DEREF                      0: self
                                6       LOAD_ATTR                       0: _can_restore_layout
                                16      POP_JUMP_FORWARD_IF_FALSE       45 (to 108)
                                18      LOAD_DEREF                      0: self
                                20      LOAD_ATTR                       1: _layout_to_restore
                                30      POP_JUMP_FORWARD_IF_FALSE       40 (to 112)
                                32      LOAD_DEREF                      0: self
                                34      LOAD_ATTR                       2: _elements
                                44      LOAD_ATTR                       3: layout_switch
                                54      LOAD_METHOD                     4: send_value
                                76      LOAD_DEREF                      0: self
                                78      LOAD_ATTR                       1: _layout_to_restore
                                88      PRECALL                         1
                                92      CALL                            1
                                102     POP_TOP                         
                                104     LOAD_CONST                      0: None
                                106     RETURN_VALUE                    
                                108     LOAD_CONST                      0: None
                                110     RETURN_VALUE                    
                                112     LOAD_CONST                      0: None
                                114     RETURN_VALUE                    
                        [Code]
                            File Name: output/Live/mac_universal_64_static/Release/python-bundle/MIDI Remote Scripts/Launchpad_Pro_MK3/launchpad_pro_mk3.py
                            Object Name: add_track_select_button_mode
                            Qualified Name: Launchpad_Pro_MK3._create_mixer_modes.<locals>.add_track_select_button_mode
                            Arg Count: 3
                            Pos Only Arg Count: 0
                            KW Only Arg Count: 0
                            Stack Size: 11
                            Flags: 0x00000013 (CO_OPTIMIZED | CO_NEWLOCALS | CO_NESTED)
                            [Names]
                                'format'
                                '_mixer_modes'
                                'add_mode'
                                'AddLayerMode'
                                'Layer'
                                'DelayMode'
                                'ReenterBehaviour'
                            [Locals+Names]
                                'name'
                                'control'
                                'component'
                                'control_key'
                                'control_dict'
                                'reselect_track_select_mode'
                                'restore_main_layout'
                                'self'
                            [Constants]
                                None
                                '{}_buttons'
                                'track_select_buttons'
                                0.1
                                (
                                    'delay'
                                )
                                (
                                    'on_reenter'
                                )
                                (
                                    'behaviour'
                                )
                                (
                                )
                            [Disassembly]
                                0       COPY_FREE_VARS                  3
                                2       RESUME                          0
                                4       LOAD_FAST                       1: control
                                6       POP_JUMP_FORWARD_IF_FALSE       2 (to 12)
                                8       LOAD_FAST                       1: control
                                10      JUMP_FORWARD                    20 (to 52)
                                12      LOAD_CONST                      1: '{}_buttons'
                                14      LOAD_METHOD                     0: format
                                36      LOAD_FAST                       0: name
                                38      PRECALL                         1
                                42      CALL                            1
                                52      STORE_FAST                      3: control_key
                                54      LOAD_FAST                       3: control_key
                                56      LOAD_CONST                      2: 'track_select_buttons'
                                58      BUILD_MAP                       1
                                60      STORE_FAST                      4: control_dict
                                62      LOAD_DEREF                      7: self
                                64      LOAD_ATTR                       1: _mixer_modes
                                74      LOAD_METHOD                     2: add_mode
                                96      LOAD_FAST                       0: name
                                98      LOAD_GLOBAL                     7: NULL + AddLayerMode
                                110     LOAD_FAST                       2: component
                                112     LOAD_GLOBAL                     9: NULL + Layer
                                124     LOAD_CONST                      7: ()
                                126     BUILD_MAP                       0
                                128     LOAD_FAST                       4: control_dict
                                130     DICT_MERGE                      1
                                132     CALL_FUNCTION_EX                1
                                134     PRECALL                         2
                                138     CALL                            2
                                148     LOAD_GLOBAL                     11: NULL + DelayMode
                                160     LOAD_DEREF                      6: restore_main_layout
                                162     LOAD_CONST                      3: 0.1
                                164     KW_NAMES                        4: ('delay',)
                                166     PRECALL                         2
                                170     CALL                            2
                                180     BUILD_TUPLE                     2
                                182     LOAD_GLOBAL                     13: NULL + ReenterBehaviour
                                194     LOAD_DEREF                      5: reselect_track_select_mode
                                196     KW_NAMES                        5: ('on_reenter',)
                                198     PRECALL                         1
                                202     CALL                            1
                                212     KW_NAMES                        6: ('behaviour',)
                                214     PRECALL                         3
                                218     CALL                            3
                                228     POP_TOP                         
                                230     LOAD_CONST                      0: None
                                232     RETURN_VALUE                    
                        'arm'
                        'mute'
                        'solo'
                        'stop'
                        'stop_track_clip_buttons'
                        (
                            'control'
                            'component'
                        )
                        [Code]
                            File Name: output/Live/mac_universal_64_static/Release/python-bundle/MIDI Remote Scripts/Launchpad_Pro_MK3/launchpad_pro_mk3.py
                            Object Name: switch_to_fader_layout
                            Qualified Name: Launchpad_Pro_MK3._create_mixer_modes.<locals>.switch_to_fader_layout
                            Arg Count: 1
                            Pos Only Arg Count: 0
                            KW Only Arg Count: 0
                            Stack Size: 3
                            Flags: 0x00000013 (CO_OPTIMIZED | CO_NEWLOCALS | CO_NESTED)
                            [Names]
                                'ids'
                                'FADER_LAYOUT_BYTE'
                                '_elements'
                                'layout_switch'
                                'send_value'
                            [Locals+Names]
                                'bank'
                                'fader_layout_bytes'
                                'self'
                            [Constants]
                                None
                                0
                            [Disassembly]
                                0       COPY_FREE_VARS                  1
                                2       RESUME                          0
                                4       LOAD_GLOBAL                     0: ids
                                16      LOAD_ATTR                       1: FADER_LAYOUT_BYTE
                                26      LOAD_FAST                       0: bank
                                28      LOAD_CONST                      1: 0
                                30      BUILD_TUPLE                     3
                                32      STORE_FAST                      1: fader_layout_bytes
                                34      LOAD_DEREF                      2: self
                                36      LOAD_ATTR                       2: _elements
                                46      LOAD_ATTR                       3: layout_switch
                                56      LOAD_METHOD                     4: send_value
                                78      LOAD_FAST                       1: fader_layout_bytes
                                80      PRECALL                         1
                                84      CALL                            1
                                94      POP_TOP                         
                                96      LOAD_CONST                      0: None
                                98      RETURN_VALUE                    
                        [Code]
                            File Name: output/Live/mac_universal_64_static/Release/python-bundle/MIDI Remote Scripts/Launchpad_Pro_MK3/launchpad_pro_mk3.py
                            Object Name: add_fader_mode
                            Qualified Name: Launchpad_Pro_MK3._create_mixer_modes.<locals>.add_fader_mode
                            Arg Count: 4
                            Pos Only Arg Count: 0
                            KW Only Arg Count: 0
                            Stack Size: 11
                            Flags: 0x00000013 (CO_OPTIMIZED | CO_NEWLOCALS | CO_NESTED)
                            [Names]
                                '_mixer_modes'
                                'add_mode'
                                'AddLayerMode'
                                '_mixer'
                                'Layer'
                                'partial'
                                '_update_send_control_colors'
                                'set_static_color_value'
                                'ReenterBehaviour'
                            [Locals+Names]
                                'name'
                                'bank'
                                'add_layer_mode'
                                'static_color'
                                'reselect_track_select_mode'
                                'self'
                                'switch_to_fader_layout'
                            [Constants]
                                None
                                'track_select_buttons'
                                (
                                    'track_select_buttons'
                                )
                                (
                                    'on_reenter'
                                )
                                (
                                    'behaviour'
                                )
                            [Disassembly]
                                0       COPY_FREE_VARS                  3
                                2       RESUME                          0
                                4       LOAD_DEREF                      5: self
                                6       LOAD_ATTR                       0: _mixer_modes
                                16      LOAD_METHOD                     1: add_mode
                                38      LOAD_FAST                       0: name
                                40      LOAD_FAST                       2: add_layer_mode
                                42      LOAD_GLOBAL                     5: NULL + AddLayerMode
                                54      LOAD_DEREF                      5: self
                                56      LOAD_ATTR                       3: _mixer
                                66      LOAD_GLOBAL                     9: NULL + Layer
                                78      LOAD_CONST                      1: 'track_select_buttons'
                                80      KW_NAMES                        2: ('track_select_buttons',)
                                82      PRECALL                         1
                                86      CALL                            1
                                96      PRECALL                         2
                                100     CALL                            2
                                110     LOAD_GLOBAL                     11: NULL + partial
                                122     LOAD_DEREF                      5: self
                                124     LOAD_ATTR                       3: _mixer
                                134     LOAD_ATTR                       6: _update_send_control_colors
                                144     PRECALL                         1
                                148     CALL                            1
                                158     LOAD_GLOBAL                     11: NULL + partial
                                170     LOAD_DEREF                      5: self
                                172     LOAD_ATTR                       3: _mixer
                                182     LOAD_ATTR                       7: set_static_color_value
                                192     LOAD_FAST                       3: static_color
                                194     PRECALL                         2
                                198     CALL                            2
                                208     LOAD_GLOBAL                     11: NULL + partial
                                220     LOAD_DEREF                      6: switch_to_fader_layout
                                222     LOAD_FAST                       1: bank
                                224     PRECALL                         2
                                228     CALL                            2
                                238     BUILD_TUPLE                     5
                                240     LOAD_GLOBAL                     17: NULL + ReenterBehaviour
                                252     LOAD_DEREF                      4: reselect_track_select_mode
                                254     KW_NAMES                        3: ('on_reenter',)
                                256     PRECALL                         1
                                260     CALL                            1
                                270     KW_NAMES                        4: ('behaviour',)
                                272     PRECALL                         3
                                276     CALL                            3
                                286     POP_TOP                         
                                288     LOAD_CONST                      0: None
                                290     RETURN_VALUE                    
                        'volume'
                        0
                        'volume_button_fader_color_elements'
                        (
                            'static_color_controls'
                        )
                        (
                            'static_color'
                        )
                        'pan'
                        1
                        'pan_button_fader_color_elements'
                        (
                            'track_color_controls'
                        )
                        'sends'
                        2
                        'scene_launch_buttons'
                        'sends_button_fader_color_elements'
                        'stop_fader_element'
                        (
                            'send_select_buttons'
                            'return_track_color_controls'
                            'stop_fader_control'
                        )
                        'device'
                        3
                        'up_button'
                        'down_button'
                        (
                            'up_button'
                            'down_button'
                        )
                        'left_button'
                        'right_button'
                        (
                            'prev_button'
                            'next_button'
                        )
                        (
                            'bank_select_buttons'
                        )
                        (
                            None
                        )
                    [Disassembly]
                        0       MAKE_CELL                       0: self
                        2       MAKE_CELL                       3: reselect_track_select_mode
                        4       MAKE_CELL                       4: restore_main_layout
                        6       MAKE_CELL                       5: switch_to_fader_layout
                        8       RESUME                          0
                        10      LOAD_GLOBAL                     1: NULL + ModesComponent
                        22      LOAD_CONST                      1: 'Mixer_Modes'
                        24      LOAD_CONST                      2: False
                        26      LOAD_CONST                      3: True
                        28      LOAD_GLOBAL                     3: NULL + Layer
                        40      LOAD_CONST                      4: 'record_arm_button'
                        42      LOAD_CONST                      5: 'mute_button'
                        44      LOAD_CONST                      6: 'solo_button'
                        46      LOAD_CONST                      7: 'volume_button'
                        48      LOAD_CONST                      8: 'pan_button'
                        50      LOAD_CONST                      9: 'sends_button'
                        52      LOAD_CONST                      10: 'device_button'
                        54      LOAD_CONST                      11: 'stop_clip_button'
                        56      KW_NAMES                        12: ('arm_button', 'mute_button', 'solo_button', 'volume_button', 'pan_button', 'sends_button', 'device_button', 'stop_button')
                        58      PRECALL                         8
                        62      CALL                            8
                        72      KW_NAMES                        13: ('name', 'is_enabled', 'enable_skinning', 'layer')
                        74      PRECALL                         4
                        78      CALL                            4
                        88      LOAD_DEREF                      0: self
                        90      STORE_ATTR                      2: _mixer_modes
                        100     LOAD_GLOBAL                     3: NULL + Layer
                        112     LOAD_CONST                      14: 'volume_button_faders'
                        114     LOAD_CONST                      15: 'pan_button_faders'
                        116     LOAD_CONST                      16: 'sends_button_faders'
                        118     KW_NAMES                        17: ('volume_controls', 'pan_controls', 'send_controls')
                        120     PRECALL                         3
                        124     CALL                            3
                        134     LOAD_DEREF                      0: self
                        136     LOAD_ATTR                       3: _mixer
                        146     STORE_ATTR                      4: layer
                        156     LOAD_GLOBAL                     11: NULL + partial
                        168     LOAD_GLOBAL                     12: setattr
                        180     LOAD_DEREF                      0: self
                        182     LOAD_ATTR                       2: _mixer_modes
                        192     LOAD_CONST                      18: 'selected_mode'
                        194     LOAD_CONST                      19: 'track_select'
                        196     PRECALL                         4
                        200     CALL                            4
                        210     STORE_DEREF                     3: reselect_track_select_mode
                        212     LOAD_CLOSURE                    0: self
                        214     BUILD_TUPLE                     1
                        216     LOAD_CONST                      20: <CODE> restore_main_layout
                        218     MAKE_FUNCTION                   8
                        220     STORE_DEREF                     4: restore_main_layout
                        222     LOAD_CONST                      0: None
                        224     LOAD_DEREF                      0: self
                        226     LOAD_ATTR                       3: _mixer
                        236     BUILD_TUPLE                     2
                        238     LOAD_CLOSURE                    3: reselect_track_select_mode
                        240     LOAD_CLOSURE                    4: restore_main_layout
                        242     LOAD_CLOSURE                    0: self
                        244     BUILD_TUPLE                     3
                        246     LOAD_CONST                      21: <CODE> add_track_select_button_mode
                        248     MAKE_FUNCTION                   9
                        250     STORE_FAST                      1: add_track_select_button_mode
                        252     PUSH_NULL                       
                        254     LOAD_FAST                       1: add_track_select_button_mode
                        256     LOAD_CONST                      19: 'track_select'
                        258     PRECALL                         1
                        262     CALL                            1
                        272     POP_TOP                         
                        274     PUSH_NULL                       
                        276     LOAD_FAST                       1: add_track_select_button_mode
                        278     LOAD_CONST                      22: 'arm'
                        280     PRECALL                         1
                        284     CALL                            1
                        294     POP_TOP                         
                        296     PUSH_NULL                       
                        298     LOAD_FAST                       1: add_track_select_button_mode
                        300     LOAD_CONST                      23: 'mute'
                        302     PRECALL                         1
                        306     CALL                            1
                        316     POP_TOP                         
                        318     PUSH_NULL                       
                        320     LOAD_FAST                       1: add_track_select_button_mode
                        322     LOAD_CONST                      24: 'solo'
                        324     PRECALL                         1
                        328     CALL                            1
                        338     POP_TOP                         
                        340     PUSH_NULL                       
                        342     LOAD_FAST                       1: add_track_select_button_mode
                        344     LOAD_CONST                      25: 'stop'
                        346     LOAD_CONST                      26: 'stop_track_clip_buttons'
                        348     LOAD_DEREF                      0: self
                        350     LOAD_ATTR                       7: _session
                        360     KW_NAMES                        27: ('control', 'component')
                        362     PRECALL                         3
                        366     CALL                            3
                        376     POP_TOP                         
                        378     LOAD_CLOSURE                    0: self
                        380     BUILD_TUPLE                     1
                        382     LOAD_CONST                      28: <CODE> switch_to_fader_layout
                        384     MAKE_FUNCTION                   8
                        386     STORE_DEREF                     5: switch_to_fader_layout
                        388     LOAD_CONST                      54: (None,)
                        390     LOAD_CLOSURE                    3: reselect_track_select_mode
                        392     LOAD_CLOSURE                    0: self
                        394     LOAD_CLOSURE                    5: switch_to_fader_layout
                        396     BUILD_TUPLE                     3
                        398     LOAD_CONST                      29: <CODE> add_fader_mode
                        400     MAKE_FUNCTION                   9
                        402     STORE_FAST                      2: add_fader_mode
                        404     PUSH_NULL                       
                        406     LOAD_FAST                       2: add_fader_mode
                        408     LOAD_CONST                      30: 'volume'
                        410     LOAD_CONST                      31: 0
                        412     LOAD_GLOBAL                     17: NULL + AddLayerMode
                        424     LOAD_DEREF                      0: self
                        426     LOAD_ATTR                       3: _mixer
                        436     LOAD_GLOBAL                     3: NULL + Layer
                        448     LOAD_CONST                      32: 'volume_button_fader_color_elements'
                        450     KW_NAMES                        33: ('static_color_controls',)
                        452     PRECALL                         1
                        456     CALL                            1
                        466     PRECALL                         2
                        470     CALL                            2
                        480     LOAD_GLOBAL                     18: Rgb
                        492     LOAD_ATTR                       10: GREEN
                        502     LOAD_ATTR                       11: midi_value
                        512     KW_NAMES                        34: ('static_color',)
                        514     PRECALL                         4
                        518     CALL                            4
                        528     POP_TOP                         
                        530     PUSH_NULL                       
                        532     LOAD_FAST                       2: add_fader_mode
                        534     LOAD_CONST                      35: 'pan'
                        536     LOAD_CONST                      36: 1
                        538     LOAD_GLOBAL                     17: NULL + AddLayerMode
                        550     LOAD_DEREF                      0: self
                        552     LOAD_ATTR                       3: _mixer
                        562     LOAD_GLOBAL                     3: NULL + Layer
                        574     LOAD_CONST                      37: 'pan_button_fader_color_elements'
                        576     KW_NAMES                        38: ('track_color_controls',)
                        578     PRECALL                         1
                        582     CALL                            1
                        592     PRECALL                         2
                        596     CALL                            2
                        606     PRECALL                         3
                        610     CALL                            3
                        620     POP_TOP                         
                        622     PUSH_NULL                       
                        624     LOAD_FAST                       2: add_fader_mode
                        626     LOAD_CONST                      39: 'sends'
                        628     LOAD_CONST                      40: 2
                        630     LOAD_GLOBAL                     17: NULL + AddLayerMode
                        642     LOAD_DEREF                      0: self
                        644     LOAD_ATTR                       3: _mixer
                        654     LOAD_GLOBAL                     3: NULL + Layer
                        666     LOAD_CONST                      41: 'scene_launch_buttons'
                        668     LOAD_CONST                      42: 'sends_button_fader_color_elements'
                        670     LOAD_CONST                      43: 'stop_fader_element'
                        672     KW_NAMES                        44: ('send_select_buttons', 'return_track_color_controls', 'stop_fader_control')
                        674     PRECALL                         3
                        678     CALL                            3
                        688     PRECALL                         2
                        692     CALL                            2
                        702     PRECALL                         3
                        706     CALL                            3
                        716     POP_TOP                         
                        718     PUSH_NULL                       
                        720     LOAD_FAST                       2: add_fader_mode
                        722     LOAD_CONST                      45: 'device'
                        724     LOAD_CONST                      46: 3
                        726     LOAD_GLOBAL                     17: NULL + AddLayerMode
                        738     LOAD_DEREF                      0: self
                        740     LOAD_ATTR                       12: _background
                        750     LOAD_GLOBAL                     3: NULL + Layer
                        762     LOAD_CONST                      47: 'up_button'
                        764     LOAD_CONST                      48: 'down_button'
                        766     KW_NAMES                        49: ('up_button', 'down_button')
                        768     PRECALL                         2
                        772     CALL                            2
                        782     PRECALL                         2
                        786     CALL                            2
                        796     LOAD_GLOBAL                     17: NULL + AddLayerMode
                        808     LOAD_DEREF                      0: self
                        810     LOAD_ATTR                       13: _device_navigation
                        820     LOAD_GLOBAL                     3: NULL + Layer
                        832     LOAD_CONST                      50: 'left_button'
                        834     LOAD_CONST                      51: 'right_button'
                        836     KW_NAMES                        52: ('prev_button', 'next_button')
                        838     PRECALL                         2
                        842     CALL                            2
                        852     PRECALL                         2
                        856     CALL                            2
                        866     LOAD_GLOBAL                     17: NULL + AddLayerMode
                        878     LOAD_DEREF                      0: self
                        880     LOAD_ATTR                       14: _device_parameters
                        890     LOAD_GLOBAL                     3: NULL + Layer
                        902     LOAD_CONST                      41: 'scene_launch_buttons'
                        904     KW_NAMES                        53: ('bank_select_buttons',)
                        906     PRECALL                         1
                        910     CALL                            1
                        920     PRECALL                         2
                        924     CALL                            2
                        934     BUILD_TUPLE                     3
                        936     PRECALL                         3
                        940     CALL                            3
                        950     POP_TOP                         
                        952     LOAD_CONST                      19: 'track_select'
                        954     LOAD_DEREF                      0: self
                        956     LOAD_ATTR                       2: _mixer_modes
                        966     STORE_ATTR                      15: selected_mode
                        976     LOAD_DEREF                      0: self
                        978     LOAD_ATTR                       2: _mixer_modes
                        988     LOAD_METHOD                     16: set_enabled
                        1010    LOAD_CONST                      3: True
                        1012    PRECALL                         1
                        1016    CALL                            1
                        1026    POP_TOP                         
                        1028    LOAD_CONST                      0: None
                        1030    RETURN_VALUE                    
                [Code]
                    File Name: output/Live/mac_universal_64_static/Release/python-bundle/MIDI Remote Scripts/Launchpad_Pro_MK3/launchpad_pro_mk3.py
                    Object Name: _create_session_modes
                    Qualified Name: Launchpad_Pro_MK3._create_session_modes
                    Arg Count: 1
                    Pos Only Arg Count: 0
                    KW Only Arg Count: 0
                    Stack Size: 14
                    Flags: 0x00000003 (CO_OPTIMIZED | CO_NEWLOCALS)
                    [Names]
                        'ModesComponent'
                        'Layer'
                        '_session_modes'
                        'add_mode'
                        'AddLayerMode'
                        '_session'
                        '_session_overview'
                        '_session_navigation'
                        'MomentaryBehaviour'
                        'selected_mode'
                    [Locals+Names]
                        'self'
                    [Constants]
                        None
                        'Session_Modes'
                        False
                        'session_mode_button'
                        (
                            'overview_button'
                        )
                        (
                            'name'
                            'is_enabled'
                            'layer'
                        )
                        'launch'
                        'shift_button'
                        'clear_button'
                        'duplicate_button'
                        'quantize_button'
                        'duplicate_button_with_shift'
                        'scene_launch_buttons'
                        (
                            'managed_select_button'
                            'managed_delete_button'
                            'managed_duplicate_button'
                            'managed_quantize_button'
                            'managed_double_button'
                            'scene_launch_buttons'
                        )
                        'overview'
                        'up_button'
                        'down_button'
                        'left_button'
                        'right_button'
                        (
                            'page_up_button'
                            'page_down_button'
                            'page_left_button'
                            'page_right_button'
                        )
                        (
                            'behaviour'
                        )
                    [Disassembly]
                        0       RESUME                          0
                        2       LOAD_GLOBAL                     1: NULL + ModesComponent
                        14      LOAD_CONST                      1: 'Session_Modes'
                        16      LOAD_CONST                      2: False
                        18      LOAD_GLOBAL                     3: NULL + Layer
                        30      LOAD_CONST                      3: 'session_mode_button'
                        32      KW_NAMES                        4: ('overview_button',)
                        34      PRECALL                         1
                        38      CALL                            1
                        48      KW_NAMES                        5: ('name', 'is_enabled', 'layer')
                        50      PRECALL                         3
                        54      CALL                            3
                        64      LOAD_FAST                       0: self
                        66      STORE_ATTR                      2: _session_modes
                        76      LOAD_FAST                       0: self
                        78      LOAD_ATTR                       2: _session_modes
                        88      LOAD_METHOD                     3: add_mode
                        110     LOAD_CONST                      6: 'launch'
                        112     LOAD_GLOBAL                     9: NULL + AddLayerMode
                        124     LOAD_FAST                       0: self
                        126     LOAD_ATTR                       5: _session
                        136     LOAD_GLOBAL                     3: NULL + Layer
                        148     LOAD_CONST                      7: 'shift_button'
                        150     LOAD_CONST                      8: 'clear_button'
                        152     LOAD_CONST                      9: 'duplicate_button'
                        154     LOAD_CONST                      10: 'quantize_button'
                        156     LOAD_CONST                      11: 'duplicate_button_with_shift'
                        158     LOAD_CONST                      12: 'scene_launch_buttons'
                        160     KW_NAMES                        13: ('managed_select_button', 'managed_delete_button', 'managed_duplicate_button', 'managed_quantize_button', 'managed_double_button', 'scene_launch_buttons')
                        162     PRECALL                         6
                        166     CALL                            6
                        176     PRECALL                         2
                        180     CALL                            2
                        190     PRECALL                         2
                        194     CALL                            2
                        204     POP_TOP                         
                        206     LOAD_FAST                       0: self
                        208     LOAD_ATTR                       2: _session_modes
                        218     LOAD_METHOD                     3: add_mode
                        240     LOAD_CONST                      14: 'overview'
                        242     LOAD_FAST                       0: self
                        244     LOAD_ATTR                       6: _session_overview
                        254     LOAD_GLOBAL                     9: NULL + AddLayerMode
                        266     LOAD_FAST                       0: self
                        268     LOAD_ATTR                       7: _session_navigation
                        278     LOAD_GLOBAL                     3: NULL + Layer
                        290     LOAD_CONST                      15: 'up_button'
                        292     LOAD_CONST                      16: 'down_button'
                        294     LOAD_CONST                      17: 'left_button'
                        296     LOAD_CONST                      18: 'right_button'
                        298     KW_NAMES                        19: ('page_up_button', 'page_down_button', 'page_left_button', 'page_right_button')
                        300     PRECALL                         4
                        304     CALL                            4
                        314     PRECALL                         2
                        318     CALL                            2
                        328     BUILD_TUPLE                     2
                        330     LOAD_GLOBAL                     17: NULL + MomentaryBehaviour
                        342     PRECALL                         0
                        346     CALL                            0
                        356     KW_NAMES                        20: ('behaviour',)
                        358     PRECALL                         3
                        362     CALL                            3
                        372     POP_TOP                         
                        374     LOAD_CONST                      6: 'launch'
                        376     LOAD_FAST                       0: self
                        378     LOAD_ATTR                       2: _session_modes
                        388     STORE_ATTR                      9: selected_mode
                        398     LOAD_CONST                      0: None
                        400     RETURN_VALUE                    
                [Code]
                    File Name: output/Live/mac_universal_64_static/Release/python-bundle/MIDI Remote Scripts/Launchpad_Pro_MK3/launchpad_pro_mk3.py
                    Object Name: _create_note_modes
                    Qualified Name: Launchpad_Pro_MK3._create_note_modes
                    Arg Count: 1
                    Pos Only Arg Count: 0
                    KW Only Arg Count: 0
                    Stack Size: 13
                    Flags: 0x00000003 (CO_OPTIMIZED | CO_NEWLOCALS)
                    [Names]
                        'ModesComponent'
                        '_note_modes'
                        'add_mode'
                        'AddLayerMode'
                        '_clip_actions'
                        'Layer'
                        '_drum_group'
                    [Locals+Names]
                        'self'
                    [Constants]
                        None
                        'Note_Modes'
                        False
                        (
                            'name'
                            'is_enabled'
                        )
                        'scale'
                        'clear_button'
                        (
                            'delete_button'
                        )
                        'drum'
                        'left_button'
                        'right_button'
                        'up_button'
                        'down_button'
                        (
                            'scroll_up_button'
                            'scroll_down_button'
                            'scroll_page_up_button'
                            'scroll_page_down_button'
                            'delete_button'
                        )
                    [Disassembly]
                        0       RESUME                          0
                        2       LOAD_GLOBAL                     1: NULL + ModesComponent
                        14      LOAD_CONST                      1: 'Note_Modes'
                        16      LOAD_CONST                      2: False
                        18      KW_NAMES                        3: ('name', 'is_enabled')
                        20      PRECALL                         2
                        24      CALL                            2
                        34      LOAD_FAST                       0: self
                        36      STORE_ATTR                      1: _note_modes
                        46      LOAD_FAST                       0: self
                        48      LOAD_ATTR                       1: _note_modes
                        58      LOAD_METHOD                     2: add_mode
                        80      LOAD_CONST                      4: 'scale'
                        82      LOAD_GLOBAL                     7: NULL + AddLayerMode
                        94      LOAD_FAST                       0: self
                        96      LOAD_ATTR                       4: _clip_actions
                        106     LOAD_GLOBAL                     11: NULL + Layer
                        118     LOAD_CONST                      5: 'clear_button'
                        120     KW_NAMES                        6: ('delete_button',)
                        122     PRECALL                         1
                        126     CALL                            1
                        136     PRECALL                         2
                        140     CALL                            2
                        150     PRECALL                         2
                        154     CALL                            2
                        164     POP_TOP                         
                        166     LOAD_FAST                       0: self
                        168     LOAD_ATTR                       1: _note_modes
                        178     LOAD_METHOD                     2: add_mode
                        200     LOAD_CONST                      7: 'drum'
                        202     LOAD_GLOBAL                     7: NULL + AddLayerMode
                        214     LOAD_FAST                       0: self
                        216     LOAD_ATTR                       6: _drum_group
                        226     LOAD_GLOBAL                     11: NULL + Layer
                        238     LOAD_CONST                      8: 'left_button'
                        240     LOAD_CONST                      9: 'right_button'
                        242     LOAD_CONST                      10: 'up_button'
                        244     LOAD_CONST                      11: 'down_button'
                        246     LOAD_CONST                      5: 'clear_button'
                        248     KW_NAMES                        12: ('scroll_up_button', 'scroll_down_button', 'scroll_page_up_button', 'scroll_page_down_button', 'delete_button')
                        250     PRECALL                         5
                        254     CALL                            5
                        264     PRECALL                         2
                        268     CALL                            2
                        278     PRECALL                         2
                        282     CALL                            2
                        292     POP_TOP                         
                        294     LOAD_CONST                      0: None
                        296     RETURN_VALUE                    
                [Code]
                    File Name: output/Live/mac_universal_64_static/Release/python-bundle/MIDI Remote Scripts/Launchpad_Pro_MK3/launchpad_pro_mk3.py
                    Object Name: _create_main_modes
                    Qualified Name: Launchpad_Pro_MK3._create_main_modes
                    Arg Count: 1
                    Pos Only Arg Count: 0
                    KW Only Arg Count: 0
                    Stack Size: 9
                    Flags: 0x00000003 (CO_OPTIMIZED | CO_NEWLOCALS)
                    [Names]
                        'ModesComponent'
                        '_main_modes'
                        'AddLayerMode'
                        '_background'
                        'Layer'
                        'add_mode'
                        '_session_modes'
                        '_note_modes'
                        '_clip_actions'
                        'selected_mode'
                        'set_enabled'
                        '_Launchpad_Pro_MK3__on_main_mode_changed'
                        'subject'
                    [Locals+Names]
                        'self'
                        'suppressed_arrow_button_mode'
                    [Constants]
                        None
                        'Main_Modes'
                        False
                        (
                            'name'
                            'is_enabled'
                        )
                        'left_button'
                        'right_button'
                        'up_button'
                        'down_button'
                        (
                            'left_button'
                            'right_button'
                            'up_button'
                            'down_button'
                        )
                        'none'
                        'fader'
                        'session'
                        'note'
                        'chord'
                        True
                    [Disassembly]
                        0       RESUME                          0
                        2       LOAD_GLOBAL                     1: NULL + ModesComponent
                        14      LOAD_CONST                      1: 'Main_Modes'
                        16      LOAD_CONST                      2: False
                        18      KW_NAMES                        3: ('name', 'is_enabled')
                        20      PRECALL                         2
                        24      CALL                            2
                        34      LOAD_FAST                       0: self
                        36      STORE_ATTR                      1: _main_modes
                        46      LOAD_GLOBAL                     5: NULL + AddLayerMode
                        58      LOAD_FAST                       0: self
                        60      LOAD_ATTR                       3: _background
                        70      LOAD_GLOBAL                     9: NULL + Layer
                        82      LOAD_CONST                      4: 'left_button'
                        84      LOAD_CONST                      5: 'right_button'
                        86      LOAD_CONST                      6: 'up_button'
                        88      LOAD_CONST                      7: 'down_button'
                        90      KW_NAMES                        8: ('left_button', 'right_button', 'up_button', 'down_button')
                        92      PRECALL                         4
                        96      CALL                            4
                        106     PRECALL                         2
                        110     CALL                            2
                        120     BUILD_TUPLE                     1
                        122     STORE_FAST                      1: suppressed_arrow_button_mode
                        124     LOAD_FAST                       0: self
                        126     LOAD_ATTR                       1: _main_modes
                        136     LOAD_METHOD                     5: add_mode
                        158     LOAD_CONST                      9: 'none'
                        160     LOAD_FAST                       1: suppressed_arrow_button_mode
                        162     PRECALL                         2
                        166     CALL                            2
                        176     POP_TOP                         
                        178     LOAD_FAST                       0: self
                        180     LOAD_ATTR                       1: _main_modes
                        190     LOAD_METHOD                     5: add_mode
                        212     LOAD_CONST                      10: 'fader'
                        214     LOAD_CONST                      0: None
                        216     PRECALL                         2
                        220     CALL                            2
                        230     POP_TOP                         
                        232     LOAD_FAST                       0: self
                        234     LOAD_ATTR                       1: _main_modes
                        244     LOAD_METHOD                     5: add_mode
                        266     LOAD_CONST                      11: 'session'
                        268     LOAD_FAST                       0: self
                        270     LOAD_ATTR                       6: _session_modes
                        280     PRECALL                         2
                        284     CALL                            2
                        294     POP_TOP                         
                        296     LOAD_FAST                       0: self
                        298     LOAD_ATTR                       1: _main_modes
                        308     LOAD_METHOD                     5: add_mode
                        330     LOAD_CONST                      12: 'note'
                        332     LOAD_FAST                       0: self
                        334     LOAD_ATTR                       7: _note_modes
                        344     LOAD_FAST                       0: self
                        346     LOAD_ATTR                       8: _clip_actions
                        356     BUILD_TUPLE                     2
                        358     PRECALL                         2
                        362     CALL                            2
                        372     POP_TOP                         
                        374     LOAD_FAST                       0: self
                        376     LOAD_ATTR                       1: _main_modes
                        386     LOAD_METHOD                     5: add_mode
                        408     LOAD_CONST                      13: 'chord'
                        410     LOAD_FAST                       1: suppressed_arrow_button_mode
                        412     PRECALL                         2
                        416     CALL                            2
                        426     POP_TOP                         
                        428     LOAD_CONST                      11: 'session'
                        430     LOAD_FAST                       0: self
                        432     LOAD_ATTR                       1: _main_modes
                        442     STORE_ATTR                      9: selected_mode
                        452     LOAD_FAST                       0: self
                        454     LOAD_ATTR                       1: _main_modes
                        464     LOAD_METHOD                     10: set_enabled
                        486     LOAD_CONST                      14: True
                        488     PRECALL                         1
                        492     CALL                            1
                        502     POP_TOP                         
                        504     LOAD_FAST                       0: self
                        506     LOAD_ATTR                       1: _main_modes
                        516     LOAD_FAST                       0: self
                        518     LOAD_ATTR                       11: _Launchpad_Pro_MK3__on_main_mode_changed
                        528     STORE_ATTR                      12: subject
                        538     LOAD_CONST                      0: None
                        540     RETURN_VALUE                    
                'selected_mode'
                [Code]
                    File Name: output/Live/mac_universal_64_static/Release/python-bundle/MIDI Remote Scripts/Launchpad_Pro_MK3/launchpad_pro_mk3.py
                    Object Name: __on_main_mode_changed
                    Qualified Name: Launchpad_Pro_MK3.__on_main_mode_changed
                    Arg Count: 2
                    Pos Only Arg Count: 0
                    KW Only Arg Count: 0
                    Stack Size: 4
                    Flags: 0x00000003 (CO_OPTIMIZED | CO_NEWLOCALS)
                    [Names]
                        '_session_modes'
                        'selected_mode'
                        '_recording_modes'
                        '_update_controlled_track'
                        '_auto_arm'
                        'set_enabled'
                        '_is_instrument_mode'
                    [Locals+Names]
                        'self'
                        'mode'
                    [Constants]
                        None
                        'session'
                        'launch'
                        'track'
                    [Disassembly]
                        0       RESUME                          0
                        2       LOAD_FAST                       1: mode
                        4       LOAD_CONST                      1: 'session'
                        6       COMPARE_OP                      2 (==)
                        12      POP_JUMP_FORWARD_IF_FALSE       12 (to 38)
                        14      LOAD_CONST                      2: 'launch'
                        16      LOAD_FAST                       0: self
                        18      LOAD_ATTR                       0: _session_modes
                        28      STORE_ATTR                      1: selected_mode
                        38      LOAD_FAST                       1: mode
                        40      LOAD_CONST                      1: 'session'
                        42      COMPARE_OP                      2 (==)
                        48      POP_JUMP_FORWARD_IF_FALSE       2 (to 54)
                        50      LOAD_CONST                      1: 'session'
                        52      JUMP_FORWARD                    1 (to 56)
                        54      LOAD_CONST                      3: 'track'
                        56      LOAD_FAST                       0: self
                        58      LOAD_ATTR                       2: _recording_modes
                        68      STORE_ATTR                      1: selected_mode
                        78      LOAD_FAST                       0: self
                        80      LOAD_METHOD                     3: _update_controlled_track
                        102     PRECALL                         0
                        106     CALL                            0
                        116     POP_TOP                         
                        118     LOAD_FAST                       0: self
                        120     LOAD_ATTR                       4: _auto_arm
                        130     LOAD_METHOD                     5: set_enabled
                        152     LOAD_FAST                       0: self
                        154     LOAD_METHOD                     6: _is_instrument_mode
                        176     PRECALL                         0
                        180     CALL                            0
                        190     PRECALL                         1
                        194     CALL                            1
                        204     POP_TOP                         
                        206     LOAD_CONST                      0: None
                        208     RETURN_VALUE                    
                'value'
                [Code]
                    File Name: output/Live/mac_universal_64_static/Release/python-bundle/MIDI Remote Scripts/Launchpad_Pro_MK3/launchpad_pro_mk3.py
                    Object Name: __on_layout_switch_value
                    Qualified Name: Launchpad_Pro_MK3.__on_layout_switch_value
                    Arg Count: 2
                    Pos Only Arg Count: 0
                    KW Only Arg Count: 0
                    Stack Size: 2
                    Flags: 0x00000003 (CO_OPTIMIZED | CO_NEWLOCALS)
                    [Names]
                        'LIVE_LAYOUT_BYTES'
                        '_can_restore_layout'
                        'ids'
                        'FADER_LAYOUT_BYTE'
                        '_main_modes'
                        'selected_mode'
                        '_layout_to_restore'
                        '_mixer_modes'
                        'FADER_MODES'
                        'LAYOUT_BYTES_TO_MODE_NAMES_MAP'
                        '_last_layout_bytes'
                    [Locals+Names]
                        'self'
                        'value'
                    [Constants]
                        None
                        0
                        'fader'
                        'track_select'
                        'none'
                    [Disassembly]
                        0       RESUME                          0
                        2       LOAD_FAST                       1: value
                        4       LOAD_CONST                      1: 0
                        6       BINARY_SUBSCR                   
                        16      LOAD_GLOBAL                     0: LIVE_LAYOUT_BYTES
                        28      CONTAINS_OP                     0 (in)
                        30      LOAD_FAST                       0: self
                        32      STORE_ATTR                      1: _can_restore_layout
                        42      LOAD_FAST                       0: self
                        44      LOAD_ATTR                       1: _can_restore_layout
                        54      POP_JUMP_FORWARD_IF_TRUE        2 (to 60)
                        56      LOAD_CONST                      0: None
                        58      RETURN_VALUE                    
                        60      LOAD_FAST                       1: value
                        62      LOAD_CONST                      1: 0
                        64      BINARY_SUBSCR                   
                        74      LOAD_GLOBAL                     4: ids
                        86      LOAD_ATTR                       3: FADER_LAYOUT_BYTE
                        96      COMPARE_OP                      2 (==)
                        102     POP_JUMP_FORWARD_IF_FALSE       13 (to 130)
                        104     LOAD_CONST                      2: 'fader'
                        106     LOAD_FAST                       0: self
                        108     LOAD_ATTR                       4: _main_modes
                        118     STORE_ATTR                      5: selected_mode
                        128     JUMP_FORWARD                    83 (to 296)
                        130     LOAD_FAST                       1: value
                        132     LOAD_FAST                       0: self
                        134     STORE_ATTR                      6: _layout_to_restore
                        144     LOAD_FAST                       0: self
                        146     LOAD_ATTR                       7: _mixer_modes
                        156     LOAD_ATTR                       5: selected_mode
                        166     LOAD_GLOBAL                     16: FADER_MODES
                        178     CONTAINS_OP                     0 (in)
                        180     POP_JUMP_FORWARD_IF_FALSE       12 (to 206)
                        182     LOAD_CONST                      3: 'track_select'
                        184     LOAD_FAST                       0: self
                        186     LOAD_ATTR                       7: _mixer_modes
                        196     STORE_ATTR                      5: selected_mode
                        206     LOAD_FAST                       1: value
                        208     LOAD_GLOBAL                     18: LAYOUT_BYTES_TO_MODE_NAMES_MAP
                        220     CONTAINS_OP                     0 (in)
                        222     POP_JUMP_FORWARD_IF_FALSE       24 (to 272)
                        224     LOAD_GLOBAL                     18: LAYOUT_BYTES_TO_MODE_NAMES_MAP
                        236     LOAD_FAST                       1: value
                        238     BINARY_SUBSCR                   
                        248     LOAD_FAST                       0: self
                        250     LOAD_ATTR                       4: _main_modes
                        260     STORE_ATTR                      5: selected_mode
                        270     JUMP_FORWARD                    12 (to 296)
                        272     LOAD_CONST                      4: 'none'
                        274     LOAD_FAST                       0: self
                        276     LOAD_ATTR                       4: _main_modes
                        286     STORE_ATTR                      5: selected_mode
                        296     LOAD_FAST                       1: value
                        298     LOAD_FAST                       0: self
                        300     STORE_ATTR                      10: _last_layout_bytes
                        310     LOAD_CONST                      0: None
                        312     RETURN_VALUE                    
                [Code]
                    File Name: output/Live/mac_universal_64_static/Release/python-bundle/MIDI Remote Scripts/Launchpad_Pro_MK3/launchpad_pro_mk3.py
                    Object Name: _drum_group_changed
                    Qualified Name: Launchpad_Pro_MK3._drum_group_changed
                    Arg Count: 1
                    Pos Only Arg Count: 0
                    KW Only Arg Count: 0
                    Stack Size: 3
                    Flags: 0x00000003 (CO_OPTIMIZED | CO_NEWLOCALS)
                    [Names]
                        '_drum_group_finder'
                        'drum_group'
                        'liveobj_valid'
                        '_drum_group'
                        'set_drum_group_device'
                        '_elements'
                        'layout_switch'
                        'send_value'
                        'ids'
                        'DRUM_LAYOUT_BYTES'
                        'SCALE_LAYOUT_BYTES'
                        '_note_modes'
                        'selected_mode'
                    [Locals+Names]
                        'self'
                        'drum_group'
                        'drum_group_valid'
                    [Constants]
                        None
                        'drum'
                        'scale'
                    [Disassembly]
                        0       RESUME                          0
                        2       LOAD_FAST                       0: self
                        4       LOAD_ATTR                       0: _drum_group_finder
                        14      LOAD_ATTR                       1: drum_group
                        24      STORE_FAST                      1: drum_group
                        26      LOAD_GLOBAL                     5: NULL + liveobj_valid
                        38      LOAD_FAST                       1: drum_group
                        40      PRECALL                         1
                        44      CALL                            1
                        54      STORE_FAST                      2: drum_group_valid
                        56      LOAD_FAST                       0: self
                        58      LOAD_ATTR                       3: _drum_group
                        68      LOAD_METHOD                     4: set_drum_group_device
                        90      LOAD_FAST                       1: drum_group
                        92      PRECALL                         1
                        96      CALL                            1
                        106     POP_TOP                         
                        108     LOAD_FAST                       0: self
                        110     LOAD_ATTR                       5: _elements
                        120     LOAD_ATTR                       6: layout_switch
                        130     LOAD_METHOD                     7: send_value
                        152     LOAD_FAST                       2: drum_group_valid
                        154     POP_JUMP_FORWARD_IF_FALSE       12 (to 180)
                        156     LOAD_GLOBAL                     16: ids
                        168     LOAD_ATTR                       9: DRUM_LAYOUT_BYTES
                        178     JUMP_FORWARD                    11 (to 202)
                        180     LOAD_GLOBAL                     16: ids
                        192     LOAD_ATTR                       10: SCALE_LAYOUT_BYTES
                        202     PRECALL                         1
                        206     CALL                            1
                        216     POP_TOP                         
                        218     LOAD_FAST                       2: drum_group_valid
                        220     POP_JUMP_FORWARD_IF_FALSE       2 (to 226)
                        222     LOAD_CONST                      1: 'drum'
                        224     JUMP_FORWARD                    1 (to 228)
                        226     LOAD_CONST                      2: 'scale'
                        228     LOAD_FAST                       0: self
                        230     LOAD_ATTR                       11: _note_modes
                        240     STORE_ATTR                      12: selected_mode
                        250     LOAD_CONST                      0: None
                        252     RETURN_VALUE                    
                [Code]
                    File Name: output/Live/mac_universal_64_static/Release/python-bundle/MIDI Remote Scripts/Launchpad_Pro_MK3/launchpad_pro_mk3.py
                    Object Name: _is_instrument_mode
                    Qualified Name: Launchpad_Pro_MK3._is_instrument_mode
                    Arg Count: 1
                    Pos Only Arg Count: 0
                    KW Only Arg Count: 0
                    Stack Size: 2
                    Flags: 0x00000003 (CO_OPTIMIZED | CO_NEWLOCALS)
                    [Names]
                        '_main_modes'
                        'selected_mode'
                        'NOTE_MODE_NAMES'
                    [Locals+Names]
                        'self'
                    [Constants]
                        None
                    [Disassembly]
                        0       RESUME                          0
                        2       LOAD_FAST                       0: self
                        4       LOAD_ATTR                       0: _main_modes
                        14      LOAD_ATTR                       1: selected_mode
                        24      LOAD_GLOBAL                     4: NOTE_MODE_NAMES
                        36      CONTAINS_OP                     0 (in)
                        38      RETURN_VALUE                    
                [Code]
                    File Name: output/Live/mac_universal_64_static/Release/python-bundle/MIDI Remote Scripts/Launchpad_Pro_MK3/launchpad_pro_mk3.py
                    Object Name: _feedback_velocity_changed
                    Qualified Name: Launchpad_Pro_MK3._feedback_velocity_changed
                    Arg Count: 2
                    Pos Only Arg Count: 0
                    KW Only Arg Count: 0
                    Stack Size: 3
                    Flags: 0x00000003 (CO_OPTIMIZED | CO_NEWLOCALS)
                    [Names]
                        '_elements'
                        'scale_feedback_switch'
                        'send_value'
                    [Locals+Names]
                        'self'
                        'feedback_velocity'
                    [Constants]
                        None
                    [Disassembly]
                        0       RESUME                          0
                        2       LOAD_FAST                       0: self
                        4       LOAD_ATTR                       0: _elements
                        14      LOAD_ATTR                       1: scale_feedback_switch
                        24      LOAD_METHOD                     2: send_value
                        46      LOAD_FAST                       1: feedback_velocity
                        48      PRECALL                         1
                        52      CALL                            1
                        62      POP_TOP                         
                        64      LOAD_CONST                      0: None
                        66      RETURN_VALUE                    
            [Disassembly]
                0       MAKE_CELL                       0: __class__
                2       RESUME                          0
                4       LOAD_NAME                       0: __name__
                6       STORE_NAME                      1: __module__
                8       LOAD_CONST                      0: 'Launchpad_Pro_MK3'
                10      STORE_NAME                      2: __qualname__
                12      LOAD_NAME                       3: ids
                14      LOAD_ATTR                       4: LP_PRO_MK3_FAMILY_CODE
                24      STORE_NAME                      5: model_family_code
                26      LOAD_NAME                       6: Elements
                28      STORE_NAME                      7: element_class
                30      LOAD_NAME                       8: SessionComponent
                32      STORE_NAME                      9: session_class
                34      LOAD_NAME                       10: MixerComponent
                36      STORE_NAME                      11: mixer_class
                38      LOAD_NAME                       12: ChannelStripComponent
                40      STORE_NAME                      13: channel_strip_class
                42      LOAD_NAME                       14: skin
                44      STORE_NAME                      14: skin
                46      LOAD_CONST                      1: False
                48      STORE_NAME                      15: suppress_layout_switch
                50      LOAD_NAME                       16: FixedLengthTrackRecordingComponent
                52      STORE_NAME                      17: track_recording_class
                54      LOAD_CLOSURE                    0: __class__
                56      BUILD_TUPLE                     1
                58      LOAD_CONST                      2: <CODE> __init__
                60      MAKE_FUNCTION                   8
                62      STORE_NAME                      18: __init__
                64      LOAD_CLOSURE                    0: __class__
                66      BUILD_TUPLE                     1
                68      LOAD_CONST                      3: <CODE> disconnect
                70      MAKE_FUNCTION                   8
                72      STORE_NAME                      19: disconnect
                74      LOAD_CLOSURE                    0: __class__
                76      BUILD_TUPLE                     1
                78      LOAD_CONST                      4: <CODE> on_identified
                80      MAKE_FUNCTION                   8
                82      STORE_NAME                      20: on_identified
                84      LOAD_CLOSURE                    0: __class__
                86      BUILD_TUPLE                     1
                88      LOAD_CONST                      5: <CODE> port_settings_changed
                90      MAKE_FUNCTION                   8
                92      STORE_NAME                      21: port_settings_changed
                94      LOAD_CONST                      6: <CODE> _setup_faders
                96      MAKE_FUNCTION                   0
                98      STORE_NAME                      22: _setup_faders
                100     LOAD_CLOSURE                    0: __class__
                102     BUILD_TUPLE                     1
                104     LOAD_CONST                      7: <CODE> _create_components
                106     MAKE_FUNCTION                   8
                108     STORE_NAME                      23: _create_components
                110     LOAD_CONST                      8: <CODE> _create_session_overview
                112     MAKE_FUNCTION                   0
                114     STORE_NAME                      24: _create_session_overview
                116     LOAD_CONST                      9: <CODE> _create_auto_arm
                118     MAKE_FUNCTION                   0
                120     STORE_NAME                      25: _create_auto_arm
                122     LOAD_CONST                      10: <CODE> _create_background
                124     MAKE_FUNCTION                   0
                126     STORE_NAME                      26: _create_background
                128     LOAD_CONST                      11: <CODE> _create_print_to_clip
                130     MAKE_FUNCTION                   0
                132     STORE_NAME                      27: _create_print_to_clip
                134     LOAD_CONST                      12: <CODE> _create_undo_redo
                136     MAKE_FUNCTION                   0
                138     STORE_NAME                      28: _create_undo_redo
                140     LOAD_CONST                      13: <CODE> _create_transport
                142     MAKE_FUNCTION                   0
                144     STORE_NAME                      29: _create_transport
                146     LOAD_CONST                      14: <CODE> _create_clip_actions
                148     MAKE_FUNCTION                   0
                150     STORE_NAME                      30: _create_clip_actions
                152     LOAD_CONST                      15: <CODE> _create_quantization
                154     MAKE_FUNCTION                   0
                156     STORE_NAME                      31: _create_quantization
                158     LOAD_CONST                      16: <CODE> _create_fixed_length
                160     MAKE_FUNCTION                   0
                162     STORE_NAME                      32: _create_fixed_length
                164     LOAD_CONST                      17: <CODE> _create_drum_group
                166     MAKE_FUNCTION                   0
                168     STORE_NAME                      33: _create_drum_group
                170     LOAD_CONST                      18: <CODE> _create_device_parameters
                172     MAKE_FUNCTION                   0
                174     STORE_NAME                      34: _create_device_parameters
                176     LOAD_CONST                      19: <CODE> _create_device_navigation
                178     MAKE_FUNCTION                   0
                180     STORE_NAME                      35: _create_device_navigation
                182     LOAD_CONST                      20: <CODE> _create_scale_pad_translator
                184     MAKE_FUNCTION                   0
                186     STORE_NAME                      36: _create_scale_pad_translator
                188     LOAD_CONST                      21: <CODE> _create_mixer_modes
                190     MAKE_FUNCTION                   0
                192     STORE_NAME                      37: _create_mixer_modes
                194     LOAD_CONST                      22: <CODE> _create_session_modes
                196     MAKE_FUNCTION                   0
                198     STORE_NAME                      38: _create_session_modes
                200     LOAD_CONST                      23: <CODE> _create_note_modes
                202     MAKE_FUNCTION                   0
                204     STORE_NAME                      39: _create_note_modes
                206     LOAD_CONST                      24: <CODE> _create_main_modes
                208     MAKE_FUNCTION                   0
                210     STORE_NAME                      40: _create_main_modes
                212     PUSH_NULL                       
                214     LOAD_NAME                       41: listens
                216     LOAD_CONST                      25: 'selected_mode'
                218     PRECALL                         1
                222     CALL                            1
                232     LOAD_CONST                      26: <CODE> __on_main_mode_changed
                234     MAKE_FUNCTION                   0
                236     PRECALL                         0
                240     CALL                            0
                250     STORE_NAME                      42: _Launchpad_Pro_MK3__on_main_mode_changed
                252     PUSH_NULL                       
                254     LOAD_NAME                       41: listens
                256     LOAD_CONST                      27: 'value'
                258     PRECALL                         1
                262     CALL                            1
                272     LOAD_CONST                      28: <CODE> __on_layout_switch_value
                274     MAKE_FUNCTION                   0
                276     PRECALL                         0
                280     CALL                            0
                290     STORE_NAME                      43: _Launchpad_Pro_MK3__on_layout_switch_value
                292     LOAD_CONST                      29: <CODE> _drum_group_changed
                294     MAKE_FUNCTION                   0
                296     STORE_NAME                      44: _drum_group_changed
                298     LOAD_CONST                      30: <CODE> _is_instrument_mode
                300     MAKE_FUNCTION                   0
                302     STORE_NAME                      45: _is_instrument_mode
                304     LOAD_CONST                      31: <CODE> _feedback_velocity_changed
                306     MAKE_FUNCTION                   0
                308     STORE_NAME                      46: _feedback_velocity_changed
                310     LOAD_CLOSURE                    0: __class__
                312     COPY                            1
                314     STORE_NAME                      47: __classcell__
                316     RETURN_VALUE                    
        'Launchpad_Pro_MK3'
        None
    [Disassembly]
        0       RESUME                          0
        2       LOAD_CONST                      0: 0
        4       LOAD_CONST                      1: ('partial',)
        6       IMPORT_NAME                     0: functools
        8       IMPORT_FROM                     1: partial
        10      STORE_NAME                      1: partial
        12      POP_TOP                         
        14      LOAD_CONST                      0: 0
        16      LOAD_CONST                      2: ('const', 'inject', 'listens', 'liveobj_valid')
        18      IMPORT_NAME                     2: ableton.v2.base
        20      IMPORT_FROM                     3: const
        22      STORE_NAME                      3: const
        24      IMPORT_FROM                     4: inject
        26      STORE_NAME                      4: inject
        28      IMPORT_FROM                     5: listens
        30      STORE_NAME                      5: listens
        32      IMPORT_FROM                     6: liveobj_valid
        34      STORE_NAME                      6: liveobj_valid
        36      POP_TOP                         
        38      LOAD_CONST                      0: 0
        40      LOAD_CONST                      3: ('Layer',)
        42      IMPORT_NAME                     7: ableton.v2.control_surface
        44      IMPORT_FROM                     8: Layer
        46      STORE_NAME                      8: Layer
        48      POP_TOP                         
        50      LOAD_CONST                      0: 0
        52      LOAD_CONST                      4: ('AutoArmComponent', 'BackgroundComponent', 'SessionOverviewComponent', 'UndoRedoComponent')
        54      IMPORT_NAME                     9: ableton.v2.control_surface.components
        56      IMPORT_FROM                     10: AutoArmComponent
        58      STORE_NAME                      10: AutoArmComponent
        60      IMPORT_FROM                     11: BackgroundComponent
        62      STORE_NAME                      11: BackgroundComponent
        64      IMPORT_FROM                     12: SessionOverviewComponent
        66      STORE_NAME                      12: SessionOverviewComponent
        68      IMPORT_FROM                     13: UndoRedoComponent
        70      STORE_NAME                      13: UndoRedoComponent
        72      POP_TOP                         
        74      LOAD_CONST                      0: 0
        76      LOAD_CONST                      5: ('AddLayerMode', 'DelayMode', 'ModesComponent', 'MomentaryBehaviour', 'ReenterBehaviour')
        78      IMPORT_NAME                     14: ableton.v2.control_surface.mode
        80      IMPORT_FROM                     15: AddLayerMode
        82      STORE_NAME                      15: AddLayerMode
        84      IMPORT_FROM                     16: DelayMode
        86      STORE_NAME                      16: DelayMode
        88      IMPORT_FROM                     17: ModesComponent
        90      STORE_NAME                      17: ModesComponent
        92      IMPORT_FROM                     18: MomentaryBehaviour
        94      STORE_NAME                      18: MomentaryBehaviour
        96      IMPORT_FROM                     19: ReenterBehaviour
        98      STORE_NAME                      19: ReenterBehaviour
        100     POP_TOP                         
        102     LOAD_CONST                      0: 0
        104     LOAD_CONST                      6: ('sysex',)
        106     IMPORT_NAME                     20: novation
        108     IMPORT_FROM                     21: sysex
        110     STORE_NAME                      21: sysex
        112     POP_TOP                         
        114     LOAD_CONST                      0: 0
        116     LOAD_CONST                      7: ('ClipActionsComponent',)
        118     IMPORT_NAME                     22: novation.clip_actions
        120     IMPORT_FROM                     23: ClipActionsComponent
        122     STORE_NAME                      23: ClipActionsComponent
        124     POP_TOP                         
        126     LOAD_CONST                      0: 0
        128     LOAD_CONST                      8: ('Rgb',)
        130     IMPORT_NAME                     24: novation.colors
        132     IMPORT_FROM                     25: Rgb
        134     STORE_NAME                      25: Rgb
        136     POP_TOP                         
        138     LOAD_CONST                      0: 0
        140     LOAD_CONST                      9: ('ConfigurablePlayableComponent',)
        142     IMPORT_NAME                     26: novation.configurable_playable
        144     IMPORT_FROM                     27: ConfigurablePlayableComponent
        146     STORE_NAME                      27: ConfigurablePlayableComponent
        148     POP_TOP                         
        150     LOAD_CONST                      0: 0
        152     LOAD_CONST                      10: ('FixedLengthComponent', 'FixedLengthSetting')
        154     IMPORT_NAME                     28: novation.fixed_length
        156     IMPORT_FROM                     29: FixedLengthComponent
        158     STORE_NAME                      29: FixedLengthComponent
        160     IMPORT_FROM                     30: FixedLengthSetting
        162     STORE_NAME                      30: FixedLengthSetting
        164     POP_TOP                         
        166     LOAD_CONST                      0: 0
        168     LOAD_CONST                      11: ('FixedLengthRecording',)
        170     IMPORT_NAME                     31: novation.fixed_length_recording
        172     IMPORT_FROM                     32: FixedLengthRecording
        174     STORE_NAME                      32: FixedLengthRecording
        176     POP_TOP                         
        178     LOAD_CONST                      0: 0
        180     LOAD_CONST                      12: ('InstrumentControlMixin',)
        182     IMPORT_NAME                     33: novation.instrument_control
        184     IMPORT_FROM                     34: InstrumentControlMixin
        186     STORE_NAME                      34: InstrumentControlMixin
        188     POP_TOP                         
        190     LOAD_CONST                      0: 0
        192     LOAD_CONST                      13: ('NovationBase',)
        194     IMPORT_NAME                     35: novation.novation_base
        196     IMPORT_FROM                     36: NovationBase
        198     STORE_NAME                      36: NovationBase
        200     POP_TOP                         
        202     LOAD_CONST                      0: 0
        204     LOAD_CONST                      14: ('PrintToClipComponent',)
        206     IMPORT_NAME                     37: novation.print_to_clip
        208     IMPORT_FROM                     38: PrintToClipComponent
        210     STORE_NAME                      38: PrintToClipComponent
        212     POP_TOP                         
        214     LOAD_CONST                      0: 0
        216     LOAD_CONST                      15: ('QuantizationComponent',)
        218     IMPORT_NAME                     39: novation.quantization
        220     IMPORT_FROM                     40: QuantizationComponent
        222     STORE_NAME                      40: QuantizationComponent
        224     POP_TOP                         
        226     LOAD_CONST                      0: 0
        228     LOAD_CONST                      16: ('SimpleDeviceNavigationComponent',)
        230     IMPORT_NAME                     41: novation.simple_device_navigation
        232     IMPORT_FROM                     42: SimpleDeviceNavigationComponent
        234     STORE_NAME                      42: SimpleDeviceNavigationComponent
        236     POP_TOP                         
        238     LOAD_CONST                      0: 0
        240     LOAD_CONST                      17: ('FixedLengthTrackRecordingComponent',)
        242     IMPORT_NAME                     43: novation.track_recording
        244     IMPORT_FROM                     44: FixedLengthTrackRecordingComponent
        246     STORE_NAME                      44: FixedLengthTrackRecordingComponent
        248     POP_TOP                         
        250     LOAD_CONST                      18: 1
        252     LOAD_CONST                      19: ('sysex_ids',)
        254     IMPORT_NAME                     45: 
        256     IMPORT_FROM                     46: sysex_ids
        258     STORE_NAME                      47: ids
        260     POP_TOP                         
        262     LOAD_CONST                      18: 1
        264     LOAD_CONST                      20: ('ChannelStripComponent',)
        266     IMPORT_NAME                     48: channel_strip
        268     IMPORT_FROM                     49: ChannelStripComponent
        270     STORE_NAME                      49: ChannelStripComponent
        272     POP_TOP                         
        274     LOAD_CONST                      18: 1
        276     LOAD_CONST                      21: ('DrumGroupComponent',)
        278     IMPORT_NAME                     50: drum_group
        280     IMPORT_FROM                     51: DrumGroupComponent
        282     STORE_NAME                      51: DrumGroupComponent
        284     POP_TOP                         
        286     LOAD_CONST                      18: 1
        288     LOAD_CONST                      22: ('FADER_MODES', 'Elements')
        290     IMPORT_NAME                     52: elements
        292     IMPORT_FROM                     53: FADER_MODES
        294     STORE_NAME                      53: FADER_MODES
        296     IMPORT_FROM                     54: Elements
        298     STORE_NAME                      54: Elements
        300     POP_TOP                         
        302     LOAD_CONST                      18: 1
        304     LOAD_CONST                      23: ('MixerComponent',)
        306     IMPORT_NAME                     55: mixer
        308     IMPORT_FROM                     56: MixerComponent
        310     STORE_NAME                      56: MixerComponent
        312     POP_TOP                         
        314     LOAD_CONST                      18: 1
        316     LOAD_CONST                      24: ('SessionComponent',)
        318     IMPORT_NAME                     57: session
        320     IMPORT_FROM                     58: SessionComponent
        322     STORE_NAME                      58: SessionComponent
        324     POP_TOP                         
        326     LOAD_CONST                      18: 1
        328     LOAD_CONST                      25: ('SimpleDeviceParameterComponent',)
        330     IMPORT_NAME                     59: simple_device
        332     IMPORT_FROM                     60: SimpleDeviceParameterComponent
        334     STORE_NAME                      60: SimpleDeviceParameterComponent
        336     POP_TOP                         
        338     LOAD_CONST                      18: 1
        340     LOAD_CONST                      26: ('skin',)
        342     IMPORT_NAME                     61: skin
        344     IMPORT_FROM                     61: skin
        346     STORE_NAME                      61: skin
        348     POP_TOP                         
        350     LOAD_CONST                      18: 1
        352     LOAD_CONST                      27: ('TransportComponent',)
        354     IMPORT_NAME                     62: transport
        356     IMPORT_FROM                     63: TransportComponent
        358     STORE_NAME                      63: TransportComponent
        360     POP_TOP                         
        362     LOAD_CONST                      18: 1
        364     STORE_NAME                      64: DRUM_FEEDBACK_CHANNEL
        366     LOAD_CONST                      28: 2
        368     STORE_NAME                      65: SCALE_FEEDBACK_CHANNEL
        370     LOAD_NAME                       47: ids
        372     LOAD_ATTR                       66: SESSION_LAYOUT_BYTES
        382     LOAD_CONST                      29: 'session'
        384     LOAD_NAME                       47: ids
        386     LOAD_ATTR                       67: CHORD_LAYOUT_BYTES
        396     LOAD_CONST                      30: 'chord'
        398     LOAD_NAME                       47: ids
        400     LOAD_ATTR                       68: NOTE_LAYOUT_BYTES
        410     LOAD_CONST                      31: 'note'
        412     BUILD_MAP                       3
        414     STORE_NAME                      69: LAYOUT_BYTES_TO_MODE_NAMES_MAP
        416     LOAD_NAME                       47: ids
        418     LOAD_ATTR                       66: SESSION_LAYOUT_BYTES
        428     LOAD_CONST                      0: 0
        430     BINARY_SUBSCR                   
        440     LOAD_NAME                       47: ids
        442     LOAD_ATTR                       67: CHORD_LAYOUT_BYTES
        452     LOAD_CONST                      0: 0
        454     BINARY_SUBSCR                   
        464     LOAD_NAME                       47: ids
        466     LOAD_ATTR                       68: NOTE_LAYOUT_BYTES
        476     LOAD_CONST                      0: 0
        478     BINARY_SUBSCR                   
        488     LOAD_NAME                       47: ids
        490     LOAD_ATTR                       70: FADER_LAYOUT_BYTE
        500     BUILD_TUPLE                     4
        502     STORE_NAME                      71: LIVE_LAYOUT_BYTES
        504     LOAD_CONST                      32: ('chord', 'note')
        506     STORE_NAME                      72: NOTE_MODE_NAMES
        508     PUSH_NULL                       
        510     LOAD_BUILD_CLASS                
        512     LOAD_CONST                      33: <CODE> Launchpad_Pro_MK3
        514     MAKE_FUNCTION                   0
        516     LOAD_CONST                      34: 'Launchpad_Pro_MK3'
        518     LOAD_NAME                       34: InstrumentControlMixin
        520     LOAD_NAME                       36: NovationBase
        522     PRECALL                         4
        526     CALL                            4
        536     STORE_NAME                      73: Launchpad_Pro_MK3
        538     LOAD_CONST                      35: None
        540     RETURN_VALUE                    
