skin.pyc (Python 3.11)
[Code]
    File Name: output/Live/mac_universal_64_static/Release/python-bundle/MIDI Remote Scripts/Launchpad_Pro_MK3/skin.py
    Object Name: <module>
    Qualified Name: <module>
    Arg Count: 0
    Pos Only Arg Count: 0
    KW Only Arg Count: 0
    Stack Size: 6
    Flags: 0x00000000
    [Names]
        'ableton.v2.control_surface'
        'Skin'
        'merge_skins'
        'novation.colors'
        'Rgb'
        'novation.skin'
        'skin'
        'base_skin'
        'object'
        'Colors'
    [Locals+Names]
    [Constants]
        0
        (
            'Skin'
            'merge_skins'
        )
        (
            'Rgb'
        )
        (
            'skin'
        )
        [Code]
            File Name: output/Live/mac_universal_64_static/Release/python-bundle/MIDI Remote Scripts/Launchpad_Pro_MK3/skin.py
            Object Name: Colors
            Qualified Name: Colors
            Arg Count: 0
            Pos Only Arg Count: 0
            KW Only Arg Count: 0
            Stack Size: 5
            Flags: 0x00000000
            [Names]
                '__name__'
                '__module__'
                '__qualname__'
                'object'
                'Device'
                'Mode'
                'Recording'
                'Transport'
                'Quantization'
            [Locals+Names]
            [Constants]
                'Colors'
                [Code]
                    File Name: output/Live/mac_universal_64_static/Release/python-bundle/MIDI Remote Scripts/Launchpad_Pro_MK3/skin.py
                    Object Name: Device
                    Qualified Name: Colors.Device
                    Arg Count: 0
                    Pos Only Arg Count: 0
                    KW Only Arg Count: 0
                    Stack Size: 1
                    Flags: 0x00000000
                    [Names]
                        '__name__'
                        '__module__'
                        '__qualname__'
                        'Rgb'
                        'DARK_BLUE_HALF'
                        'Navigation'
                        'WHITE'
                        'NavigationPressed'
                    [Locals+Names]
                    [Constants]
                        'Colors.Device'
                        None
                    [Disassembly]
                        0       RESUME                          0
                        2       LOAD_NAME                       0: __name__
                        4       STORE_NAME                      1: __module__
                        6       LOAD_CONST                      0: 'Colors.Device'
                        8       STORE_NAME                      2: __qualname__
                        10      LOAD_NAME                       3: Rgb
                        12      LOAD_ATTR                       4: DARK_BLUE_HALF
                        22      STORE_NAME                      5: Navigation
                        24      LOAD_NAME                       3: Rgb
                        26      LOAD_ATTR                       6: WHITE
                        36      STORE_NAME                      7: NavigationPressed
                        38      LOAD_CONST                      1: None
                        40      RETURN_VALUE                    
                'Device'
                [Code]
                    File Name: output/Live/mac_universal_64_static/Release/python-bundle/MIDI Remote Scripts/Launchpad_Pro_MK3/skin.py
                    Object Name: Mode
                    Qualified Name: Colors.Mode
                    Arg Count: 0
                    Pos Only Arg Count: 0
                    KW Only Arg Count: 0
                    Stack Size: 5
                    Flags: 0x00000000
                    [Names]
                        '__name__'
                        '__module__'
                        '__qualname__'
                        'object'
                        'Device'
                        'Sends'
                    [Locals+Names]
                    [Constants]
                        'Colors.Mode'
                        [Code]
                            File Name: output/Live/mac_universal_64_static/Release/python-bundle/MIDI Remote Scripts/Launchpad_Pro_MK3/skin.py
                            Object Name: Device
                            Qualified Name: Colors.Mode.Device
                            Arg Count: 0
                            Pos Only Arg Count: 0
                            KW Only Arg Count: 0
                            Stack Size: 5
                            Flags: 0x00000000
                            [Names]
                                '__name__'
                                '__module__'
                                '__qualname__'
                                'Rgb'
                                'DARK_BLUE'
                                'On'
                                'WHITE_HALF'
                                'Off'
                                'object'
                                'Bank'
                            [Locals+Names]
                            [Constants]
                                'Colors.Mode.Device'
                                [Code]
                                    File Name: output/Live/mac_universal_64_static/Release/python-bundle/MIDI Remote Scripts/Launchpad_Pro_MK3/skin.py
                                    Object Name: Bank
                                    Qualified Name: Colors.Mode.Device.Bank
                                    Arg Count: 0
                                    Pos Only Arg Count: 0
                                    KW Only Arg Count: 0
                                    Stack Size: 1
                                    Flags: 0x00000000
                                    [Names]
                                        '__name__'
                                        '__module__'
                                        '__qualname__'
                                        'Rgb'
                                        'DARK_BLUE'
                                        'Selected'
                                        'WHITE_HALF'
                                        'Available'
                                    [Locals+Names]
                                    [Constants]
                                        'Colors.Mode.Device.Bank'
                                        None
                                    [Disassembly]
                                        0       RESUME                          0
                                        2       LOAD_NAME                       0: __name__
                                        4       STORE_NAME                      1: __module__
                                        6       LOAD_CONST                      0: 'Colors.Mode.Device.Bank'
                                        8       STORE_NAME                      2: __qualname__
                                        10      LOAD_NAME                       3: Rgb
                                        12      LOAD_ATTR                       4: DARK_BLUE
                                        22      STORE_NAME                      5: Selected
                                        24      LOAD_NAME                       3: Rgb
                                        26      LOAD_ATTR                       6: WHITE_HALF
                                        36      STORE_NAME                      7: Available
                                        38      LOAD_CONST                      1: None
                                        40      RETURN_VALUE                    
                                'Bank'
                                None
                            [Disassembly]
                                0       RESUME                          0
                                2       LOAD_NAME                       0: __name__
                                4       STORE_NAME                      1: __module__
                                6       LOAD_CONST                      0: 'Colors.Mode.Device'
                                8       STORE_NAME                      2: __qualname__
                                10      LOAD_NAME                       3: Rgb
                                12      LOAD_ATTR                       4: DARK_BLUE
                                22      STORE_NAME                      5: On
                                24      LOAD_NAME                       3: Rgb
                                26      LOAD_ATTR                       6: WHITE_HALF
                                36      STORE_NAME                      7: Off
                                38      PUSH_NULL                       
                                40      LOAD_BUILD_CLASS                
                                42      LOAD_CONST                      1: <CODE> Bank
                                44      MAKE_FUNCTION                   0
                                46      LOAD_CONST                      2: 'Bank'
                                48      LOAD_NAME                       8: object
                                50      PRECALL                         3
                                54      CALL                            3
                                64      STORE_NAME                      9: Bank
                                66      LOAD_CONST                      3: None
                                68      RETURN_VALUE                    
                        'Device'
                        [Code]
                            File Name: output/Live/mac_universal_64_static/Release/python-bundle/MIDI Remote Scripts/Launchpad_Pro_MK3/skin.py
                            Object Name: Sends
                            Qualified Name: Colors.Mode.Sends
                            Arg Count: 0
                            Pos Only Arg Count: 0
                            KW Only Arg Count: 0
                            Stack Size: 5
                            Flags: 0x00000000
                            [Names]
                                '__name__'
                                '__module__'
                                '__qualname__'
                                'Rgb'
                                'VIOLET'
                                'On'
                                'WHITE_HALF'
                                'Off'
                                'object'
                                'Bank'
                            [Locals+Names]
                            [Constants]
                                'Colors.Mode.Sends'
                                [Code]
                                    File Name: output/Live/mac_universal_64_static/Release/python-bundle/MIDI Remote Scripts/Launchpad_Pro_MK3/skin.py
                                    Object Name: Bank
                                    Qualified Name: Colors.Mode.Sends.Bank
                                    Arg Count: 0
                                    Pos Only Arg Count: 0
                                    KW Only Arg Count: 0
                                    Stack Size: 1
                                    Flags: 0x00000000
                                    [Names]
                                        '__name__'
                                        '__module__'
                                        '__qualname__'
                                        'Rgb'
                                        'WHITE_HALF'
                                        'Available'
                                    [Locals+Names]
                                    [Constants]
                                        'Colors.Mode.Sends.Bank'
                                        None
                                    [Disassembly]
                                        0       RESUME                          0
                                        2       LOAD_NAME                       0: __name__
                                        4       STORE_NAME                      1: __module__
                                        6       LOAD_CONST                      0: 'Colors.Mode.Sends.Bank'
                                        8       STORE_NAME                      2: __qualname__
                                        10      LOAD_NAME                       3: Rgb
                                        12      LOAD_ATTR                       4: WHITE_HALF
                                        22      STORE_NAME                      5: Available
                                        24      LOAD_CONST                      1: None
                                        26      RETURN_VALUE                    
                                'Bank'
                                None
                            [Disassembly]
                                0       RESUME                          0
                                2       LOAD_NAME                       0: __name__
                                4       STORE_NAME                      1: __module__
                                6       LOAD_CONST                      0: 'Colors.Mode.Sends'
                                8       STORE_NAME                      2: __qualname__
                                10      LOAD_NAME                       3: Rgb
                                12      LOAD_ATTR                       4: VIOLET
                                22      STORE_NAME                      5: On
                                24      LOAD_NAME                       3: Rgb
                                26      LOAD_ATTR                       6: WHITE_HALF
                                36      STORE_NAME                      7: Off
                                38      PUSH_NULL                       
                                40      LOAD_BUILD_CLASS                
                                42      LOAD_CONST                      1: <CODE> Bank
                                44      MAKE_FUNCTION                   0
                                46      LOAD_CONST                      2: 'Bank'
                                48      LOAD_NAME                       8: object
                                50      PRECALL                         3
                                54      CALL                            3
                                64      STORE_NAME                      9: Bank
                                66      LOAD_CONST                      3: None
                                68      RETURN_VALUE                    
                        'Sends'
                        None
                    [Disassembly]
                        0       RESUME                          0
                        2       LOAD_NAME                       0: __name__
                        4       STORE_NAME                      1: __module__
                        6       LOAD_CONST                      0: 'Colors.Mode'
                        8       STORE_NAME                      2: __qualname__
                        10      PUSH_NULL                       
                        12      LOAD_BUILD_CLASS                
                        14      LOAD_CONST                      1: <CODE> Device
                        16      MAKE_FUNCTION                   0
                        18      LOAD_CONST                      2: 'Device'
                        20      LOAD_NAME                       3: object
                        22      PRECALL                         3
                        26      CALL                            3
                        36      STORE_NAME                      4: Device
                        38      PUSH_NULL                       
                        40      LOAD_BUILD_CLASS                
                        42      LOAD_CONST                      3: <CODE> Sends
                        44      MAKE_FUNCTION                   0
                        46      LOAD_CONST                      4: 'Sends'
                        48      LOAD_NAME                       3: object
                        50      PRECALL                         3
                        54      CALL                            3
                        64      STORE_NAME                      5: Sends
                        66      LOAD_CONST                      5: None
                        68      RETURN_VALUE                    
                'Mode'
                [Code]
                    File Name: output/Live/mac_universal_64_static/Release/python-bundle/MIDI Remote Scripts/Launchpad_Pro_MK3/skin.py
                    Object Name: Recording
                    Qualified Name: Colors.Recording
                    Arg Count: 0
                    Pos Only Arg Count: 0
                    KW Only Arg Count: 0
                    Stack Size: 1
                    Flags: 0x00000000
                    [Names]
                        '__name__'
                        '__module__'
                        '__qualname__'
                        'Rgb'
                        'WHITE_HALF'
                        'Off'
                    [Locals+Names]
                    [Constants]
                        'Colors.Recording'
                        None
                    [Disassembly]
                        0       RESUME                          0
                        2       LOAD_NAME                       0: __name__
                        4       STORE_NAME                      1: __module__
                        6       LOAD_CONST                      0: 'Colors.Recording'
                        8       STORE_NAME                      2: __qualname__
                        10      LOAD_NAME                       3: Rgb
                        12      LOAD_ATTR                       4: WHITE_HALF
                        22      STORE_NAME                      5: Off
                        24      LOAD_CONST                      1: None
                        26      RETURN_VALUE                    
                'Recording'
                [Code]
                    File Name: output/Live/mac_universal_64_static/Release/python-bundle/MIDI Remote Scripts/Launchpad_Pro_MK3/skin.py
                    Object Name: Transport
                    Qualified Name: Colors.Transport
                    Arg Count: 0
                    Pos Only Arg Count: 0
                    KW Only Arg Count: 0
                    Stack Size: 1
                    Flags: 0x00000000
                    [Names]
                        '__name__'
                        '__module__'
                        '__qualname__'
                        'Rgb'
                        'WHITE_HALF'
                        'PlayOff'
                        'GREEN'
                        'PlayOn'
                        'AQUA'
                        'ContinueOff'
                        'RED_HALF'
                        'ContinueOn'
                        'BLACK'
                        'CaptureOff'
                        'CREAM'
                        'CaptureOn'
                        'TapTempo'
                    [Locals+Names]
                    [Constants]
                        'Colors.Transport'
                        None
                    [Disassembly]
                        0       RESUME                          0
                        2       LOAD_NAME                       0: __name__
                        4       STORE_NAME                      1: __module__
                        6       LOAD_CONST                      0: 'Colors.Transport'
                        8       STORE_NAME                      2: __qualname__
                        10      LOAD_NAME                       3: Rgb
                        12      LOAD_ATTR                       4: WHITE_HALF
                        22      STORE_NAME                      5: PlayOff
                        24      LOAD_NAME                       3: Rgb
                        26      LOAD_ATTR                       6: GREEN
                        36      STORE_NAME                      7: PlayOn
                        38      LOAD_NAME                       3: Rgb
                        40      LOAD_ATTR                       8: AQUA
                        50      STORE_NAME                      9: ContinueOff
                        52      LOAD_NAME                       3: Rgb
                        54      LOAD_ATTR                       10: RED_HALF
                        64      STORE_NAME                      11: ContinueOn
                        66      LOAD_NAME                       3: Rgb
                        68      LOAD_ATTR                       12: BLACK
                        78      STORE_NAME                      13: CaptureOff
                        80      LOAD_NAME                       3: Rgb
                        82      LOAD_ATTR                       14: CREAM
                        92      STORE_NAME                      15: CaptureOn
                        94      LOAD_NAME                       3: Rgb
                        96      LOAD_ATTR                       14: CREAM
                        106     STORE_NAME                      16: TapTempo
                        108     LOAD_CONST                      1: None
                        110     RETURN_VALUE                    
                'Transport'
                [Code]
                    File Name: output/Live/mac_universal_64_static/Release/python-bundle/MIDI Remote Scripts/Launchpad_Pro_MK3/skin.py
                    Object Name: Quantization
                    Qualified Name: Colors.Quantization
                    Arg Count: 0
                    Pos Only Arg Count: 0
                    KW Only Arg Count: 0
                    Stack Size: 1
                    Flags: 0x00000000
                    [Names]
                        '__name__'
                        '__module__'
                        '__qualname__'
                        'Rgb'
                        'RED_HALF'
                        'Off'
                        'AQUA'
                        'On'
                    [Locals+Names]
                    [Constants]
                        'Colors.Quantization'
                        None
                    [Disassembly]
                        0       RESUME                          0
                        2       LOAD_NAME                       0: __name__
                        4       STORE_NAME                      1: __module__
                        6       LOAD_CONST                      0: 'Colors.Quantization'
                        8       STORE_NAME                      2: __qualname__
                        10      LOAD_NAME                       3: Rgb
                        12      LOAD_ATTR                       4: RED_HALF
                        22      STORE_NAME                      5: Off
                        24      LOAD_NAME                       3: Rgb
                        26      LOAD_ATTR                       6: AQUA
                        36      STORE_NAME                      7: On
                        38      LOAD_CONST                      1: None
                        40      RETURN_VALUE                    
                'Quantization'
                None
            [Disassembly]
                0       RESUME                          0
                2       LOAD_NAME                       0: __name__
                4       STORE_NAME                      1: __module__
                6       LOAD_CONST                      0: 'Colors'
                8       STORE_NAME                      2: __qualname__
                10      PUSH_NULL                       
                12      LOAD_BUILD_CLASS                
                14      LOAD_CONST                      1: <CODE> Device
                16      MAKE_FUNCTION                   0
                18      LOAD_CONST                      2: 'Device'
                20      LOAD_NAME                       3: object
                22      PRECALL                         3
                26      CALL                            3
                36      STORE_NAME                      4: Device
                38      PUSH_NULL                       
                40      LOAD_BUILD_CLASS                
                42      LOAD_CONST                      3: <CODE> Mode
                44      MAKE_FUNCTION                   0
                46      LOAD_CONST                      4: 'Mode'
                48      LOAD_NAME                       3: object
                50      PRECALL                         3
                54      CALL                            3
                64      STORE_NAME                      5: Mode
                66      PUSH_NULL                       
                68      LOAD_BUILD_CLASS                
                70      LOAD_CONST                      5: <CODE> Recording
                72      MAKE_FUNCTION                   0
                74      LOAD_CONST                      6: 'Recording'
                76      LOAD_NAME                       3: object
                78      PRECALL                         3
                82      CALL                            3
                92      STORE_NAME                      6: Recording
                94      PUSH_NULL                       
                96      LOAD_BUILD_CLASS                
                98      LOAD_CONST                      7: <CODE> Transport
                100     MAKE_FUNCTION                   0
                102     LOAD_CONST                      8: 'Transport'
                104     LOAD_NAME                       3: object
                106     PRECALL                         3
                110     CALL                            3
                120     STORE_NAME                      7: Transport
                122     PUSH_NULL                       
                124     LOAD_BUILD_CLASS                
                126     LOAD_CONST                      9: <CODE> Quantization
                128     MAKE_FUNCTION                   0
                130     LOAD_CONST                      10: 'Quantization'
                132     LOAD_NAME                       3: object
                134     PRECALL                         3
                138     CALL                            3
                148     STORE_NAME                      8: Quantization
                150     LOAD_CONST                      11: None
                152     RETURN_VALUE                    
        'Colors'
        None
    [Disassembly]
        0       RESUME                          0
        2       LOAD_CONST                      0: 0
        4       LOAD_CONST                      1: ('Skin', 'merge_skins')
        6       IMPORT_NAME                     0: ableton.v2.control_surface
        8       IMPORT_FROM                     1: Skin
        10      STORE_NAME                      1: Skin
        12      IMPORT_FROM                     2: merge_skins
        14      STORE_NAME                      2: merge_skins
        16      POP_TOP                         
        18      LOAD_CONST                      0: 0
        20      LOAD_CONST                      2: ('Rgb',)
        22      IMPORT_NAME                     3: novation.colors
        24      IMPORT_FROM                     4: Rgb
        26      STORE_NAME                      4: Rgb
        28      POP_TOP                         
        30      LOAD_CONST                      0: 0
        32      LOAD_CONST                      3: ('skin',)
        34      IMPORT_NAME                     5: novation.skin
        36      IMPORT_FROM                     6: skin
        38      STORE_NAME                      7: base_skin
        40      POP_TOP                         
        42      PUSH_NULL                       
        44      LOAD_BUILD_CLASS                
        46      LOAD_CONST                      4: <CODE> Colors
        48      MAKE_FUNCTION                   0
        50      LOAD_CONST                      5: 'Colors'
        52      LOAD_NAME                       8: object
        54      PRECALL                         3
        58      CALL                            3
        68      STORE_NAME                      9: Colors
        70      PUSH_NULL                       
        72      LOAD_NAME                       2: merge_skins
        74      LOAD_NAME                       7: base_skin
        76      PUSH_NULL                       
        78      LOAD_NAME                       1: Skin
        80      LOAD_NAME                       9: Colors
        82      PRECALL                         1
        86      CALL                            1
        96      BUILD_TUPLE                     2
        98      CALL_FUNCTION_EX                0
        100     STORE_NAME                      6: skin
        102     LOAD_CONST                      6: None
        104     RETURN_VALUE                    
