sysex_ids.pyc (Python 3.11)
[Code]
    File Name: output/Live/mac_universal_64_static/Release/python-bundle/MIDI Remote Scripts/Launchpad_Pro_MK3/sysex_ids.py
    Object Name: <module>
    Qualified Name: <module>
    Arg Count: 0
    Pos Only Arg Count: 0
    KW Only Arg Count: 0
    Stack Size: 1
    Flags: 0x00000000
    [Names]
        'LP_PRO_MK3_FAMILY_CODE'
        'LP_PRO_MK3_ID'
        'SESSION_LAYOUT_BYTES'
        'CHORD_LAYOUT_BYTES'
        'NOTE_LAYOUT_BYTES'
        'FADER_LAYOUT_BYTE'
        'SCALE_LAYOUT_BYTES'
        'DRUM_LAYOUT_BYTES'
    [Locals+Names]
    [Constants]
        (
            35
            1
        )
        14
        (
            0
            0
            0
        )
        (
            2
            0
            0
        )
        (
            4
            0
            0
        )
        1
        (
            1
        )
        (
            2
        )
        None
    [Disassembly]
        0       RESUME                          0
        2       LOAD_CONST                      0: (35, 1)
        4       STORE_NAME                      0: LP_PRO_MK3_FAMILY_CODE
        6       LOAD_CONST                      1: 14
        8       STORE_NAME                      1: LP_PRO_MK3_ID
        10      LOAD_CONST                      2: (0, 0, 0)
        12      STORE_NAME                      2: SESSION_LAYOUT_BYTES
        14      LOAD_CONST                      3: (2, 0, 0)
        16      STORE_NAME                      3: CHORD_LAYOUT_BYTES
        18      LOAD_CONST                      4: (4, 0, 0)
        20      STORE_NAME                      4: NOTE_LAYOUT_BYTES
        22      LOAD_CONST                      5: 1
        24      STORE_NAME                      5: FADER_LAYOUT_BYTE
        26      LOAD_CONST                      6: (1,)
        28      STORE_NAME                      6: SCALE_LAYOUT_BYTES
        30      LOAD_CONST                      7: (2,)
        32      STORE_NAME                      7: DRUM_LAYOUT_BYTES
        34      LOAD_CONST                      8: None
        36      RETURN_VALUE                    
