skin.pyc (Python 3.11)
[Code]
    File Name: output/Live/mac_universal_64_static/Release/python-bundle/MIDI Remote Scripts/novation/skin.py
    Object Name: <module>
    Qualified Name: <module>
    Arg Count: 0
    Pos Only Arg Count: 0
    KW Only Arg Count: 0
    Stack Size: 5
    Flags: 0x00000000
    [Names]
        'ableton.v2.control_surface'
        'Skin'
        'colors'
        'Mono'
        'Rgb'
        'object'
        'Colors'
        'skin'
    [Locals+Names]
    [Constants]
        0
        (
            'Skin'
        )
        1
        (
            'Mono'
            'Rgb'
        )
        [Code]
            File Name: output/Live/mac_universal_64_static/Release/python-bundle/MIDI Remote Scripts/novation/skin.py
            Object Name: Colors
            Qualified Name: Colors
            Arg Count: 0
            Pos Only Arg Count: 0
            KW Only Arg Count: 0
            Stack Size: 5
            Flags: 0x00000000
            [Names]
                '__name__'
                '__module__'
                '__qualname__'
                'object'
                'DefaultButton'
                'Recording'
                'FixedLength'
                'Transport'
                'Action'
                'Session'
                'Zooming'
                'Mixer'
                'DrumGroup'
                'Mode'
            [Locals+Names]
            [Constants]
                'Colors'
                [Code]
                    File Name: output/Live/mac_universal_64_static/Release/python-bundle/MIDI Remote Scripts/novation/skin.py
                    Object Name: DefaultButton
                    Qualified Name: Colors.DefaultButton
                    Arg Count: 0
                    Pos Only Arg Count: 0
                    KW Only Arg Count: 0
                    Stack Size: 1
                    Flags: 0x00000000
                    [Names]
                        '__name__'
                        '__module__'
                        '__qualname__'
                        'Rgb'
                        'GREEN'
                        'On'
                        'BLACK'
                        'Off'
                        'Disabled'
                    [Locals+Names]
                    [Constants]
                        'Colors.DefaultButton'
                        None
                    [Disassembly]
                        0       RESUME                          0
                        2       LOAD_NAME                       0: __name__
                        4       STORE_NAME                      1: __module__
                        6       LOAD_CONST                      0: 'Colors.DefaultButton'
                        8       STORE_NAME                      2: __qualname__
                        10      LOAD_NAME                       3: Rgb
                        12      LOAD_ATTR                       4: GREEN
                        22      STORE_NAME                      5: On
                        24      LOAD_NAME                       3: Rgb
                        26      LOAD_ATTR                       6: BLACK
                        36      STORE_NAME                      7: Off
                        38      LOAD_NAME                       3: Rgb
                        40      LOAD_ATTR                       6: BLACK
                        50      STORE_NAME                      8: Disabled
                        52      LOAD_CONST                      1: None
                        54      RETURN_VALUE                    
                'DefaultButton'
                [Code]
                    File Name: output/Live/mac_universal_64_static/Release/python-bundle/MIDI Remote Scripts/novation/skin.py
                    Object Name: Recording
                    Qualified Name: Colors.Recording
                    Arg Count: 0
                    Pos Only Arg Count: 0
                    KW Only Arg Count: 0
                    Stack Size: 1
                    Flags: 0x00000000
                    [Names]
                        '__name__'
                        '__module__'
                        '__qualname__'
                        'Rgb'
                        'RED'
                        'On'
                        'RED_HALF'
                        'Off'
                        'RED_BLINK'
                        'Transition'
                        'WHITE'
                        'CaptureTriggered'
                    [Locals+Names]
                    [Constants]
                        'Colors.Recording'
                        None
                    [Disassembly]
                        0       RESUME                          0
                        2       LOAD_NAME                       0: __name__
                        4       STORE_NAME                      1: __module__
                        6       LOAD_CONST                      0: 'Colors.Recording'
                        8       STORE_NAME                      2: __qualname__
                        10      LOAD_NAME                       3: Rgb
                        12      LOAD_ATTR                       4: RED
                        22      STORE_NAME                      5: On
                        24      LOAD_NAME                       3: Rgb
                        26      LOAD_ATTR                       6: RED_HALF
                        36      STORE_NAME                      7: Off
                        38      LOAD_NAME                       3: Rgb
                        40      LOAD_ATTR                       8: RED_BLINK
                        50      STORE_NAME                      9: Transition
                        52      LOAD_NAME                       3: Rgb
                        54      LOAD_ATTR                       10: WHITE
                        64      STORE_NAME                      11: CaptureTriggered
                        66      LOAD_CONST                      1: None
                        68      RETURN_VALUE                    
                'Recording'
                [Code]
                    File Name: output/Live/mac_universal_64_static/Release/python-bundle/MIDI Remote Scripts/novation/skin.py
                    Object Name: FixedLength
                    Qualified Name: Colors.FixedLength
                    Arg Count: 0
                    Pos Only Arg Count: 0
                    KW Only Arg Count: 0
                    Stack Size: 1
                    Flags: 0x00000000
                    [Names]
                        '__name__'
                        '__module__'
                        '__qualname__'
                        'Rgb'
                        'BLUE'
                        'On'
                        'WHITE_HALF'
                        'Off'
                        'BLUE_PULSE'
                        'Held'
                        'BLACK'
                        'Option'
                        'OptionInRange'
                        'OptionHeld'
                    [Locals+Names]
                    [Constants]
                        'Colors.FixedLength'
                        None
                    [Disassembly]
                        0       RESUME                          0
                        2       LOAD_NAME                       0: __name__
                        4       STORE_NAME                      1: __module__
                        6       LOAD_CONST                      0: 'Colors.FixedLength'
                        8       STORE_NAME                      2: __qualname__
                        10      LOAD_NAME                       3: Rgb
                        12      LOAD_ATTR                       4: BLUE
                        22      STORE_NAME                      5: On
                        24      LOAD_NAME                       3: Rgb
                        26      LOAD_ATTR                       6: WHITE_HALF
                        36      STORE_NAME                      7: Off
                        38      LOAD_NAME                       3: Rgb
                        40      LOAD_ATTR                       8: BLUE_PULSE
                        50      STORE_NAME                      9: Held
                        52      LOAD_NAME                       3: Rgb
                        54      LOAD_ATTR                       10: BLACK
                        64      STORE_NAME                      11: Option
                        66      LOAD_NAME                       3: Rgb
                        68      LOAD_ATTR                       8: BLUE_PULSE
                        78      STORE_NAME                      12: OptionInRange
                        80      LOAD_NAME                       3: Rgb
                        82      LOAD_ATTR                       4: BLUE
                        92      STORE_NAME                      13: OptionHeld
                        94      LOAD_CONST                      1: None
                        96      RETURN_VALUE                    
                'FixedLength'
                [Code]
                    File Name: output/Live/mac_universal_64_static/Release/python-bundle/MIDI Remote Scripts/novation/skin.py
                    Object Name: Transport
                    Qualified Name: Colors.Transport
                    Arg Count: 0
                    Pos Only Arg Count: 0
                    KW Only Arg Count: 0
                    Stack Size: 1
                    Flags: 0x00000000
                    [Names]
                        '__name__'
                        '__module__'
                        '__qualname__'
                        'Mono'
                        'OFF'
                        'PlayOff'
                        'ON'
                        'PlayOn'
                        'ContinueOff'
                        'HALF'
                        'ContinueOn'
                        'CaptureOff'
                        'CaptureOn'
                        'Rgb'
                        'RED_HALF'
                        'MetronomeOff'
                        'AQUA'
                        'MetronomeOn'
                    [Locals+Names]
                    [Constants]
                        'Colors.Transport'
                        None
                    [Disassembly]
                        0       RESUME                          0
                        2       LOAD_NAME                       0: __name__
                        4       STORE_NAME                      1: __module__
                        6       LOAD_CONST                      0: 'Colors.Transport'
                        8       STORE_NAME                      2: __qualname__
                        10      LOAD_NAME                       3: Mono
                        12      LOAD_ATTR                       4: OFF
                        22      STORE_NAME                      5: PlayOff
                        24      LOAD_NAME                       3: Mono
                        26      LOAD_ATTR                       6: ON
                        36      STORE_NAME                      7: PlayOn
                        38      LOAD_NAME                       3: Mono
                        40      LOAD_ATTR                       4: OFF
                        50      STORE_NAME                      8: ContinueOff
                        52      LOAD_NAME                       3: Mono
                        54      LOAD_ATTR                       9: HALF
                        64      STORE_NAME                      10: ContinueOn
                        66      LOAD_NAME                       3: Mono
                        68      LOAD_ATTR                       4: OFF
                        78      STORE_NAME                      11: CaptureOff
                        80      LOAD_NAME                       3: Mono
                        82      LOAD_ATTR                       9: HALF
                        92      STORE_NAME                      12: CaptureOn
                        94      LOAD_NAME                       13: Rgb
                        96      LOAD_ATTR                       14: RED_HALF
                        106     STORE_NAME                      15: MetronomeOff
                        108     LOAD_NAME                       13: Rgb
                        110     LOAD_ATTR                       16: AQUA
                        120     STORE_NAME                      17: MetronomeOn
                        122     LOAD_CONST                      1: None
                        124     RETURN_VALUE                    
                'Transport'
                [Code]
                    File Name: output/Live/mac_universal_64_static/Release/python-bundle/MIDI Remote Scripts/novation/skin.py
                    Object Name: Action
                    Qualified Name: Colors.Action
                    Arg Count: 0
                    Pos Only Arg Count: 0
                    KW Only Arg Count: 0
                    Stack Size: 1
                    Flags: 0x00000000
                    [Names]
                        '__name__'
                        '__module__'
                        '__qualname__'
                        'Rgb'
                        'CREAM'
                        'Undo'
                        'WHITE'
                        'UndoPressed'
                        'Redo'
                        'RedoPressed'
                        'WHITE_HALF'
                        'Delete'
                        'DeletePressed'
                        'Duplicate'
                        'DuplicatePressed'
                        'Quantize'
                        'QuantizePressed'
                        'Double'
                        'DoublePressed'
                    [Locals+Names]
                    [Constants]
                        'Colors.Action'
                        None
                    [Disassembly]
                        0       RESUME                          0
                        2       LOAD_NAME                       0: __name__
                        4       STORE_NAME                      1: __module__
                        6       LOAD_CONST                      0: 'Colors.Action'
                        8       STORE_NAME                      2: __qualname__
                        10      LOAD_NAME                       3: Rgb
                        12      LOAD_ATTR                       4: CREAM
                        22      STORE_NAME                      5: Undo
                        24      LOAD_NAME                       3: Rgb
                        26      LOAD_ATTR                       6: WHITE
                        36      STORE_NAME                      7: UndoPressed
                        38      LOAD_NAME                       3: Rgb
                        40      LOAD_ATTR                       4: CREAM
                        50      STORE_NAME                      8: Redo
                        52      LOAD_NAME                       3: Rgb
                        54      LOAD_ATTR                       6: WHITE
                        64      STORE_NAME                      9: RedoPressed
                        66      LOAD_NAME                       3: Rgb
                        68      LOAD_ATTR                       10: WHITE_HALF
                        78      STORE_NAME                      11: Delete
                        80      LOAD_NAME                       3: Rgb
                        82      LOAD_ATTR                       6: WHITE
                        92      STORE_NAME                      12: DeletePressed
                        94      LOAD_NAME                       3: Rgb
                        96      LOAD_ATTR                       10: WHITE_HALF
                        106     STORE_NAME                      13: Duplicate
                        108     LOAD_NAME                       3: Rgb
                        110     LOAD_ATTR                       6: WHITE
                        120     STORE_NAME                      14: DuplicatePressed
                        122     LOAD_NAME                       3: Rgb
                        124     LOAD_ATTR                       10: WHITE_HALF
                        134     STORE_NAME                      15: Quantize
                        136     LOAD_NAME                       3: Rgb
                        138     LOAD_ATTR                       6: WHITE
                        148     STORE_NAME                      16: QuantizePressed
                        150     LOAD_NAME                       3: Rgb
                        152     LOAD_ATTR                       4: CREAM
                        162     STORE_NAME                      17: Double
                        164     LOAD_NAME                       3: Rgb
                        166     LOAD_ATTR                       6: WHITE
                        176     STORE_NAME                      18: DoublePressed
                        178     LOAD_CONST                      1: None
                        180     RETURN_VALUE                    
                'Action'
                [Code]
                    File Name: output/Live/mac_universal_64_static/Release/python-bundle/MIDI Remote Scripts/novation/skin.py
                    Object Name: Session
                    Qualified Name: Colors.Session
                    Arg Count: 0
                    Pos Only Arg Count: 0
                    KW Only Arg Count: 0
                    Stack Size: 1
                    Flags: 0x00000000
                    [Names]
                        '__name__'
                        '__module__'
                        '__qualname__'
                        'Rgb'
                        'RED_HALF'
                        'RecordButton'
                        'GREEN_BLINK'
                        'ClipTriggeredPlay'
                        'RED_BLINK'
                        'ClipTriggeredRecord'
                        'GREEN_PULSE'
                        'ClipStarted'
                        'RED_PULSE'
                        'ClipRecording'
                        'BLACK'
                        'ClipEmpty'
                        'Scene'
                        'SceneTriggered'
                        'NoScene'
                        'StopClipTriggered'
                        'RED'
                        'StopClip'
                        'StopClipDisabled'
                        'WHITE_HALF'
                        'Navigation'
                        'WHITE'
                        'NavigationPressed'
                        'Select'
                        'SelectPressed'
                        'Delete'
                        'DeletePressed'
                        'Duplicate'
                        'DuplicatePressed'
                        'Quantize'
                        'QuantizePressed'
                        'CREAM'
                        'Double'
                        'DoublePressed'
                        'ActionTriggered'
                    [Locals+Names]
                    [Constants]
                        'Colors.Session'
                        None
                    [Disassembly]
                        0       RESUME                          0
                        2       LOAD_NAME                       0: __name__
                        4       STORE_NAME                      1: __module__
                        6       LOAD_CONST                      0: 'Colors.Session'
                        8       STORE_NAME                      2: __qualname__
                        10      LOAD_NAME                       3: Rgb
                        12      LOAD_ATTR                       4: RED_HALF
                        22      STORE_NAME                      5: RecordButton
                        24      LOAD_NAME                       3: Rgb
                        26      LOAD_ATTR                       6: GREEN_BLINK
                        36      STORE_NAME                      7: ClipTriggeredPlay
                        38      LOAD_NAME                       3: Rgb
                        40      LOAD_ATTR                       8: RED_BLINK
                        50      STORE_NAME                      9: ClipTriggeredRecord
                        52      LOAD_NAME                       3: Rgb
                        54      LOAD_ATTR                       10: GREEN_PULSE
                        64      STORE_NAME                      11: ClipStarted
                        66      LOAD_NAME                       3: Rgb
                        68      LOAD_ATTR                       12: RED_PULSE
                        78      STORE_NAME                      13: ClipRecording
                        80      LOAD_NAME                       3: Rgb
                        82      LOAD_ATTR                       14: BLACK
                        92      STORE_NAME                      15: ClipEmpty
                        94      LOAD_NAME                       3: Rgb
                        96      LOAD_ATTR                       14: BLACK
                        106     STORE_NAME                      16: Scene
                        108     LOAD_NAME                       3: Rgb
                        110     LOAD_ATTR                       6: GREEN_BLINK
                        120     STORE_NAME                      17: SceneTriggered
                        122     LOAD_NAME                       3: Rgb
                        124     LOAD_ATTR                       14: BLACK
                        134     STORE_NAME                      18: NoScene
                        136     LOAD_NAME                       3: Rgb
                        138     LOAD_ATTR                       8: RED_BLINK
                        148     STORE_NAME                      19: StopClipTriggered
                        150     LOAD_NAME                       3: Rgb
                        152     LOAD_ATTR                       20: RED
                        162     STORE_NAME                      21: StopClip
                        164     LOAD_NAME                       3: Rgb
                        166     LOAD_ATTR                       4: RED_HALF
                        176     STORE_NAME                      22: StopClipDisabled
                        178     LOAD_NAME                       3: Rgb
                        180     LOAD_ATTR                       23: WHITE_HALF
                        190     STORE_NAME                      24: Navigation
                        192     LOAD_NAME                       3: Rgb
                        194     LOAD_ATTR                       25: WHITE
                        204     STORE_NAME                      26: NavigationPressed
                        206     LOAD_NAME                       3: Rgb
                        208     LOAD_ATTR                       23: WHITE_HALF
                        218     STORE_NAME                      27: Select
                        220     LOAD_NAME                       3: Rgb
                        222     LOAD_ATTR                       25: WHITE
                        232     STORE_NAME                      28: SelectPressed
                        234     LOAD_NAME                       3: Rgb
                        236     LOAD_ATTR                       23: WHITE_HALF
                        246     STORE_NAME                      29: Delete
                        248     LOAD_NAME                       3: Rgb
                        250     LOAD_ATTR                       25: WHITE
                        260     STORE_NAME                      30: DeletePressed
                        262     LOAD_NAME                       3: Rgb
                        264     LOAD_ATTR                       23: WHITE_HALF
                        274     STORE_NAME                      31: Duplicate
                        276     LOAD_NAME                       3: Rgb
                        278     LOAD_ATTR                       25: WHITE
                        288     STORE_NAME                      32: DuplicatePressed
                        290     LOAD_NAME                       3: Rgb
                        292     LOAD_ATTR                       23: WHITE_HALF
                        302     STORE_NAME                      33: Quantize
                        304     LOAD_NAME                       3: Rgb
                        306     LOAD_ATTR                       25: WHITE
                        316     STORE_NAME                      34: QuantizePressed
                        318     LOAD_NAME                       3: Rgb
                        320     LOAD_ATTR                       35: CREAM
                        330     STORE_NAME                      36: Double
                        332     LOAD_NAME                       3: Rgb
                        334     LOAD_ATTR                       25: WHITE
                        344     STORE_NAME                      37: DoublePressed
                        346     LOAD_NAME                       3: Rgb
                        348     LOAD_ATTR                       25: WHITE
                        358     STORE_NAME                      38: ActionTriggered
                        360     LOAD_CONST                      1: None
                        362     RETURN_VALUE                    
                'Session'
                [Code]
                    File Name: output/Live/mac_universal_64_static/Release/python-bundle/MIDI Remote Scripts/novation/skin.py
                    Object Name: Zooming
                    Qualified Name: Colors.Zooming
                    Arg Count: 0
                    Pos Only Arg Count: 0
                    KW Only Arg Count: 0
                    Stack Size: 1
                    Flags: 0x00000000
                    [Names]
                        '__name__'
                        '__module__'
                        '__qualname__'
                        'Rgb'
                        'OFF_WHITE'
                        'Selected'
                        'LIGHT_BLUE_HALF'
                        'Stopped'
                        'GREEN_PULSE'
                        'Playing'
                        'BLACK'
                        'Empty'
                    [Locals+Names]
                    [Constants]
                        'Colors.Zooming'
                        None
                    [Disassembly]
                        0       RESUME                          0
                        2       LOAD_NAME                       0: __name__
                        4       STORE_NAME                      1: __module__
                        6       LOAD_CONST                      0: 'Colors.Zooming'
                        8       STORE_NAME                      2: __qualname__
                        10      LOAD_NAME                       3: Rgb
                        12      LOAD_ATTR                       4: OFF_WHITE
                        22      STORE_NAME                      5: Selected
                        24      LOAD_NAME                       3: Rgb
                        26      LOAD_ATTR                       6: LIGHT_BLUE_HALF
                        36      STORE_NAME                      7: Stopped
                        38      LOAD_NAME                       3: Rgb
                        40      LOAD_ATTR                       8: GREEN_PULSE
                        50      STORE_NAME                      9: Playing
                        52      LOAD_NAME                       3: Rgb
                        54      LOAD_ATTR                       10: BLACK
                        64      STORE_NAME                      11: Empty
                        66      LOAD_CONST                      1: None
                        68      RETURN_VALUE                    
                'Zooming'
                [Code]
                    File Name: output/Live/mac_universal_64_static/Release/python-bundle/MIDI Remote Scripts/novation/skin.py
                    Object Name: Mixer
                    Qualified Name: Colors.Mixer
                    Arg Count: 0
                    Pos Only Arg Count: 0
                    KW Only Arg Count: 0
                    Stack Size: 1
                    Flags: 0x00000000
                    [Names]
                        '__name__'
                        '__module__'
                        '__qualname__'
                        'Rgb'
                        'BLUE'
                        'SoloOn'
                        'BLUE_HALF'
                        'SoloOff'
                        'YELLOW_HALF'
                        'MuteOn'
                        'YELLOW'
                        'MuteOff'
                        'RED'
                        'ArmOn'
                        'RED_HALF'
                        'ArmOff'
                        'BLACK'
                        'EmptyTrack'
                        'WHITE'
                        'TrackSelected'
                        'WHITE_HALF'
                        'TrackNotSelected'
                    [Locals+Names]
                    [Constants]
                        'Colors.Mixer'
                        None
                    [Disassembly]
                        0       RESUME                          0
                        2       LOAD_NAME                       0: __name__
                        4       STORE_NAME                      1: __module__
                        6       LOAD_CONST                      0: 'Colors.Mixer'
                        8       STORE_NAME                      2: __qualname__
                        10      LOAD_NAME                       3: Rgb
                        12      LOAD_ATTR                       4: BLUE
                        22      STORE_NAME                      5: SoloOn
                        24      LOAD_NAME                       3: Rgb
                        26      LOAD_ATTR                       6: BLUE_HALF
                        36      STORE_NAME                      7: SoloOff
                        38      LOAD_NAME                       3: Rgb
                        40      LOAD_ATTR                       8: YELLOW_HALF
                        50      STORE_NAME                      9: MuteOn
                        52      LOAD_NAME                       3: Rgb
                        54      LOAD_ATTR                       10: YELLOW
                        64      STORE_NAME                      11: MuteOff
                        66      LOAD_NAME                       3: Rgb
                        68      LOAD_ATTR                       12: RED
                        78      STORE_NAME                      13: ArmOn
                        80      LOAD_NAME                       3: Rgb
                        82      LOAD_ATTR                       14: RED_HALF
                        92      STORE_NAME                      15: ArmOff
                        94      LOAD_NAME                       3: Rgb
                        96      LOAD_ATTR                       16: BLACK
                        106     STORE_NAME                      17: EmptyTrack
                        108     LOAD_NAME                       3: Rgb
                        110     LOAD_ATTR                       18: WHITE
                        120     STORE_NAME                      19: TrackSelected
                        122     LOAD_NAME                       3: Rgb
                        124     LOAD_ATTR                       20: WHITE_HALF
                        134     STORE_NAME                      21: TrackNotSelected
                        136     LOAD_CONST                      1: None
                        138     RETURN_VALUE                    
                'Mixer'
                [Code]
                    File Name: output/Live/mac_universal_64_static/Release/python-bundle/MIDI Remote Scripts/novation/skin.py
                    Object Name: DrumGroup
                    Qualified Name: Colors.DrumGroup
                    Arg Count: 0
                    Pos Only Arg Count: 0
                    KW Only Arg Count: 0
                    Stack Size: 1
                    Flags: 0x00000000
                    [Names]
                        '__name__'
                        '__module__'
                        '__qualname__'
                        'Rgb'
                        'BLACK'
                        'PadEmpty'
                        'YELLOW'
                        'PadFilled'
                        'LIGHT_BLUE'
                        'PadSelected'
                        'PadSelectedNotSoloed'
                        'DARK_ORANGE'
                        'PadMuted'
                        'PadMutedSelected'
                        'DARK_BLUE'
                        'PadSoloed'
                        'PadSoloedSelected'
                        'WHITE'
                        'PadAction'
                        'YELLOW_HALF'
                        'Navigation'
                        'NavigationPressed'
                    [Locals+Names]
                    [Constants]
                        'Colors.DrumGroup'
                        None
                    [Disassembly]
                        0       RESUME                          0
                        2       LOAD_NAME                       0: __name__
                        4       STORE_NAME                      1: __module__
                        6       LOAD_CONST                      0: 'Colors.DrumGroup'
                        8       STORE_NAME                      2: __qualname__
                        10      LOAD_NAME                       3: Rgb
                        12      LOAD_ATTR                       4: BLACK
                        22      STORE_NAME                      5: PadEmpty
                        24      LOAD_NAME                       3: Rgb
                        26      LOAD_ATTR                       6: YELLOW
                        36      STORE_NAME                      7: PadFilled
                        38      LOAD_NAME                       3: Rgb
                        40      LOAD_ATTR                       8: LIGHT_BLUE
                        50      STORE_NAME                      9: PadSelected
                        52      LOAD_NAME                       3: Rgb
                        54      LOAD_ATTR                       8: LIGHT_BLUE
                        64      STORE_NAME                      10: PadSelectedNotSoloed
                        66      LOAD_NAME                       3: Rgb
                        68      LOAD_ATTR                       11: DARK_ORANGE
                        78      STORE_NAME                      12: PadMuted
                        80      LOAD_NAME                       3: Rgb
                        82      LOAD_ATTR                       8: LIGHT_BLUE
                        92      STORE_NAME                      13: PadMutedSelected
                        94      LOAD_NAME                       3: Rgb
                        96      LOAD_ATTR                       14: DARK_BLUE
                        106     STORE_NAME                      15: PadSoloed
                        108     LOAD_NAME                       3: Rgb
                        110     LOAD_ATTR                       8: LIGHT_BLUE
                        120     STORE_NAME                      16: PadSoloedSelected
                        122     LOAD_NAME                       3: Rgb
                        124     LOAD_ATTR                       17: WHITE
                        134     STORE_NAME                      18: PadAction
                        136     LOAD_NAME                       3: Rgb
                        138     LOAD_ATTR                       19: YELLOW_HALF
                        148     STORE_NAME                      20: Navigation
                        150     LOAD_NAME                       3: Rgb
                        152     LOAD_ATTR                       6: YELLOW
                        162     STORE_NAME                      21: NavigationPressed
                        164     LOAD_CONST                      1: None
                        166     RETURN_VALUE                    
                'DrumGroup'
                [Code]
                    File Name: output/Live/mac_universal_64_static/Release/python-bundle/MIDI Remote Scripts/novation/skin.py
                    Object Name: Mode
                    Qualified Name: Colors.Mode
                    Arg Count: 0
                    Pos Only Arg Count: 0
                    KW Only Arg Count: 0
                    Stack Size: 5
                    Flags: 0x00000000
                    [Names]
                        '__name__'
                        '__module__'
                        '__qualname__'
                        'object'
                        'Volume'
                        'Pan'
                        'SendA'
                        'SendB'
                        'Stop'
                        'Mute'
                        'Solo'
                        'Arm'
                        'Launch'
                    [Locals+Names]
                    [Constants]
                        'Colors.Mode'
                        [Code]
                            File Name: output/Live/mac_universal_64_static/Release/python-bundle/MIDI Remote Scripts/novation/skin.py
                            Object Name: Volume
                            Qualified Name: Colors.Mode.Volume
                            Arg Count: 0
                            Pos Only Arg Count: 0
                            KW Only Arg Count: 0
                            Stack Size: 1
                            Flags: 0x00000000
                            [Names]
                                '__name__'
                                '__module__'
                                '__qualname__'
                                'Rgb'
                                'GREEN'
                                'On'
                                'WHITE_HALF'
                                'Off'
                            [Locals+Names]
                            [Constants]
                                'Colors.Mode.Volume'
                                None
                            [Disassembly]
                                0       RESUME                          0
                                2       LOAD_NAME                       0: __name__
                                4       STORE_NAME                      1: __module__
                                6       LOAD_CONST                      0: 'Colors.Mode.Volume'
                                8       STORE_NAME                      2: __qualname__
                                10      LOAD_NAME                       3: Rgb
                                12      LOAD_ATTR                       4: GREEN
                                22      STORE_NAME                      5: On
                                24      LOAD_NAME                       3: Rgb
                                26      LOAD_ATTR                       6: WHITE_HALF
                                36      STORE_NAME                      7: Off
                                38      LOAD_CONST                      1: None
                                40      RETURN_VALUE                    
                        'Volume'
                        [Code]
                            File Name: output/Live/mac_universal_64_static/Release/python-bundle/MIDI Remote Scripts/novation/skin.py
                            Object Name: Pan
                            Qualified Name: Colors.Mode.Pan
                            Arg Count: 0
                            Pos Only Arg Count: 0
                            KW Only Arg Count: 0
                            Stack Size: 1
                            Flags: 0x00000000
                            [Names]
                                '__name__'
                                '__module__'
                                '__qualname__'
                                'Rgb'
                                'ORANGE'
                                'On'
                                'WHITE_HALF'
                                'Off'
                            [Locals+Names]
                            [Constants]
                                'Colors.Mode.Pan'
                                None
                            [Disassembly]
                                0       RESUME                          0
                                2       LOAD_NAME                       0: __name__
                                4       STORE_NAME                      1: __module__
                                6       LOAD_CONST                      0: 'Colors.Mode.Pan'
                                8       STORE_NAME                      2: __qualname__
                                10      LOAD_NAME                       3: Rgb
                                12      LOAD_ATTR                       4: ORANGE
                                22      STORE_NAME                      5: On
                                24      LOAD_NAME                       3: Rgb
                                26      LOAD_ATTR                       6: WHITE_HALF
                                36      STORE_NAME                      7: Off
                                38      LOAD_CONST                      1: None
                                40      RETURN_VALUE                    
                        'Pan'
                        [Code]
                            File Name: output/Live/mac_universal_64_static/Release/python-bundle/MIDI Remote Scripts/novation/skin.py
                            Object Name: SendA
                            Qualified Name: Colors.Mode.SendA
                            Arg Count: 0
                            Pos Only Arg Count: 0
                            KW Only Arg Count: 0
                            Stack Size: 1
                            Flags: 0x00000000
                            [Names]
                                '__name__'
                                '__module__'
                                '__qualname__'
                                'Rgb'
                                'VIOLET'
                                'On'
                                'WHITE_HALF'
                                'Off'
                            [Locals+Names]
                            [Constants]
                                'Colors.Mode.SendA'
                                None
                            [Disassembly]
                                0       RESUME                          0
                                2       LOAD_NAME                       0: __name__
                                4       STORE_NAME                      1: __module__
                                6       LOAD_CONST                      0: 'Colors.Mode.SendA'
                                8       STORE_NAME                      2: __qualname__
                                10      LOAD_NAME                       3: Rgb
                                12      LOAD_ATTR                       4: VIOLET
                                22      STORE_NAME                      5: On
                                24      LOAD_NAME                       3: Rgb
                                26      LOAD_ATTR                       6: WHITE_HALF
                                36      STORE_NAME                      7: Off
                                38      LOAD_CONST                      1: None
                                40      RETURN_VALUE                    
                        'SendA'
                        [Code]
                            File Name: output/Live/mac_universal_64_static/Release/python-bundle/MIDI Remote Scripts/novation/skin.py
                            Object Name: SendB
                            Qualified Name: Colors.Mode.SendB
                            Arg Count: 0
                            Pos Only Arg Count: 0
                            KW Only Arg Count: 0
                            Stack Size: 1
                            Flags: 0x00000000
                            [Names]
                                '__name__'
                                '__module__'
                                '__qualname__'
                                'Rgb'
                                'DARK_BLUE'
                                'On'
                                'WHITE_HALF'
                                'Off'
                            [Locals+Names]
                            [Constants]
                                'Colors.Mode.SendB'
                                None
                            [Disassembly]
                                0       RESUME                          0
                                2       LOAD_NAME                       0: __name__
                                4       STORE_NAME                      1: __module__
                                6       LOAD_CONST                      0: 'Colors.Mode.SendB'
                                8       STORE_NAME                      2: __qualname__
                                10      LOAD_NAME                       3: Rgb
                                12      LOAD_ATTR                       4: DARK_BLUE
                                22      STORE_NAME                      5: On
                                24      LOAD_NAME                       3: Rgb
                                26      LOAD_ATTR                       6: WHITE_HALF
                                36      STORE_NAME                      7: Off
                                38      LOAD_CONST                      1: None
                                40      RETURN_VALUE                    
                        'SendB'
                        [Code]
                            File Name: output/Live/mac_universal_64_static/Release/python-bundle/MIDI Remote Scripts/novation/skin.py
                            Object Name: Stop
                            Qualified Name: Colors.Mode.Stop
                            Arg Count: 0
                            Pos Only Arg Count: 0
                            KW Only Arg Count: 0
                            Stack Size: 1
                            Flags: 0x00000000
                            [Names]
                                '__name__'
                                '__module__'
                                '__qualname__'
                                'Rgb'
                                'RED'
                                'On'
                                'WHITE_HALF'
                                'Off'
                            [Locals+Names]
                            [Constants]
                                'Colors.Mode.Stop'
                                None
                            [Disassembly]
                                0       RESUME                          0
                                2       LOAD_NAME                       0: __name__
                                4       STORE_NAME                      1: __module__
                                6       LOAD_CONST                      0: 'Colors.Mode.Stop'
                                8       STORE_NAME                      2: __qualname__
                                10      LOAD_NAME                       3: Rgb
                                12      LOAD_ATTR                       4: RED
                                22      STORE_NAME                      5: On
                                24      LOAD_NAME                       3: Rgb
                                26      LOAD_ATTR                       6: WHITE_HALF
                                36      STORE_NAME                      7: Off
                                38      LOAD_CONST                      1: None
                                40      RETURN_VALUE                    
                        'Stop'
                        [Code]
                            File Name: output/Live/mac_universal_64_static/Release/python-bundle/MIDI Remote Scripts/novation/skin.py
                            Object Name: Mute
                            Qualified Name: Colors.Mode.Mute
                            Arg Count: 0
                            Pos Only Arg Count: 0
                            KW Only Arg Count: 0
                            Stack Size: 1
                            Flags: 0x00000000
                            [Names]
                                '__name__'
                                '__module__'
                                '__qualname__'
                                'Rgb'
                                'YELLOW'
                                'On'
                                'WHITE_HALF'
                                'Off'
                            [Locals+Names]
                            [Constants]
                                'Colors.Mode.Mute'
                                None
                            [Disassembly]
                                0       RESUME                          0
                                2       LOAD_NAME                       0: __name__
                                4       STORE_NAME                      1: __module__
                                6       LOAD_CONST                      0: 'Colors.Mode.Mute'
                                8       STORE_NAME                      2: __qualname__
                                10      LOAD_NAME                       3: Rgb
                                12      LOAD_ATTR                       4: YELLOW
                                22      STORE_NAME                      5: On
                                24      LOAD_NAME                       3: Rgb
                                26      LOAD_ATTR                       6: WHITE_HALF
                                36      STORE_NAME                      7: Off
                                38      LOAD_CONST                      1: None
                                40      RETURN_VALUE                    
                        'Mute'
                        [Code]
                            File Name: output/Live/mac_universal_64_static/Release/python-bundle/MIDI Remote Scripts/novation/skin.py
                            Object Name: Solo
                            Qualified Name: Colors.Mode.Solo
                            Arg Count: 0
                            Pos Only Arg Count: 0
                            KW Only Arg Count: 0
                            Stack Size: 1
                            Flags: 0x00000000
                            [Names]
                                '__name__'
                                '__module__'
                                '__qualname__'
                                'Rgb'
                                'BLUE'
                                'On'
                                'WHITE_HALF'
                                'Off'
                            [Locals+Names]
                            [Constants]
                                'Colors.Mode.Solo'
                                None
                            [Disassembly]
                                0       RESUME                          0
                                2       LOAD_NAME                       0: __name__
                                4       STORE_NAME                      1: __module__
                                6       LOAD_CONST                      0: 'Colors.Mode.Solo'
                                8       STORE_NAME                      2: __qualname__
                                10      LOAD_NAME                       3: Rgb
                                12      LOAD_ATTR                       4: BLUE
                                22      STORE_NAME                      5: On
                                24      LOAD_NAME                       3: Rgb
                                26      LOAD_ATTR                       6: WHITE_HALF
                                36      STORE_NAME                      7: Off
                                38      LOAD_CONST                      1: None
                                40      RETURN_VALUE                    
                        'Solo'
                        [Code]
                            File Name: output/Live/mac_universal_64_static/Release/python-bundle/MIDI Remote Scripts/novation/skin.py
                            Object Name: Arm
                            Qualified Name: Colors.Mode.Arm
                            Arg Count: 0
                            Pos Only Arg Count: 0
                            KW Only Arg Count: 0
                            Stack Size: 1
                            Flags: 0x00000000
                            [Names]
                                '__name__'
                                '__module__'
                                '__qualname__'
                                'Rgb'
                                'RED'
                                'On'
                                'WHITE_HALF'
                                'Off'
                            [Locals+Names]
                            [Constants]
                                'Colors.Mode.Arm'
                                None
                            [Disassembly]
                                0       RESUME                          0
                                2       LOAD_NAME                       0: __name__
                                4       STORE_NAME                      1: __module__
                                6       LOAD_CONST                      0: 'Colors.Mode.Arm'
                                8       STORE_NAME                      2: __qualname__
                                10      LOAD_NAME                       3: Rgb
                                12      LOAD_ATTR                       4: RED
                                22      STORE_NAME                      5: On
                                24      LOAD_NAME                       3: Rgb
                                26      LOAD_ATTR                       6: WHITE_HALF
                                36      STORE_NAME                      7: Off
                                38      LOAD_CONST                      1: None
                                40      RETURN_VALUE                    
                        'Arm'
                        [Code]
                            File Name: output/Live/mac_universal_64_static/Release/python-bundle/MIDI Remote Scripts/novation/skin.py
                            Object Name: Launch
                            Qualified Name: Colors.Mode.Launch
                            Arg Count: 0
                            Pos Only Arg Count: 0
                            KW Only Arg Count: 0
                            Stack Size: 1
                            Flags: 0x00000000
                            [Names]
                                '__name__'
                                '__module__'
                                '__qualname__'
                                'Rgb'
                                'WHITE_HALF'
                                'On'
                            [Locals+Names]
                            [Constants]
                                'Colors.Mode.Launch'
                                None
                            [Disassembly]
                                0       RESUME                          0
                                2       LOAD_NAME                       0: __name__
                                4       STORE_NAME                      1: __module__
                                6       LOAD_CONST                      0: 'Colors.Mode.Launch'
                                8       STORE_NAME                      2: __qualname__
                                10      LOAD_NAME                       3: Rgb
                                12      LOAD_ATTR                       4: WHITE_HALF
                                22      STORE_NAME                      5: On
                                24      LOAD_CONST                      1: None
                                26      RETURN_VALUE                    
                        'Launch'
                        None
                    [Disassembly]
                        0       RESUME                          0
                        2       LOAD_NAME                       0: __name__
                        4       STORE_NAME                      1: __module__
                        6       LOAD_CONST                      0: 'Colors.Mode'
                        8       STORE_NAME                      2: __qualname__
                        10      PUSH_NULL                       
                        12      LOAD_BUILD_CLASS                
                        14      LOAD_CONST                      1: <CODE> Volume
                        16      MAKE_FUNCTION                   0
                        18      LOAD_CONST                      2: 'Volume'
                        20      LOAD_NAME                       3: object
                        22      PRECALL                         3
                        26      CALL                            3
                        36      STORE_NAME                      4: Volume
                        38      PUSH_NULL                       
                        40      LOAD_BUILD_CLASS                
                        42      LOAD_CONST                      3: <CODE> Pan
                        44      MAKE_FUNCTION                   0
                        46      LOAD_CONST                      4: 'Pan'
                        48      LOAD_NAME                       3: object
                        50      PRECALL                         3
                        54      CALL                            3
                        64      STORE_NAME                      5: Pan
                        66      PUSH_NULL                       
                        68      LOAD_BUILD_CLASS                
                        70      LOAD_CONST                      5: <CODE> SendA
                        72      MAKE_FUNCTION                   0
                        74      LOAD_CONST                      6: 'SendA'
                        76      LOAD_NAME                       3: object
                        78      PRECALL                         3
                        82      CALL                            3
                        92      STORE_NAME                      6: SendA
                        94      PUSH_NULL                       
                        96      LOAD_BUILD_CLASS                
                        98      LOAD_CONST                      7: <CODE> SendB
                        100     MAKE_FUNCTION                   0
                        102     LOAD_CONST                      8: 'SendB'
                        104     LOAD_NAME                       3: object
                        106     PRECALL                         3
                        110     CALL                            3
                        120     STORE_NAME                      7: SendB
                        122     PUSH_NULL                       
                        124     LOAD_BUILD_CLASS                
                        126     LOAD_CONST                      9: <CODE> Stop
                        128     MAKE_FUNCTION                   0
                        130     LOAD_CONST                      10: 'Stop'
                        132     LOAD_NAME                       3: object
                        134     PRECALL                         3
                        138     CALL                            3
                        148     STORE_NAME                      8: Stop
                        150     PUSH_NULL                       
                        152     LOAD_BUILD_CLASS                
                        154     LOAD_CONST                      11: <CODE> Mute
                        156     MAKE_FUNCTION                   0
                        158     LOAD_CONST                      12: 'Mute'
                        160     LOAD_NAME                       3: object
                        162     PRECALL                         3
                        166     CALL                            3
                        176     STORE_NAME                      9: Mute
                        178     PUSH_NULL                       
                        180     LOAD_BUILD_CLASS                
                        182     LOAD_CONST                      13: <CODE> Solo
                        184     MAKE_FUNCTION                   0
                        186     LOAD_CONST                      14: 'Solo'
                        188     LOAD_NAME                       3: object
                        190     PRECALL                         3
                        194     CALL                            3
                        204     STORE_NAME                      10: Solo
                        206     PUSH_NULL                       
                        208     LOAD_BUILD_CLASS                
                        210     LOAD_CONST                      15: <CODE> Arm
                        212     MAKE_FUNCTION                   0
                        214     LOAD_CONST                      16: 'Arm'
                        216     LOAD_NAME                       3: object
                        218     PRECALL                         3
                        222     CALL                            3
                        232     STORE_NAME                      11: Arm
                        234     PUSH_NULL                       
                        236     LOAD_BUILD_CLASS                
                        238     LOAD_CONST                      17: <CODE> Launch
                        240     MAKE_FUNCTION                   0
                        242     LOAD_CONST                      18: 'Launch'
                        244     LOAD_NAME                       3: object
                        246     PRECALL                         3
                        250     CALL                            3
                        260     STORE_NAME                      12: Launch
                        262     LOAD_CONST                      19: None
                        264     RETURN_VALUE                    
                'Mode'
                None
            [Disassembly]
                0       RESUME                          0
                2       LOAD_NAME                       0: __name__
                4       STORE_NAME                      1: __module__
                6       LOAD_CONST                      0: 'Colors'
                8       STORE_NAME                      2: __qualname__
                10      PUSH_NULL                       
                12      LOAD_BUILD_CLASS                
                14      LOAD_CONST                      1: <CODE> DefaultButton
                16      MAKE_FUNCTION                   0
                18      LOAD_CONST                      2: 'DefaultButton'
                20      LOAD_NAME                       3: object
                22      PRECALL                         3
                26      CALL                            3
                36      STORE_NAME                      4: DefaultButton
                38      PUSH_NULL                       
                40      LOAD_BUILD_CLASS                
                42      LOAD_CONST                      3: <CODE> Recording
                44      MAKE_FUNCTION                   0
                46      LOAD_CONST                      4: 'Recording'
                48      LOAD_NAME                       3: object
                50      PRECALL                         3
                54      CALL                            3
                64      STORE_NAME                      5: Recording
                66      PUSH_NULL                       
                68      LOAD_BUILD_CLASS                
                70      LOAD_CONST                      5: <CODE> FixedLength
                72      MAKE_FUNCTION                   0
                74      LOAD_CONST                      6: 'FixedLength'
                76      LOAD_NAME                       3: object
                78      PRECALL                         3
                82      CALL                            3
                92      STORE_NAME                      6: FixedLength
                94      PUSH_NULL                       
                96      LOAD_BUILD_CLASS                
                98      LOAD_CONST                      7: <CODE> Transport
                100     MAKE_FUNCTION                   0
                102     LOAD_CONST                      8: 'Transport'
                104     LOAD_NAME                       3: object
                106     PRECALL                         3
                110     CALL                            3
                120     STORE_NAME                      7: Transport
                122     PUSH_NULL                       
                124     LOAD_BUILD_CLASS                
                126     LOAD_CONST                      9: <CODE> Action
                128     MAKE_FUNCTION                   0
                130     LOAD_CONST                      10: 'Action'
                132     LOAD_NAME                       3: object
                134     PRECALL                         3
                138     CALL                            3
                148     STORE_NAME                      8: Action
                150     PUSH_NULL                       
                152     LOAD_BUILD_CLASS                
                154     LOAD_CONST                      11: <CODE> Session
                156     MAKE_FUNCTION                   0
                158     LOAD_CONST                      12: 'Session'
                160     LOAD_NAME                       3: object
                162     PRECALL                         3
                166     CALL                            3
                176     STORE_NAME                      9: Session
                178     PUSH_NULL                       
                180     LOAD_BUILD_CLASS                
                182     LOAD_CONST                      13: <CODE> Zooming
                184     MAKE_FUNCTION                   0
                186     LOAD_CONST                      14: 'Zooming'
                188     LOAD_NAME                       3: object
                190     PRECALL                         3
                194     CALL                            3
                204     STORE_NAME                      10: Zooming
                206     PUSH_NULL                       
                208     LOAD_BUILD_CLASS                
                210     LOAD_CONST                      15: <CODE> Mixer
                212     MAKE_FUNCTION                   0
                214     LOAD_CONST                      16: 'Mixer'
                216     LOAD_NAME                       3: object
                218     PRECALL                         3
                222     CALL                            3
                232     STORE_NAME                      11: Mixer
                234     PUSH_NULL                       
                236     LOAD_BUILD_CLASS                
                238     LOAD_CONST                      17: <CODE> DrumGroup
                240     MAKE_FUNCTION                   0
                242     LOAD_CONST                      18: 'DrumGroup'
                244     LOAD_NAME                       3: object
                246     PRECALL                         3
                250     CALL                            3
                260     STORE_NAME                      12: DrumGroup
                262     PUSH_NULL                       
                264     LOAD_BUILD_CLASS                
                266     LOAD_CONST                      19: <CODE> Mode
                268     MAKE_FUNCTION                   0
                270     LOAD_CONST                      20: 'Mode'
                272     LOAD_NAME                       3: object
                274     PRECALL                         3
                278     CALL                            3
                288     STORE_NAME                      13: Mode
                290     LOAD_CONST                      21: None
                292     RETURN_VALUE                    
        'Colors'
        None
    [Disassembly]
        0       RESUME                          0
        2       LOAD_CONST                      0: 0
        4       LOAD_CONST                      1: ('Skin',)
        6       IMPORT_NAME                     0: ableton.v2.control_surface
        8       IMPORT_FROM                     1: Skin
        10      STORE_NAME                      1: Skin
        12      POP_TOP                         
        14      LOAD_CONST                      2: 1
        16      LOAD_CONST                      3: ('Mono', 'Rgb')
        18      IMPORT_NAME                     2: colors
        20      IMPORT_FROM                     3: Mono
        22      STORE_NAME                      3: Mono
        24      IMPORT_FROM                     4: Rgb
        26      STORE_NAME                      4: Rgb
        28      POP_TOP                         
        30      PUSH_NULL                       
        32      LOAD_BUILD_CLASS                
        34      LOAD_CONST                      4: <CODE> Colors
        36      MAKE_FUNCTION                   0
        38      LOAD_CONST                      5: 'Colors'
        40      LOAD_NAME                       5: object
        42      PRECALL                         3
        46      CALL                            3
        56      STORE_NAME                      6: Colors
        58      PUSH_NULL                       
        60      LOAD_NAME                       1: Skin
        62      LOAD_NAME                       6: Colors
        64      PRECALL                         1
        68      CALL                            1
        78      STORE_NAME                      7: skin
        80      LOAD_CONST                      6: None
        82      RETURN_VALUE                    
